{
  "type": "Feature",
  "properties": {
    "gn:admin1_code":"65.0",
    "gn:asciiname":"Toceni",
    "gn:country_code":"MD",
    "gn:dem":59,
    "gn:feature_class":"P",
    "gn:feature_code":"PPL",
    "gn:name":"Toceni",
    "gn:population":0,
    "gn:timezone":"Europe/Chisinau",
    "iso:country":"MD",
    "name:rus_x_preferred":[
        "\u0422\u043e\u0447\u0435\u043d\u044b"
    ],
    "name:und_x_variant":[
        "Tocheny",
        "Toceni"
    ],
    "wof:name":"Toceni",
    "wof:placetype":"locality"
},
  "geometry": {"coordinates":[28.21792,46.36679],"type":"Point"}
}