{
  "type": "Feature",
  "properties": {
    "iso:country":"MD",
    "name:arz_x_preferred":[
        "\u0627\u0634\u0646\u0648\u06a4\u0627\u062a\u0633"
    ],
    "name:ceb_x_preferred":[
        "I\u0219nov\u0103\u021b"
    ],
    "name:che_x_preferred":[
        "\u0418\u0448\u043d\u043e\u0432\u044d\u0446"
    ],
    "name:dan_x_preferred":[
        "I\u0219nov\u0103\u021b"
    ],
    "name:deu_x_preferred":[
        "I\u0219nov\u0103\u021b"
    ],
    "name:eng_x_preferred":[
        "Ishnovets"
    ],
    "name:eng_x_variant":[
        "I\u0219nov\u0103\u021b"
    ],
    "name:eus_x_preferred":[
        "I\u0219nov\u0103\u021b"
    ],
    "name:fra_x_preferred":[
        "I\u0219nov\u0103\u021b"
    ],
    "name:gle_x_preferred":[
        "I\u0219nov\u0103\u021b"
    ],
    "name:ita_x_preferred":[
        "I\u0219nov\u0103\u021b"
    ],
    "name:ita_x_variant":[
        "I\u015fnov\u0103\u0163"
    ],
    "name:kat_x_preferred":[
        "\u10d8\u10e8\u10dc\u10dd\u10d5\u10d4\u10ea\u10d8"
    ],
    "name:nld_x_preferred":[
        "I\u015fnov\u0103\u0163"
    ],
    "name:nno_x_preferred":[
        "I\u0219nov\u0103\u021b"
    ],
    "name:nob_x_preferred":[
        "I\u0219nov\u0103\u021b"
    ],
    "name:pol_x_preferred":[
        "I\u0219nov\u0103\u021b"
    ],
    "name:por_x_preferred":[
        "I\u0219nov\u0103\u021b"
    ],
    "name:ron_x_preferred":[
        "I\u0219nov\u0103\u021b"
    ],
    "name:ron_x_variant":[
        "Zamciogi"
    ],
    "name:rus_x_preferred":[
        "\u0418\u0448\u043d\u043e\u0432\u0435\u0446"
    ],
    "name:spa_x_preferred":[
        "I\u0219nov\u0103\u021b"
    ],
    "name:swe_x_preferred":[
        "I\u0219nov\u0103\u021b"
    ],
    "name:tat_x_preferred":[
        "\u0418\u0448\u043d\u043e\u0432\u044b\u0446"
    ],
    "name:ukr_x_preferred":[
        "\u0406\u0448\u043d\u043e\u0432\u0435\u0446"
    ],
    "name:und_x_colloquial":[
        "Isnovat"
    ],
    "qs:a0":"Moldova",
    "qs:a1":"*Criuleni",
    "qs:a1_alt":"Criuleni",
    "qs:a1r":"0",
    "qs:adm0":"Moldova",
    "qs:la_lc":"*",
    "qs:level":"locality",
    "qs:loc":"I\u015fnov\u0103\u0163",
    "qs:loc_alt":"Isnovat",
    "qs:pop":0,
    "qs:type":"buffered point",
    "wd:wordcount":57,
    "wof:lang":[
        "unk"
    ],
    "wof:name":"I\u015fnov\u0103\u0163",
    "wof:placetype":"locality"
},
  "geometry": {"coordinates":[28.862944,47.232754],"type":"Point"}
}