{
  "type": "Feature",
  "properties": {
    "iso:country":"MD",
    "name:ceb_x_preferred":[
        "Voinescu"
    ],
    "name:dan_x_preferred":[
        "Voinescu"
    ],
    "name:deu_x_preferred":[
        "Voinescu"
    ],
    "name:eng_x_preferred":[
        "Voynesku"
    ],
    "name:eng_x_variant":[
        "Pobeda",
        "Voynesko",
        "Voinescu"
    ],
    "name:eus_x_preferred":[
        "Voinescu"
    ],
    "name:fra_x_preferred":[
        "Voinescu"
    ],
    "name:ita_x_preferred":[
        "Voinescu"
    ],
    "name:kat_x_preferred":[
        "\u10d5\u10dd\u10d8\u10dc\u10d4\u10e1\u10d9\u10e3"
    ],
    "name:nld_x_preferred":[
        "Voinescu"
    ],
    "name:nno_x_preferred":[
        "Voinescu"
    ],
    "name:nob_x_preferred":[
        "Voinescu"
    ],
    "name:pol_x_preferred":[
        "Voinescu"
    ],
    "name:por_x_preferred":[
        "Voinescu"
    ],
    "name:ron_x_preferred":[
        "Voinescu"
    ],
    "name:rus_x_preferred":[
        "\u0412\u043e\u0439\u043d\u0435\u0441\u043a\u0443"
    ],
    "name:rus_x_variant":[
        "\u041f\u043e\u0431\u0435\u0434\u0430"
    ],
    "name:spa_x_preferred":[
        "Voinescu"
    ],
    "name:swe_x_preferred":[
        "Voinescu"
    ],
    "name:ukr_x_preferred":[
        "\u0412\u043e\u0439\u043d\u0435\u0441\u043a\u0443"
    ],
    "name:ukr_x_variant":[
        "\u0411\u043e\u043a\u0430\u043d\u044c"
    ],
    "qs:a0":"Moldova",
    "qs:a1":"*H\u00eence\u015fti",
    "qs:a1_alt":"Hincesti",
    "qs:a1r":"0",
    "qs:adm0":"Moldova",
    "qs:la_lc":"*",
    "qs:level":"locality",
    "qs:loc":"Voinescu",
    "qs:loc_alt":"Voinescu",
    "qs:pop":0,
    "qs:type":"buffered point",
    "wd:wordcount":75,
    "wof:lang":[
        "unk"
    ],
    "wof:name":"Voinescu",
    "wof:placetype":"locality"
},
  "geometry": {"coordinates":[28.301403,46.649986],"type":"Point"}
}