{
  "type": "Feature",
  "properties": {
    "gn:admin1_code":"68.0",
    "gn:asciiname":"Valea Perjei",
    "gn:country_code":"MD",
    "gn:dem":100,
    "gn:feature_class":"P",
    "gn:feature_code":"PPL",
    "gn:name":"Valea Perjei",
    "gn:population":0,
    "gn:timezone":"Europe/Chisinau",
    "iso:country":"MD",
    "name:ita_x_preferred":[
        "Valea Perjei"
    ],
    "name:ron_x_preferred":[
        "Valea Perjei"
    ],
    "name:rus_x_preferred":[
        "\u0412\u0430\u043b\u044f-\u041f\u0435\u0440\u0436\u0435\u0439"
    ],
    "name:rus_x_variant":[
        "\u0412\u0430\u043b\u044f \u041f\u0435\u0440\u0436\u0435\u0439"
    ],
    "name:ukr_x_preferred":[
        "\u0412\u0430\u043b\u044f-\u041f\u0435\u0440\u0436\u0435\u0439"
    ],
    "name:und_x_variant":[
        "Valya-Perzhiy",
        "Valya-Perzhey",
        "Valya Perzhey Noua",
        "Valea Perjii",
        "Valea Perjei"
    ],
    "wof:name":"Valea Perjei",
    "wof:placetype":"locality"
},
  "geometry": {"coordinates":[28.72297,46.62194],"type":"Point"}
}