{
  "type": "Feature",
  "properties": {
    "gn:admin1_code":"92.0",
    "gn:asciiname":"Romanovca",
    "gn:country_code":"MD",
    "gn:dem":125,
    "gn:feature_class":"P",
    "gn:feature_code":"PPL",
    "gn:name":"Romanovca",
    "gn:population":0,
    "gn:timezone":"Europe/Chisinau",
    "iso:country":"MD",
    "name:ita_x_preferred":[
        "Romanovca"
    ],
    "name:kat_x_preferred":[
        "\u10e0\u10dd\u10db\u10d0\u10dc\u10dd\u10d5\u10d9\u10d0"
    ],
    "name:ron_x_preferred":[
        "Romanovca"
    ],
    "name:rus_x_preferred":[
        "\u0420\u043e\u043c\u0430\u043d\u043e\u0432\u043a\u0430"
    ],
    "name:ukr_x_preferred":[
        "\u0420\u043e\u043c\u0430\u043d\u043e\u0432\u043a\u0430"
    ],
    "name:und_x_variant":[
        "Romynesht\u2019",
        "Romanovka",
        "Romanovca"
    ],
    "wof:name":"Romanovca",
    "wof:placetype":"locality"
},
  "geometry": {"coordinates":[27.97082,47.37468],"type":"Point"}
}