{
  "type": "Feature",
  "properties": {
    "gn:admin1_code":"91.0",
    "gn:asciiname":"Flutura",
    "gn:country_code":"MD",
    "gn:dem":161,
    "gn:feature_class":"P",
    "gn:feature_code":"PPL",
    "gn:name":"Flutura",
    "gn:population":0,
    "gn:timezone":"Europe/Chisinau",
    "iso:country":"MD",
    "name:ron_x_preferred":[
        "Flutura"
    ],
    "wof:name":"Flutura",
    "wof:placetype":"locality"
},
  "geometry": {"coordinates":[28.5475,47.68833],"type":"Point"}
}