{
  "type": "Feature",
  "properties": {
    "iso:country":"MD",
    "name:eng_x_preferred":[
        "Ketrish"
    ],
    "name:eng_x_variant":[
        "Ketrosh'",
        "Chetri\u0219"
    ],
    "name:ita_x_preferred":[
        "Chetri\u0219"
    ],
    "name:ita_x_variant":[
        "Chetri\u015f"
    ],
    "name:kat_x_preferred":[
        "\u10d9\u10d4\u10e2\u10e0\u10d8\u10e8\u10d8"
    ],
    "name:nld_x_preferred":[
        "Chetri\u015f"
    ],
    "name:ron_x_preferred":[
        "Chetri\u0219"
    ],
    "name:rus_x_preferred":[
        "\u041a\u0435\u0442\u0440\u0438\u0448"
    ],
    "name:ukr_x_preferred":[
        "\u041a\u0435\u0442\u0440\u0456\u0448"
    ],
    "name:und_x_colloquial":[
        "Chetris"
    ],
    "name:und_x_preferred":[
        "Chetri\u015f"
    ],
    "name:unk_x_variant":[
        "Ketrish"
    ],
    "qs:a0":"Moldova",
    "qs:a1":"*F\u0103le\u015fti",
    "qs:a1_alt":"Falesti",
    "qs:a1r":"0",
    "qs:adm0":"Moldova",
    "qs:la_lc":"*",
    "qs:level":"locality",
    "qs:loc":"Chetri\u015f",
    "qs:loc_alt":"Chetris",
    "qs:pop":0,
    "qs:type":"buffered point",
    "wd:wordcount":48,
    "wof:lang":[
        "unk"
    ],
    "wof:name":"Chetri\u015f",
    "wof:placetype":"locality"
},
  "geometry": {"coordinates":[27.445054,47.595352],"type":"Point"}
}