{
  "type": "Feature",
  "properties": {
    "gn:admin1_code":"75.0",
    "gn:asciiname":"Marculesti",
    "gn:country_code":"MD",
    "gn:dem":107,
    "gn:feature_class":"P",
    "gn:feature_code":"PPL",
    "gn:name":"M\u0103rcule\u015fti",
    "gn:population":0,
    "gn:timezone":"Europe/Chisinau",
    "iso:country":"MD",
    "name:rus_x_preferred":[
        "\u041c\u0430\u0440\u043a\u0443\u043b\u0435\u0448\u0442\u044b"
    ],
    "name:und_x_variant":[
        "M\u0103rcule\u015fti-Sat",
        "Markuleshti-Sat",
        "Markuleshty-Sat",
        "Markulesht\u2019-Sat",
        "M\u0103rcule\u015fti",
        "Markuleshty"
    ],
    "wof:name":"Marculesti",
    "wof:placetype":"locality"
},
  "geometry": {"coordinates":[28.24609,47.88369],"type":"Point"}
}