{
  "type": "Feature",
  "properties": {
    "gn:admin1_code":"89.0",
    "gn:asciiname":"Ghelauza",
    "gn:country_code":"MD",
    "gn:dem":131,
    "gn:feature_class":"P",
    "gn:feature_code":"PPL",
    "gn:name":"Ghel\u0103uza",
    "gn:population":0,
    "gn:timezone":"Europe/Chisinau",
    "iso:country":"MD",
    "name:rus_x_preferred":[
        "\u0413\u0435\u043b\u0430\u0443\u0437\u0430"
    ],
    "name:und_x_variant":[
        "Gelauza",
        "Ghel\u0103uza"
    ],
    "wof:name":"Ghelauza",
    "wof:placetype":"locality"
},
  "geometry": {"coordinates":[28.59607,47.19264],"type":"Point"}
}