{
  "type": "Feature",
  "properties": {
    "gn:admin1_code":"83.0",
    "gn:asciiname":"Pereni",
    "gn:country_code":"MD",
    "gn:dem":147,
    "gn:feature_class":"P",
    "gn:feature_code":"PPL",
    "gn:name":"Pereni",
    "gn:population":0,
    "gn:timezone":"Europe/Chisinau",
    "iso:country":"MD",
    "name:rus_x_preferred":[
        "\u041f\u0435\u0440\u0435\u043d\u044b"
    ],
    "name:und_x_variant":[
        "Peren\u2019",
        "Pereny",
        "Pereni"
    ],
    "wof:name":"Pereni",
    "wof:placetype":"locality"
},
  "geometry": {"coordinates":[28.77977000000001,47.65581],"type":"Point"}
}