{
  "type": "Feature",
  "properties": {
    "gn:admin1_code":"71.0",
    "gn:asciiname":"Surii Noi",
    "gn:country_code":"MD",
    "gn:dem":164,
    "gn:feature_class":"P",
    "gn:feature_code":"PPL",
    "gn:name":"\u015eurii Noi",
    "gn:population":0,
    "gn:timezone":"Europe/Chisinau",
    "iso:country":"MD",
    "name:rus_x_preferred":[
        "\u041d\u043e\u0432\u044b\u0435 \u0428\u0443\u0440\u044b"
    ],
    "name:und_x_variant":[
        "Novyye Shury",
        "\u015eurii Noi"
    ],
    "wof:name":"Surii Noi",
    "wof:placetype":"locality"
},
  "geometry": {"coordinates":[27.79929000000001,48.06434],"type":"Point"}
}