{
  "type": "Feature",
  "properties": {
    "gn:admin1_code":"69.0",
    "gn:asciiname":"Izbiste",
    "gn:country_code":"MD",
    "gn:dem":82,
    "gn:feature_class":"P",
    "gn:feature_code":"PPL",
    "gn:name":"Izbi\u015fte",
    "gn:population":0,
    "gn:timezone":"Europe/Chisinau",
    "iso:country":"MD",
    "name:und_x_variant":[
        "Izbe\u015fte",
        "Izbishche",
        "Izbeshty",
        "Izbishtya",
        "Izbi\u015fte",
        "\u0418\u0437\u0431\u0438\u0449\u0435"
    ],
    "wof:name":"Izbiste",
    "wof:placetype":"locality"
},
  "geometry": {"coordinates":[29.00194,47.22139],"type":"Point"}
}