{
  "type": "Feature",
  "properties": {
    "gn:admin1_code":"83.0",
    "gn:asciiname":"Pripiceni-Razesi",
    "gn:country_code":"MD",
    "gn:dem":176,
    "gn:feature_class":"P",
    "gn:feature_code":"PPL",
    "gn:name":"Pripiceni-R\u0103ze\u015fi",
    "gn:population":0,
    "gn:timezone":"Europe/Chisinau",
    "iso:country":"MD",
    "name:rus_x_preferred":[
        "\u041f\u0440\u0438\u043f\u0438\u0447\u0435\u043d\u044b-\u0420\u0435\u0437\u0435\u0448\u044c"
    ],
    "name:und_x_variant":[
        "Pripicheny-Rezesh\u2019",
        "Pripichen\u2019",
        "Pripiceni-R\u0103ze\u015fi"
    ],
    "wof:name":"Pripiceni-Razesi",
    "wof:placetype":"locality"
},
  "geometry": {"coordinates":[28.76136,47.6872],"type":"Point"}
}