{
  "type": "Feature",
  "properties": {
    "gn:admin1_code":"87.0",
    "gn:asciiname":"Cremenciug",
    "gn:country_code":"MD",
    "gn:dem":67,
    "gn:feature_class":"P",
    "gn:feature_code":"PPL",
    "gn:name":"Cremenciug",
    "gn:population":0,
    "gn:timezone":"Europe/Chisinau",
    "iso:country":"MD",
    "name:ita_x_preferred":[
        "Cremenciug"
    ],
    "name:ron_x_preferred":[
        "Comuna Cremenciug"
    ],
    "name:rus_x_preferred":[
        "\u041a\u0440\u0435\u043c\u0435\u043d\u0447\u0443\u0433"
    ],
    "name:und_x_variant":[
        "Kremenchuk",
        "Kremenchug",
        "Cremenciug"
    ],
    "wof:name":"Cremenciug",
    "wof:placetype":"locality"
},
  "geometry": {"coordinates":[28.08459,48.27567],"type":"Point"}
}