{
  "type": "Feature",
  "properties": {
    "gn:admin1_code":"58.0",
    "gn:asciiname":"Alexandrovca Noua",
    "gn:country_code":"MD",
    "gn:dem":75,
    "gn:feature_class":"P",
    "gn:feature_code":"PPL",
    "gn:name":"Alexandrovca Nou\u0103",
    "gn:population":0,
    "gn:timezone":"Europe/Chisinau",
    "iso:country":"MD",
    "name:rus_x_preferred":[
        "\u041d\u043e\u0432\u0430\u044f \u0410\u043b\u0435\u043a\u0441\u0430\u043d\u0434\u0440\u043e\u0432\u043a\u0430"
    ],
    "name:und_x_variant":[
        "Novaya Aleksandrovka",
        "Alexandrovca Nou\u0103"
    ],
    "wof:name":"Alexandrovca Noua",
    "wof:placetype":"locality"
},
  "geometry": {"coordinates":[29.3031,47.29956],"type":"Point"}
}