{
  "type": "Feature",
  "properties": {
    "gn:admin1_code":"84.0",
    "gn:asciiname":"Ramazan",
    "gn:country_code":"MD",
    "gn:dem":172,
    "gn:feature_class":"P",
    "gn:feature_code":"PPL",
    "gn:name":"R\u0103m\u0103zan",
    "gn:population":0,
    "gn:timezone":"Europe/Chisinau",
    "iso:country":"MD",
    "name:deu_x_preferred":[
        "Ramazan"
    ],
    "name:fra_x_preferred":[
        "Ramazan"
    ],
    "name:kat_x_preferred":[
        "\u10e0\u10d0\u10db\u10d0\u10d6\u10d0\u10dc\u10d8"
    ],
    "name:rus_x_preferred":[
        "\u0420\u0430\u043c\u0430\u0437\u0430\u043d"
    ],
    "name:tur_x_preferred":[
        "Ramazan"
    ],
    "name:und_x_variant":[
        "R\u0103m\u0103zani",
        "Ramazany",
        "R\u0103m\u0103zan"
    ],
    "wof:name":"Ramazan",
    "wof:placetype":"locality"
},
  "geometry": {"coordinates":[27.61571,47.98613],"type":"Point"}
}