{
  "type": "Feature",
  "properties": {
    "iso:country":"MD",
    "name:ceb_x_preferred":[
        "B\u00eernova"
    ],
    "name:dan_x_preferred":[
        "B\u00eernova"
    ],
    "name:deu_x_preferred":[
        "B\u00eernova"
    ],
    "name:eng_x_preferred":[
        "Byrnovo"
    ],
    "name:eng_x_variant":[
        "Byrnova",
        "B\u00eernova"
    ],
    "name:eus_x_preferred":[
        "B\u00eernova"
    ],
    "name:fra_x_preferred":[
        "B\u00eernova"
    ],
    "name:ita_x_preferred":[
        "B\u00eernova"
    ],
    "name:kat_x_preferred":[
        "\u10d1\u10d8\u10e0\u10dc\u10dd\u10d5\u10d0"
    ],
    "name:nld_x_preferred":[
        "B\u00eernova"
    ],
    "name:nno_x_preferred":[
        "B\u00eernova"
    ],
    "name:nob_x_preferred":[
        "B\u00eernova"
    ],
    "name:pol_x_preferred":[
        "B\u00eernova"
    ],
    "name:por_x_preferred":[
        "B\u00eernova"
    ],
    "name:ron_x_preferred":[
        "B\u00eernova"
    ],
    "name:ron_x_variant":[
        "Comuna Z\u0103briceni"
    ],
    "name:rus_x_preferred":[
        "\u0411\u044b\u0440\u043d\u043e\u0432\u043e"
    ],
    "name:spa_x_preferred":[
        "B\u00eernova"
    ],
    "name:swe_x_preferred":[
        "B\u00eernova"
    ],
    "name:ukr_x_preferred":[
        "\u0411\u0438\u0440\u043d\u043e\u0432\u0430"
    ],
    "name:und_x_colloquial":[
        "Barnova",
        "Birnova"
    ],
    "name:und_x_variant":[
        "B\u00e2rnova"
    ],
    "qs:a0":"Moldova",
    "qs:a1":"*Ocni\u0163a",
    "qs:a1_alt":"Ocnita",
    "qs:a1r":"0",
    "qs:adm0":"Moldova",
    "qs:la_lc":"*",
    "qs:level":"locality",
    "qs:loc":"B\u00eernova",
    "qs:loc_alt":"Birnova",
    "qs:pop":0,
    "qs:type":"buffered point",
    "wd:wordcount":47,
    "wof:lang":[
        "unk"
    ],
    "wof:name":"B\u00eernova",
    "wof:placetype":"locality"
},
  "geometry": {"coordinates":[27.528702,48.421589],"type":"Point"}
}