{
  "type": "Feature",
  "properties": {
    "gn:admin1_code":"91.0",
    "gn:asciiname":"Zgardesti",
    "gn:country_code":"MD",
    "gn:dem":95,
    "gn:feature_class":"P",
    "gn:feature_code":"PPL",
    "gn:name":"Zg\u0103rde\u015fti",
    "gn:population":0,
    "gn:timezone":"Europe/Chisinau",
    "iso:country":"MD",
    "name:rus_x_preferred":[
        "\u0417\u0433\u043e\u0440\u0434\u0435\u0448\u0442\u044b"
    ],
    "name:und_x_variant":[
        "Zgardeshti",
        "Zgordeshty",
        "Zgardeshty",
        "Zgardesht\u2019",
        "Zg\u0103rde\u015fti"
    ],
    "wof:name":"Zgardesti",
    "wof:placetype":"locality"
},
  "geometry": {"coordinates":[28.1905,47.53058],"type":"Point"}
}