{
  "type": "Feature",
  "properties": {
    "gn:asciiname":"Hanasenii de Prut",
    "gn:country_code":"MD",
    "gn:dem":30,
    "gn:feature_class":"P",
    "gn:feature_code":"PPL",
    "gn:name":"H\u0103n\u0103\u015fenii de Prut",
    "gn:population":0,
    "gn:timezone":"Europe/Chisinau",
    "iso:country":"MD",
    "wof:name":"Hanasenii de Prut",
    "wof:placetype":"locality"
},
  "geometry": {"coordinates":[28.27408,46.39586],"type":"Point"}
}