{
  "type": "Feature",
  "properties": {
    "gn:admin1_code":"59.0",
    "gn:asciiname":"Botnarestii Noi",
    "gn:country_code":"MD",
    "gn:dem":57,
    "gn:feature_class":"P",
    "gn:feature_code":"PPL",
    "gn:name":"Botn\u0103re\u015ftii Noi",
    "gn:population":0,
    "gn:timezone":"Europe/Chisinau",
    "iso:country":"MD",
    "name:rus_x_preferred":[
        "\u041d\u043e\u0432\u044b\u0435 \u0411\u043e\u0442\u043d\u0430\u0440\u0435\u0448\u0442\u044b"
    ],
    "name:und_x_variant":[
        "Novyye Botnareshty",
        "Botn\u0103re\u015ftii Noi"
    ],
    "wof:name":"Botnarestii Noi",
    "wof:placetype":"locality"
},
  "geometry": {"coordinates":[29.16597,46.92158],"type":"Point"}
}