{
  "type": "Feature",
  "properties": {
    "iso:country":"MD",
    "name:eng_x_preferred":[
        "Kotovsk"
    ],
    "name:eng_x_variant":[
        "Kotova",
        "Kotovo"
    ],
    "name:ita_x_preferred":[
        "Cotova"
    ],
    "name:kat_x_preferred":[
        "\u10d9\u10dd\u10e2\u10dd\u10d5\u10d0"
    ],
    "name:ron_x_preferred":[
        "Cotova"
    ],
    "name:rus_x_preferred":[
        "\u041a\u043e\u0442\u043e\u0432\u0430"
    ],
    "name:rus_x_variant":[
        "\u041a\u043e\u0442\u043e\u0432\u043e"
    ],
    "name:ukr_x_preferred":[
        "\u041a\u043e\u0442\u043e\u0432\u0430"
    ],
    "name:und_x_preferred":[
        "Cotova"
    ],
    "name:unk_x_variant":[
        "Kotova"
    ],
    "qs:a0":"Moldova",
    "qs:a1":"*Drocia",
    "qs:a1_alt":"Drochia",
    "qs:a1r":"0",
    "qs:adm0":"Moldova",
    "qs:la_lc":"*",
    "qs:level":"locality",
    "qs:loc":"Cotova",
    "qs:loc_alt":"Cotova",
    "qs:pop":0,
    "qs:type":"buffered point",
    "wd:wordcount":43,
    "wof:lang":[
        "unk"
    ],
    "wof:name":"Cotova",
    "wof:placetype":"locality"
},
  "geometry": {"coordinates":[27.950362,48.16299],"type":"Point"}
}