{
  "type": "Feature",
  "properties": {
    "gn:admin1_code":"78.0",
    "gn:asciiname":"Manoilesti",
    "gn:cc2":"MD",
    "gn:country_code":"MD",
    "gn:dem":115,
    "gn:feature_class":"P",
    "gn:feature_code":"PPL",
    "gn:name":"Manoile\u015fti",
    "gn:population":0,
    "gn:timezone":"Europe/Chisinau",
    "iso:country":"MD",
    "name:und_x_variant":[
        "Manoylesht'",
        "Manoyleshty",
        "Manoileshty"
    ],
    "wof:name":"Manoilesti",
    "wof:placetype":"locality"
},
  "geometry": {"coordinates":[28.60222000000001,46.95917],"type":"Point"}
}