{
  "type": "Feature",
  "properties": {
    "gn:admin1_code":"73.0",
    "gn:asciiname":"Chiurt",
    "gn:country_code":"MD",
    "gn:dem":139,
    "gn:feature_class":"P",
    "gn:feature_code":"PPL",
    "gn:name":"Chiurt",
    "gn:population":0,
    "gn:timezone":"Europe/Chisinau",
    "iso:country":"MD",
    "name:rus_x_preferred":[
        "\u041a\u044e\u0440\u0442"
    ],
    "name:und_x_variant":[
        "Kyurt",
        "Chiurt"
    ],
    "wof:name":"Chiurt",
    "wof:placetype":"locality"
},
  "geometry": {"coordinates":[27.34291,48.06131],"type":"Point"}
}