{
  "type": "Feature",
  "properties": {
    "iso:country":"MD",
    "name:arz_x_preferred":[
        "\u062a\u0627\u0631\u0627\u0643\u0644\u064a\u0627 \u062f\u0649 \u0633\u0627\u0644\u0633\u0649"
    ],
    "name:che_x_preferred":[
        "\u0422\u0430\u0440\u0430\u043a\u043b\u0438\u0430 \u0434\u0435 \u0421\u0430\u043b\u0447\u0438\u0435"
    ],
    "name:eng_x_preferred":[
        "Tarakliya"
    ],
    "name:ita_x_preferred":[
        "Taraclia de Salcie"
    ],
    "name:kat_x_preferred":[
        "\u10e2\u10d0\u10e0\u10d0\u10d9\u10da\u10d8\u10d0-\u10d3\u10d4-\u10e1\u10d0\u10da\u10e9\u10d8\u10d4"
    ],
    "name:ron_x_preferred":[
        "Taraclia de Salcie"
    ],
    "name:rus_x_preferred":[
        "\u0422\u0430\u0440\u0430\u043a\u043b\u0438\u044f \u0434\u0435 \u0421\u0430\u043b\u0447\u0438\u0435"
    ],
    "name:rus_x_variant":[
        "\u0422\u0430\u0440\u0430\u043a\u043b\u0438\u044f-\u0434\u0435-\u0421\u0430\u043b\u0447\u0438\u0435"
    ],
    "name:tat_x_preferred":[
        "\u0422\u0430\u0440\u0430\u043a\u043b\u0438\u0430 \u0434\u0435 \u0421\u0430\u043b\u0447\u0438\u0435"
    ],
    "name:ukr_x_preferred":[
        "\u0422\u0430\u0440\u0430\u043a\u043b\u0456\u044f-\u0434\u0435-\u0421\u0430\u043b\u0447\u0456\u0454"
    ],
    "name:und_x_variant":[
        "Taraclia",
        "Tarakliya de Salche"
    ],
    "name:zho_x_preferred":[
        "\u6070\u5fb7\u723e\u502b\u52a0"
    ],
    "qs:a0":"Moldova",
    "qs:a1":"*Cahul",
    "qs:a1_alt":"Cahul",
    "qs:a1r":"0",
    "qs:adm0":"Moldova",
    "qs:la_lc":"*",
    "qs:level":"locality",
    "qs:loc":"Taraclia de Salcie",
    "qs:loc_alt":"Taraclia de Salcie",
    "qs:pop":0,
    "qs:type":"buffered point",
    "wd:wordcount":123,
    "wof:lang":[
        "unk"
    ],
    "wof:name":"Taraclia de Salcie",
    "wof:placetype":"locality"
},
  "geometry": {"coordinates":[28.41567,46.010632],"type":"Point"}
}