{
  "type": "Feature",
  "properties": {
    "iso:country":"MD",
    "name:dut_x_preferred":[
        "Bozieni"
    ],
    "name:eng_x_preferred":[
        "Boziyeny"
    ],
    "name:eng_x_variant":[
        "Boziyen'",
        "Boziyeni",
        "Bozieni"
    ],
    "name:geo_x_preferred":[
        "\u10d1\u10dd\u10d6\u10d8\u10d4\u10dc\u10d8"
    ],
    "name:ita_x_preferred":[
        "Bozieni"
    ],
    "name:ron_x_preferred":[
        "Bozieni"
    ],
    "name:rum_x_preferred":[
        "Bozieni"
    ],
    "name:rus_x_preferred":[
        "\u0411\u043e\u0437\u0438\u0435\u043d\u044b"
    ],
    "name:ukr_x_preferred":[
        "\u0411\u043e\u0437\u0456\u0454\u043d\u044c"
    ],
    "name:und_x_preferred":[
        "Bozieni"
    ],
    "name:unk_x_variant":[
        "Boziyen\u2019"
    ],
    "qs:a0":"Moldova",
    "qs:a1":"*H\u00eence\u015fti",
    "qs:a1_alt":"Hincesti",
    "qs:a1r":"0",
    "qs:adm0":"Moldova",
    "qs:la_lc":"*",
    "qs:level":"locality",
    "qs:loc":"Bozieni",
    "qs:loc_alt":"Bozieni",
    "qs:pop":0,
    "qs:type":"buffered point",
    "wd:wordcount":46,
    "wof:lang":[
        "unk"
    ],
    "wof:name":"Bozieni",
    "wof:placetype":"locality"
},
  "geometry": {"coordinates":[28.642889,46.752358],"type":"Point"}
}