{
  "type": "Feature",
  "properties": {
    "gn:admin1_code":"66.0",
    "gn:asciiname":"Muzhik",
    "gn:country_code":"MD",
    "gn:dem":162,
    "gn:feature_class":"P",
    "gn:feature_code":"PPL",
    "gn:name":"Muzhik",
    "gn:population":0,
    "gn:timezone":"Europe/Chisinau",
    "iso:country":"MD",
    "wof:name":"Muzhik",
    "wof:placetype":"locality"
},
  "geometry": {"coordinates":[28.20762,47.3013],"type":"Point"}
}