{
  "type": "Feature",
  "properties": {
    "iso:country":"MD",
    "name:dan_x_preferred":[
        "Dolna"
    ],
    "name:deu_x_preferred":[
        "Dolna"
    ],
    "name:eng_x_preferred":[
        "Pushkino"
    ],
    "name:eus_x_preferred":[
        "Dolna"
    ],
    "name:fra_x_preferred":[
        "Dolna"
    ],
    "name:ita_x_preferred":[
        "Dolna"
    ],
    "name:kat_x_preferred":[
        "\u10d3\u10dd\u10da\u10dc\u10d0"
    ],
    "name:nld_x_preferred":[
        "Dolna"
    ],
    "name:nno_x_preferred":[
        "Dolna"
    ],
    "name:nob_x_preferred":[
        "Dolna"
    ],
    "name:pol_x_preferred":[
        "Dolna"
    ],
    "name:por_x_preferred":[
        "Dolna"
    ],
    "name:ron_x_preferred":[
        "Dolna"
    ],
    "name:rus_x_preferred":[
        "\u0414\u043e\u043b\u043d\u0430"
    ],
    "name:rus_x_variant":[
        "\u041f\u0443\u0448\u043a\u0438\u043d\u043e"
    ],
    "name:spa_x_preferred":[
        "Dolna"
    ],
    "name:swe_x_preferred":[
        "Dolna"
    ],
    "name:ukr_x_preferred":[
        "\u0414\u043e\u043b\u043d\u0430"
    ],
    "name:und_x_preferred":[
        "Dolna"
    ],
    "name:unk_x_variant":[
        "Pushkino"
    ],
    "qs:a0":"Moldova",
    "qs:a1":"*Str\u0103\u015feni",
    "qs:a1_alt":"Straseni",
    "qs:a1r":"0",
    "qs:adm0":"Moldova",
    "qs:la_lc":"*",
    "qs:level":"locality",
    "qs:loc":"Dolna",
    "qs:loc_alt":"Dolna",
    "qs:pop":0,
    "qs:type":"buffered point",
    "wd:wordcount":16,
    "wof:lang":[
        "unk"
    ],
    "wof:name":"Dolna",
    "wof:placetype":"locality"
},
  "geometry": {"coordinates":[28.270134,47.118355],"type":"Point"}
}