{
  "type": "Feature",
  "properties": {
    "iso:country":"MD",
    "name:eng_x_preferred":[
        "Leu\u0219eni"
    ],
    "name:ita_x_preferred":[
        "Leu\u0219eni"
    ],
    "name:jpn_x_preferred":[
        "\u30ec\u30a6\u30bb\u30cb"
    ],
    "name:kat_x_preferred":[
        "\u10da\u10d4\u10e3\u10e8\u10d4\u10dc\u10d8"
    ],
    "name:nld_x_preferred":[
        "Leu\u015feni"
    ],
    "name:pol_x_preferred":[
        "Leu\u0219eni"
    ],
    "name:ron_x_preferred":[
        "Leu\u0219eni"
    ],
    "name:rus_x_preferred":[
        "\u041b\u0435\u0443\u0448\u0435\u043d\u044b"
    ],
    "name:ukr_x_preferred":[
        "\u041b\u0435\u0443\u0448\u0435\u043d\u044c"
    ],
    "name:und_x_variant":[
        "Leusheny",
        "Leusheni"
    ],
    "qs:a0":"Moldova",
    "qs:a1":"*H\u00eence\u015fti",
    "qs:a1_alt":"Hincesti",
    "qs:a1r":"0",
    "qs:adm0":"Moldova",
    "qs:la_lc":"*",
    "qs:level":"locality",
    "qs:loc":"Leu\u015feni",
    "qs:loc_alt":"Leuseni",
    "qs:pop":0,
    "qs:type":"buffered point",
    "wd:wordcount":28,
    "wof:lang":[
        "unk"
    ],
    "wof:name":"Leu\u015feni",
    "wof:placetype":"locality"
},
  "geometry": {"coordinates":[28.200096,46.814945],"type":"Point"}
}