{
  "type": "Feature",
  "properties": {
    "gn:gn_country":"MD",
    "gn:gn_fcode":"PPL",
    "gn:gn_pop":0,
    "iso:country":"MD",
    "name:eng_x_preferred":[
        "Sec\u0103reni"
    ],
    "name:ita_x_preferred":[
        "Sec\u0103reni"
    ],
    "name:jpn_x_preferred":[
        "\u30bb\u30ab\u30ec\u30cb"
    ],
    "name:kat_x_preferred":[
        "\u10e1\u10d4\u10d9\u10d4\u10e0\u10d4\u10dc\u10d8"
    ],
    "name:nld_x_preferred":[
        "Sec\u0103reni"
    ],
    "name:ron_x_preferred":[
        "Sec\u0103reni"
    ],
    "name:rus_x_preferred":[
        "\u0421\u0435\u043a\u0430\u0440\u0435\u043d\u044b"
    ],
    "name:ukr_x_preferred":[
        "\u0421\u0435\u043a\u0435\u0440\u0435\u043d\u044c"
    ],
    "name:unk_x_variant":[
        "Sekaren\u2019"
    ],
    "qs_pg:aaroncc":"MD",
    "qs_pg:gn_country":"MD",
    "qs_pg:gn_fcode":"PPL",
    "qs_pg:gn_pop":0,
    "qs_pg:name":"Sec\u00e6reni",
    "qs_pg:name_adm0":"Moldova",
    "qs_pg:name_adm1":"Hincesti",
    "qs_pg:photos":3,
    "qs_pg:photos_1k":1,
    "qs_pg:photos_9k":1,
    "qs_pg:photos_9r":1,
    "qs_pg:photos_all":3,
    "qs_pg:photos_sr":1,
    "qs_pg:pop_sr":0,
    "qs_pg:qs_pg_placetype":"locality",
    "qs_pg:qs_pg_placetype_gp":"Town",
    "qs_pg:woe_adm0":23424885,
    "woe:adm0_id":23424885,
    "woe:name_adm0":"Moldova",
    "woe:name_adm1":"Hincesti",
    "woe:placetype":"Town",
    "wof:name":"Sec\u00e6reni",
    "wof:placetype":"locality"
},
  "geometry": {"coordinates":[28.3325,47.02528],"type":"Point"}
}