{
  "type": "Feature",
  "properties": {
    "gn:admin1_code":"59.0",
    "gn:asciiname":"Floresti",
    "gn:country_code":"MD",
    "gn:dem":117,
    "gn:feature_class":"P",
    "gn:feature_code":"PPL",
    "gn:name":"Flore\u015fti",
    "gn:population":0,
    "gn:timezone":"Europe/Chisinau",
    "iso:country":"MD",
    "name:rus_x_preferred":[
        "\u0424\u043b\u043e\u0440\u0435\u0448\u0442\u044b"
    ],
    "name:und_x_variant":[
        "Floresht\u2019",
        "Floreshty",
        "Flore\u015fti"
    ],
    "wof:name":"Floresti",
    "wof:placetype":"locality"
},
  "geometry": {"coordinates":[29.18092,46.99744000000001],"type":"Point"}
}