{
  "type": "Feature",
  "properties": {
    "gn:admin1_code":"75.0",
    "gn:asciiname":"Nicolaevca",
    "gn:country_code":"MD",
    "gn:dem":300,
    "gn:feature_class":"P",
    "gn:feature_code":"PPL",
    "gn:name":"Nicolaevca",
    "gn:population":0,
    "gn:timezone":"Europe/Chisinau",
    "iso:country":"MD",
    "name:ita_x_preferred":[
        "Nicolaevca"
    ],
    "name:ron_x_preferred":[
        "Comuna Nicolaevca"
    ],
    "name:rus_x_preferred":[
        "\u041d\u0438\u043a\u043e\u043b\u0430\u0435\u0432\u043a\u0430"
    ],
    "name:und_x_variant":[
        "Nikolayevka",
        "Nicolaevca"
    ],
    "wof:name":"Nicolaevca",
    "wof:placetype":"locality"
},
  "geometry": {"coordinates":[28.52855,47.91859],"type":"Point"}
}