{
  "type": "Feature",
  "properties": {
    "gn:admin1_code":"79.0",
    "gn:asciiname":"Valea Florii",
    "gn:country_code":"MD",
    "gn:dem":106,
    "gn:feature_class":"P",
    "gn:feature_code":"PPL",
    "gn:name":"Valea Florii",
    "gn:population":0,
    "gn:timezone":"Europe/Chisinau",
    "iso:country":"MD",
    "name:rus_x_preferred":[
        "\u0412\u0430\u043b\u044f-\u0424\u043b\u043e\u0430\u0440\u044f"
    ],
    "name:und_x_variant":[
        "Ivanovka",
        "Valya-Floarya",
        "Valya-Floriy",
        "Valea Florii"
    ],
    "wof:name":"Valea Florii",
    "wof:placetype":"locality"
},
  "geometry": {"coordinates":[28.43755,46.71351],"type":"Point"}
}