{
  "type": "Feature",
  "properties": {
    "gn:admin1_code":"90.0",
    "gn:asciiname":"Orehovca",
    "gn:country_code":"MD",
    "gn:dem":76,
    "gn:feature_class":"P",
    "gn:feature_code":"PPL",
    "gn:name":"Orehovca",
    "gn:population":0,
    "gn:timezone":"Europe/Chisinau",
    "iso:country":"MD",
    "name:rus_x_preferred":[
        "\u041e\u0440\u0435\u0445\u043e\u0432\u043a\u0430"
    ],
    "name:und_x_variant":[
        "Verkhnyaya Biserikucha",
        "Orekhovka",
        "Biserikutsa Verkhnyaya",
        "Bisericu\u0163a",
        "Bisericu\u0163a-de Sus",
        "Orehovca"
    ],
    "wof:name":"Orehovca",
    "wof:placetype":"locality"
},
  "geometry": {"coordinates":[28.52836,45.9075],"type":"Point"}
}