{
  "type": "Feature",
  "properties": {
    "iso:country":"MD",
    "name:arz_x_preferred":[
        "\u067e\u0648\u0686\u0627\u0631\u064a\u0646\u0649"
    ],
    "name:cat_x_preferred":[
        "Poj\u0103reni"
    ],
    "name:ceb_x_preferred":[
        "Poj\u0103reni"
    ],
    "name:che_x_preferred":[
        "\u041f\u043e\u0436\u044b\u0440\u0435\u043d\u0438"
    ],
    "name:dan_x_preferred":[
        "Poj\u0103reni"
    ],
    "name:deu_x_preferred":[
        "Poj\u0103reni"
    ],
    "name:eng_x_preferred":[
        "Poj\u0103reni"
    ],
    "name:eus_x_preferred":[
        "Poj\u0103reni"
    ],
    "name:fra_x_preferred":[
        "Poj\u0103reni"
    ],
    "name:gle_x_preferred":[
        "Poj\u0103reni"
    ],
    "name:glg_x_preferred":[
        "Poj\u0103reni"
    ],
    "name:ita_x_preferred":[
        "Poj\u0103reni"
    ],
    "name:kat_x_preferred":[
        "\u10de\u10dd\u10df\u10d4\u10e0\u10d4\u10dc\u10d8"
    ],
    "name:nld_x_preferred":[
        "Poj\u0103reni"
    ],
    "name:nno_x_preferred":[
        "Poj\u0103reni"
    ],
    "name:nob_x_preferred":[
        "Poj\u0103reni"
    ],
    "name:pol_x_preferred":[
        "Poj\u0103reni"
    ],
    "name:por_x_preferred":[
        "Poj\u0103reni"
    ],
    "name:ron_x_preferred":[
        "Poj\u0103reni"
    ],
    "name:rus_x_preferred":[
        "\u041f\u043e\u0436\u044d\u0440\u0435\u043d\u044c"
    ],
    "name:rus_x_variant":[
        "\u041f\u043e\u0436\u0430\u0440\u0435\u043d\u044b"
    ],
    "name:spa_x_preferred":[
        "Poj\u0103reni"
    ],
    "name:swe_x_preferred":[
        "Poj\u0103reni"
    ],
    "name:tat_x_preferred":[
        "\u041f\u043e\u0436\u044b\u0440\u0435\u043d\u0438"
    ],
    "name:ukr_x_preferred":[
        "\u041f\u043e\u0436\u0435\u0440\u0435\u043d\u044c"
    ],
    "name:ukr_x_variant":[
        "\u0427\u0443\u0447\u0443\u0440-\u041c\u0456\u043d\u0434\u0436\u0456\u0440"
    ],
    "name:und_x_variant":[
        "Pozhareny"
    ],
    "qs:a0":"Moldova",
    "qs:a1":"*Ialoveni",
    "qs:a1_alt":"Ialoveni",
    "qs:a1r":"0",
    "qs:adm0":"Moldova",
    "qs:la_lc":"*",
    "qs:level":"locality",
    "qs:loc":"Poj\u0103reni",
    "qs:loc_alt":"Pojareni",
    "qs:pop":0,
    "qs:type":"buffered point",
    "wd:wordcount":18,
    "wof:name":"Poj\u0103reni",
    "wof:placetype":"locality"
},
  "geometry": {"coordinates":[28.690689,46.886929],"type":"Point"}
}