{
  "type": "Feature",
  "properties": {
    "iso:country":"MD",
    "name:deu_x_preferred":[
        "M\u0103rine\u0219ti"
    ],
    "name:eng_x_preferred":[
        "M\u0103rine\u015fti"
    ],
    "name:ron_x_preferred":[
        "M\u0103rine\u0219ti"
    ],
    "name:rus_x_preferred":[
        "\u041c\u044d\u0440\u0438\u043d\u0435\u0448\u0442\u044c"
    ],
    "name:rus_x_variant":[
        "\u041c\u0430\u0440\u0438\u043d\u0435\u0448\u0442\u044b"
    ],
    "name:ukr_x_preferred":[
        "\u041c\u0435\u0440\u0456\u043d\u0435\u0448\u0442\u044c"
    ],
    "name:unk_x_variant":[
        "Marineshty"
    ],
    "qs:a0":"Moldova",
    "qs:a1":"*S\u00eengerei",
    "qs:a1_alt":"Singerei",
    "qs:a1r":"0",
    "qs:adm0":"Moldova",
    "qs:la_lc":"*",
    "qs:level":"locality",
    "qs:loc":"M\u0103rine\u015fti",
    "qs:loc_alt":"Marinesti",
    "qs:pop":0,
    "qs:type":"buffered point",
    "wd:wordcount":45,
    "wof:name":"M\u0103rine\u015fti",
    "wof:placetype":"locality"
},
  "geometry": {"coordinates":[28.063188,47.724175],"type":"Point"}
}