{
  "type": "Feature",
  "properties": {
    "iso:country":"MD",
    "name:baq_x_preferred":[
        "C\u00eern\u0103\u021beni"
    ],
    "name:dan_x_preferred":[
        "C\u00eern\u0103\u021beni"
    ],
    "name:dut_x_preferred":[
        "C\u00eern\u0103\u021beni"
    ],
    "name:eng_x_preferred":[
        "Kirnatsen"
    ],
    "name:eng_x_variant":[
        "Kirnatsany",
        "Kirnatseny",
        "Kirnetseni",
        "Kyrnatseny",
        "C\u00eern\u0103\u021beni"
    ],
    "name:fre_x_preferred":[
        "C\u00eern\u0103\u021beni"
    ],
    "name:geo_x_preferred":[
        "\u10d9\u10d8\u10e0\u10dc\u10d4\u10ea\u10d4\u10dc\u10d8"
    ],
    "name:ger_x_preferred":[
        "C\u00eern\u0103\u021beni"
    ],
    "name:ita_x_preferred":[
        "C\u00eern\u0103\u021beni"
    ],
    "name:kat_x_preferred":[
        "\u10d9\u10d8\u10e0\u10dc\u10d4\u10ea\u10d4\u10dc\u10d8"
    ],
    "name:nno_x_preferred":[
        "C\u00eern\u0103\u021beni"
    ],
    "name:nob_x_preferred":[
        "C\u00eern\u0103\u021beni"
    ],
    "name:pol_x_preferred":[
        "C\u00eern\u0103\u021beni"
    ],
    "name:por_x_preferred":[
        "C\u00eern\u0103\u021beni"
    ],
    "name:ron_x_preferred":[
        "C\u00eern\u0103\u021beni"
    ],
    "name:ron_x_variant":[
        "Cirn\u0103\u0163eni"
    ],
    "name:rum_x_preferred":[
        "C\u00eern\u0103\u021beni"
    ],
    "name:rus_x_preferred":[
        "\u041a\u044b\u0440\u043d\u0430\u0446\u0435\u043d\u044b"
    ],
    "name:spa_x_preferred":[
        "C\u00eern\u0103\u021beni"
    ],
    "name:swe_x_preferred":[
        "C\u00eern\u0103\u021beni"
    ],
    "name:ukr_x_preferred":[
        "\u041a\u0438\u0440\u043d\u0435\u0446\u0435\u043d\u044c"
    ],
    "name:und_x_colloquial":[
        "Carnateni",
        "Cirnateni"
    ],
    "name:und_x_preferred":[
        "C\u00eern\u0103\u0163eni"
    ],
    "name:und_x_variant":[
        "C\u00e2rn\u0103\u0163eni"
    ],
    "name:unk_x_variant":[
        "Kirnatsany"
    ],
    "qs:a0":"Moldova",
    "qs:a1":"*C\u0103u\u015feni",
    "qs:a1_alt":"Causeni",
    "qs:a1r":"0",
    "qs:adm0":"Moldova",
    "qs:la_lc":"*",
    "qs:level":"locality",
    "qs:loc":"C\u00eern\u0103\u0163eni",
    "qs:loc_alt":"Cirnateni",
    "qs:pop":0,
    "qs:type":"buffered point",
    "wd:wordcount":33,
    "wof:lang":[
        "unk"
    ],
    "wof:name":"C\u00eern\u0103\u0163eni",
    "wof:placetype":"locality"
},
  "geometry": {"coordinates":[29.489389,46.649884],"type":"Point"}
}