{
  "type": "Feature",
  "properties": {
    "gn:admin1_code":"84.0",
    "gn:asciiname":"Moseni",
    "gn:country_code":"MD",
    "gn:dem":201,
    "gn:feature_class":"P",
    "gn:feature_code":"PPL",
    "gn:name":"Mo\u015feni",
    "gn:population":0,
    "gn:timezone":"Europe/Chisinau",
    "iso:country":"MD",
    "name:rus_x_preferred":[
        "\u041c\u043e\u0448\u0430\u043d\u044b"
    ],
    "name:und_x_variant":[
        "Moshany",
        "Moshen\u2019",
        "Mo\u015feni"
    ],
    "wof:name":"Moseni",
    "wof:placetype":"locality"
},
  "geometry": {"coordinates":[27.45501,48.02861],"type":"Point"}
}