{
  "type": "Feature",
  "properties": {
    "iso:country":"MD",
    "name:eng_x_preferred":[
        "Lipnik"
    ],
    "name:eng_x_variant":[
        "Lipnic"
    ],
    "name:ita_x_preferred":[
        "Lipnic"
    ],
    "name:kat_x_preferred":[
        "\u10da\u10d8\u10de\u10dc\u10d8\u10d9\u10d8"
    ],
    "name:nld_x_preferred":[
        "Lipnic"
    ],
    "name:ron_x_preferred":[
        "Lipnic"
    ],
    "name:rus_x_preferred":[
        "\u041b\u0438\u043f\u043d\u0438\u043a"
    ],
    "name:ukr_x_preferred":[
        "\u041b\u0456\u043f\u043d\u0456\u043a"
    ],
    "qs:a0":"Moldova",
    "qs:a1":"*Ocni\u0163a",
    "qs:a1_alt":"Ocnita",
    "qs:a1r":"0",
    "qs:adm0":"Moldova",
    "qs:la_lc":"*",
    "qs:level":"locality",
    "qs:loc":"Lipnic",
    "qs:loc_alt":"Lipnic",
    "qs:pop":0,
    "qs:type":"buffered point",
    "wd:wordcount":34,
    "wof:lang":[
        "unk"
    ],
    "wof:name":"Lipnic",
    "wof:placetype":"locality"
},
  "geometry": {"coordinates":[27.514177,48.395401],"type":"Point"}
}