{
  "type": "Feature",
  "properties": {
    "gn:admin1_code":"66.0",
    "gn:asciiname":"Palanca",
    "gn:country_code":"MD",
    "gn:dem":174,
    "gn:feature_class":"P",
    "gn:feature_code":"PPL",
    "gn:name":"Palanca",
    "gn:population":0,
    "gn:timezone":"Europe/Chisinau",
    "iso:country":"MD",
    "name:arg_x_preferred":[
        "Palanca"
    ],
    "name:cat_x_preferred":[
        "Palanca"
    ],
    "name:ceb_x_preferred":[
        "Palanca"
    ],
    "name:deu_x_preferred":[
        "Palanca"
    ],
    "name:eus_x_preferred":[
        "Palanka"
    ],
    "name:ita_x_preferred":[
        "Palanca"
    ],
    "name:por_x_preferred":[
        "Palanca"
    ],
    "name:ron_x_preferred":[
        "Palanca"
    ],
    "name:rus_x_preferred":[
        "\u041f\u0430\u043b\u0430\u043d\u043a\u0430"
    ],
    "name:spa_x_preferred":[
        "Palanca"
    ],
    "name:swe_x_preferred":[
        "Palanca"
    ],
    "name:tgl_x_preferred":[
        "Palanca"
    ],
    "name:ukr_x_preferred":[
        "\u041f\u0430\u043b\u0430\u043d\u043a\u0430"
    ],
    "name:vie_x_preferred":[
        "Palanca"
    ],
    "wof:name":"Palanca",
    "wof:placetype":"locality"
},
  "geometry": {"coordinates":[28.20367,47.33474],"type":"Point"}
}