{
  "type": "Feature",
  "properties": {
    "gn:admin1_code":"66.0",
    "gn:asciiname":"Palanca",
    "gn:country_code":"MD",
    "gn:dem":174,
    "gn:feature_class":"P",
    "gn:feature_code":"PPL",
    "gn:name":"Palanca",
    "gn:population":0,
    "gn:timezone":"Europe/Chisinau",
    "iso:country":"MD",
    "name:rus_x_preferred":[
        "\u041f\u0430\u043b\u0430\u043d\u043a\u0430"
    ],
    "name:und_x_variant":[
        "Palanka",
        "Palanca"
    ],
    "wof:name":"Palanca",
    "wof:placetype":"locality"
},
  "geometry": {"coordinates":[28.20367,47.33474],"type":"Point"}
}