{
  "type": "Feature",
  "properties": {
    "iso:country":"MD",
    "name:ceb_x_preferred":[
        "Bocani"
    ],
    "name:dan_x_preferred":[
        "Bocani"
    ],
    "name:deu_x_preferred":[
        "Bocani"
    ],
    "name:eng_x_preferred":[
        "Bokani"
    ],
    "name:eng_x_variant":[
        "Bokan'",
        "Bokany",
        "Bocani"
    ],
    "name:eus_x_preferred":[
        "Bocani"
    ],
    "name:fra_x_preferred":[
        "Bocani"
    ],
    "name:ita_x_preferred":[
        "Bocani"
    ],
    "name:kat_x_preferred":[
        "\u10d1\u10dd\u10d9\u10d0\u10dc\u10d8"
    ],
    "name:nld_x_preferred":[
        "Bocani"
    ],
    "name:nno_x_preferred":[
        "Bocani"
    ],
    "name:nob_x_preferred":[
        "Bocani"
    ],
    "name:pol_x_preferred":[
        "Bocani"
    ],
    "name:por_x_preferred":[
        "Bocani"
    ],
    "name:ron_x_preferred":[
        "Bocani"
    ],
    "name:rus_x_preferred":[
        "\u0411\u043e\u043a\u0430\u043d\u044c"
    ],
    "name:rus_x_variant":[
        "\u0411\u043e\u043a\u0430\u043d\u044b"
    ],
    "name:spa_x_preferred":[
        "Bocani"
    ],
    "name:swe_x_preferred":[
        "Bocani"
    ],
    "name:ukr_x_preferred":[
        "\u0411\u043e\u043a\u0430\u043d\u044c"
    ],
    "name:und_x_colloquial":[
        "Bacani",
        "Baecani"
    ],
    "name:und_x_variant":[
        "B\u00e6cani",
        "Bokan\u2019"
    ],
    "qs:a0":"Moldova",
    "qs:a1":"*F\u0103le\u015fti",
    "qs:a1_alt":"Falesti",
    "qs:a1r":"0",
    "qs:adm0":"Moldova",
    "qs:la_lc":"*",
    "qs:level":"locality",
    "qs:loc":"Bocani",
    "qs:loc_alt":"Bocani",
    "qs:pop":0,
    "qs:type":"buffered point",
    "wd:wordcount":33,
    "wof:lang":[
        "unk"
    ],
    "wof:name":"Bocani",
    "wof:placetype":"locality"
},
  "geometry": {"coordinates":[27.889994,47.520474],"type":"Point"}
}