{
  "type": "Feature",
  "properties": {
    "gn:admin1_code":"67.0",
    "gn:asciiname":"Constantinovca",
    "gn:country_code":"MD",
    "gn:dem":54,
    "gn:feature_class":"P",
    "gn:feature_code":"PPL",
    "gn:name":"Constantinovca",
    "gn:population":0,
    "gn:timezone":"Europe/Chisinau",
    "iso:country":"MD",
    "name:ita_x_preferred":[
        "Constantinovca"
    ],
    "name:ron_x_preferred":[
        "Comuna Constantinovca"
    ],
    "name:rus_x_preferred":[
        "\u041a\u043e\u043d\u0441\u0442\u0430\u043d\u0442\u0438\u043d\u043e\u0432\u043a\u0430"
    ],
    "name:und_x_variant":[
        "Constantinesti",
        "Konstantinovka",
        "Konstantineshti"
    ],
    "wof:name":"Constantinovca",
    "wof:placetype":"locality"
},
  "geometry": {"coordinates":[29.11305,46.72246],"type":"Point"}
}