{
  "type": "Feature",
  "properties": {
    "iso:country":"MD",
    "name:ceb_x_preferred":[
        "Alexanderfeld"
    ],
    "name:dan_x_preferred":[
        "Alexanderfeld"
    ],
    "name:deu_x_preferred":[
        "Alexanderfeld"
    ],
    "name:eng_x_preferred":[
        "Alexandru cel Bun"
    ],
    "name:eng_x_variant":[
        "Aleksandrofel'd",
        "Aleksandru Chel Bun",
        "Kympen'",
        "Alexanderfeld"
    ],
    "name:eus_x_preferred":[
        "Alexanderfeld"
    ],
    "name:fra_x_preferred":[
        "Alexanderfeld"
    ],
    "name:ita_x_preferred":[
        "Alexanderfeld"
    ],
    "name:kat_x_preferred":[
        "\u10d0\u10da\u10d4\u10e5\u10e1\u10d0\u10dc\u10d3\u10d4\u10e0\u10e4\u10d4\u10da\u10d3\u10d8"
    ],
    "name:nld_x_preferred":[
        "Alexanderfeld"
    ],
    "name:nno_x_preferred":[
        "Alexanderfeld"
    ],
    "name:nob_x_preferred":[
        "Alexanderfeld"
    ],
    "name:pol_x_preferred":[
        "Alexanderfeld"
    ],
    "name:por_x_preferred":[
        "Alexanderfeld"
    ],
    "name:ron_x_preferred":[
        "Alexanderfeld"
    ],
    "name:rus_x_preferred":[
        "\u0410\u043b\u0435\u043a\u0441\u0430\u043d\u0434\u0435\u0440\u0444\u0435\u043b\u0434"
    ],
    "name:rus_x_variant":[
        "\u041a\u044b\u043c\u043f\u0435\u043d\u044c"
    ],
    "name:spa_x_preferred":[
        "Alexanderfeld"
    ],
    "name:swe_x_preferred":[
        "Alexanderfeld"
    ],
    "name:ukr_x_preferred":[
        "\u0410\u043b\u0435\u043a\u0441\u0430\u043d\u0434\u0435\u0440\u0444\u0435\u043b\u044c\u0434"
    ],
    "name:ukr_x_variant":[
        "\u0411\u0435\u0448\u0430\u043b\u043c\u0430"
    ],
    "name:und_x_colloquial":[
        "Campeni",
        "Cimpeni"
    ],
    "name:und_x_preferred":[
        "C\u00eempeni"
    ],
    "name:und_x_variant":[
        "C\u00e2mpeni"
    ],
    "name:unk_x_variant":[
        "Kympen\u2019"
    ],
    "qs:a0":"Moldova",
    "qs:a1":"*Cahul",
    "qs:a1_alt":"Cahul",
    "qs:a1r":"0",
    "qs:adm0":"Moldova",
    "qs:la_lc":"*",
    "qs:level":"locality",
    "qs:loc":"Alexanderfeld",
    "qs:loc_alt":"Alexanderfeld",
    "qs:pop":0,
    "qs:type":"buffered point",
    "wd:wordcount":107,
    "wof:lang":[
        "unk"
    ],
    "wof:name":"Alexanderfeld",
    "wof:placetype":"locality"
},
  "geometry": {"coordinates":[28.428198,45.810997],"type":"Point"}
}