{
  "type": "Feature",
  "properties": {
    "gn:asciiname":"Oxintea",
    "gn:country_code":"MD",
    "gn:dem":191,
    "gn:feature_class":"P",
    "gn:feature_code":"PPL",
    "gn:name":"Oxintea",
    "gn:population":0,
    "gn:timezone":"Europe/Chisinau",
    "iso:country":"MD",
    "wof:name":"Oxintea",
    "wof:placetype":"locality"
},
  "geometry": {"coordinates":[29.02269,47.39061],"type":"Point"}
}