{
  "type": "Feature",
  "properties": {
    "gn:admin1_code":"84.0",
    "gn:asciiname":"Pascauti",
    "gn:country_code":"MD",
    "gn:dem":116,
    "gn:feature_class":"P",
    "gn:feature_code":"PPL",
    "gn:name":"P\u0103sc\u0103u\u0163i",
    "gn:population":0,
    "gn:timezone":"Europe/Chisinau",
    "iso:country":"MD",
    "name:rus_x_preferred":[
        "\u041f\u0430\u0441\u043a\u0430\u0443\u0446\u044b"
    ],
    "name:und_x_variant":[
        "Paskautsy",
        "P\u0103sc\u0103u\u0163i"
    ],
    "wof:name":"Pascauti",
    "wof:placetype":"locality"
},
  "geometry": {"coordinates":[27.27869,47.83496],"type":"Point"}
}