{
  "type": "Feature",
  "properties": {
    "iso:country":"MD",
    "name:baq_x_preferred":[
        "Bardar"
    ],
    "name:dan_x_preferred":[
        "Bardar"
    ],
    "name:dut_x_preferred":[
        "Bardar"
    ],
    "name:eng_x_preferred":[
        "Bardaru"
    ],
    "name:fre_x_preferred":[
        "Bardar"
    ],
    "name:geo_x_preferred":[
        "\u10d1\u10d0\u10e0\u10d3\u10d0\u10e0\u10d8"
    ],
    "name:ger_x_preferred":[
        "Bardar"
    ],
    "name:ita_x_preferred":[
        "Bardar"
    ],
    "name:kat_x_preferred":[
        "\u10d1\u10d0\u10e0\u10d3\u10d0\u10e0\u10d8"
    ],
    "name:nno_x_preferred":[
        "Bardar"
    ],
    "name:nob_x_preferred":[
        "Bardar"
    ],
    "name:pol_x_preferred":[
        "Bardar"
    ],
    "name:por_x_preferred":[
        "Bardar"
    ],
    "name:ron_x_preferred":[
        "Bardar"
    ],
    "name:rum_x_preferred":[
        "Bardar"
    ],
    "name:rus_x_preferred":[
        "\u0411\u0430\u0440\u0434\u0430\u0440"
    ],
    "name:spa_x_preferred":[
        "Bardar"
    ],
    "name:swe_x_preferred":[
        "Bardar"
    ],
    "name:ukr_x_preferred":[
        "\u0411\u0430\u0440\u0434\u0430\u0440"
    ],
    "name:und_x_preferred":[
        "Bardar"
    ],
    "name:unk_x_variant":[
        "B\u0103rdaru"
    ],
    "qs:a0":"Moldova",
    "qs:a1":"*Ialoveni",
    "qs:a1_alt":"Ialoveni",
    "qs:a1r":"0",
    "qs:adm0":"Moldova",
    "qs:la_lc":"*",
    "qs:level":"locality",
    "qs:loc":"Bardar",
    "qs:loc_alt":"Bardar",
    "qs:pop":0,
    "qs:type":"buffered point",
    "wd:wordcount":33,
    "wof:lang":[
        "unk"
    ],
    "wof:name":"Bardar",
    "wof:placetype":"locality"
},
  "geometry": {"coordinates":[28.669346,46.90176],"type":"Point"}
}