{
  "type": "Feature",
  "properties": {
    "gn:admin1_code":"74.0",
    "gn:asciiname":"Unteni",
    "gn:country_code":"MD",
    "gn:dem":74,
    "gn:feature_class":"P",
    "gn:feature_code":"PPL",
    "gn:name":"Unteni",
    "gn:population":0,
    "gn:timezone":"Europe/Bucharest",
    "iso:country":"MD",
    "name:rus_x_preferred":[
        "\u0423\u043d\u0442\u0435\u043d\u044c"
    ],
    "name:rus_x_variant":[
        "\u0413\u043e\u0440\u0435\u0448\u0442\u044b"
    ],
    "name:und_x_variant":[
        "Goreshty",
        "Unten\u2019",
        "Unteni"
    ],
    "wof:name":"Unteni",
    "wof:placetype":"locality"
},
  "geometry": {"coordinates":[27.57898,47.41612],"type":"Point"}
}