{
  "type": "Feature",
  "properties": {
    "iso:country":"MD",
    "name:bel_x_preferred":[
        "\u0421\u044f\u043b\u043e \u041f\u0430\u0440\u043a\u0430\u043d\u044b"
    ],
    "name:bul_x_preferred":[
        "\u041f\u0430\u0440\u043a\u0430\u043d\u0438"
    ],
    "name:ceb_x_preferred":[
        "Parcani"
    ],
    "name:dan_x_preferred":[
        "Parcani"
    ],
    "name:deu_x_preferred":[
        "Parcani"
    ],
    "name:eng_x_preferred":[
        "Parcani"
    ],
    "name:eus_x_preferred":[
        "Parcani"
    ],
    "name:fra_x_preferred":[
        "Parcani"
    ],
    "name:ita_x_preferred":[
        "Parcani"
    ],
    "name:nld_x_preferred":[
        "Parcani"
    ],
    "name:nno_x_preferred":[
        "Parcani"
    ],
    "name:nob_x_preferred":[
        "Parcani"
    ],
    "name:pol_x_preferred":[
        "Parcani"
    ],
    "name:por_x_preferred":[
        "Parcani"
    ],
    "name:ron_x_preferred":[
        "Parcani"
    ],
    "name:rus_x_preferred":[
        "\u041f\u0430\u0440\u043a\u0430\u043d\u044b"
    ],
    "name:spa_x_preferred":[
        "Parcani"
    ],
    "name:swe_x_preferred":[
        "Parcani"
    ],
    "name:tur_x_preferred":[
        "Parcani"
    ],
    "name:ukr_x_preferred":[
        "\u041f\u0430\u0440\u043a\u0430\u043d\u0438"
    ],
    "name:unk_x_variant":[
        "Parkany"
    ],
    "name:zho_x_preferred":[
        "\u675c\u4f2f\u85a9\u91cc"
    ],
    "qs:a0":"Moldova",
    "qs:a1":"*UAT din St\u00eenga Nistrului",
    "qs:a1_alt":"Unitatile administrativ-teritoriale din stinga Nistrului",
    "qs:a1r":"0",
    "qs:adm0":"Moldova",
    "qs:la_lc":"*",
    "qs:level":"locality",
    "qs:loc":"Parcani",
    "qs:loc_alt":"Parcani",
    "qs:pop":0,
    "qs:type":"buffered point",
    "wd:wordcount":200,
    "wof:name":"Parcani",
    "wof:placetype":"locality"
},
  "geometry": {"coordinates":[29.517877,46.83804],"type":"Point"}
}