{
  "type": "Feature",
  "properties": {
    "iso:country":"MD",
    "name:ceb_x_preferred":[
        "Ofatin\u021bi"
    ],
    "name:dan_x_preferred":[
        "Ofatin\u021bi"
    ],
    "name:deu_x_preferred":[
        "Ofatin\u021bi"
    ],
    "name:eng_x_preferred":[
        "Ofatin\u021bi"
    ],
    "name:eus_x_preferred":[
        "Ofatin\u021bi"
    ],
    "name:fra_x_preferred":[
        "Ofatin\u021bi"
    ],
    "name:ita_x_preferred":[
        "Ofatin\u021bi"
    ],
    "name:ita_x_variant":[
        "Ofatin\u0163i"
    ],
    "name:jpn_x_preferred":[
        "\u30aa\u30d5\u30a1\u30c6\u30a3\u30f3\u30c4\u30a3"
    ],
    "name:nld_x_preferred":[
        "Ofatin\u0163i"
    ],
    "name:nno_x_preferred":[
        "Ofatin\u021bi"
    ],
    "name:nob_x_preferred":[
        "Ofatin\u021bi"
    ],
    "name:pol_x_preferred":[
        "Ofatin\u021bi"
    ],
    "name:por_x_preferred":[
        "Vikhvatinets"
    ],
    "name:por_x_variant":[
        "Ofatin\u021bi"
    ],
    "name:ron_x_preferred":[
        "Ofatin\u021bi"
    ],
    "name:rus_x_preferred":[
        "\u0412\u044b\u0445\u0432\u0430\u0442\u0438\u043d\u0446\u044b"
    ],
    "name:spa_x_preferred":[
        "Ofatin\u021bi"
    ],
    "name:swe_x_preferred":[
        "Ofatin\u021bi"
    ],
    "name:tur_x_preferred":[
        "Ofatin\u021bi"
    ],
    "name:ukr_x_preferred":[
        "\u0412\u0438\u0445\u0432\u0430\u0442\u0438\u043d\u0446\u0456"
    ],
    "name:ukr_x_variant":[
        "\u0425\u0440\u0443\u0441\u0442\u043e\u0432\u0430"
    ],
    "name:unk_x_variant":[
        "Vykhvatintsy"
    ],
    "qs:a0":"Moldova",
    "qs:a1":"*UAT din St\u00eenga Nistrului",
    "qs:a1_alt":"Unitatile administrativ-teritoriale din stinga Nistrului",
    "qs:a1r":"0",
    "qs:adm0":"Moldova",
    "qs:la_lc":"*",
    "qs:level":"locality",
    "qs:loc":"Ofatin\u0163i",
    "qs:loc_alt":"Ofatinti",
    "qs:pop":0,
    "qs:type":"buffered point",
    "wd:wordcount":93,
    "wof:name":"Ofatin\u0163i",
    "wof:placetype":"locality"
},
  "geometry": {"coordinates":[29.000948,47.666474],"type":"Point"}
}