{
  "type": "Feature",
  "properties": {
    "gn:admin1_code":"71.0",
    "gn:asciiname":"Iliciovca",
    "gn:country_code":"MD",
    "gn:dem":190,
    "gn:feature_class":"P",
    "gn:feature_code":"PPL",
    "gn:name":"Iliciovca",
    "gn:population":0,
    "gn:timezone":"Europe/Chisinau",
    "iso:country":"MD",
    "name:ita_x_preferred":[
        "Iliciovca"
    ],
    "name:ron_x_preferred":[
        "Comuna Iliciovca"
    ],
    "name:rus_x_preferred":[
        "Il\u2019ichevka"
    ],
    "name:rus_x_variant":[
        "\u0418\u043b\u044c\u0438\u0447\u0435\u0432\u043a\u0430"
    ],
    "name:und_x_variant":[
        "Il\u2019ich\u00ebvka"
    ],
    "wof:name":"Iliciovca",
    "wof:placetype":"locality"
},
  "geometry": {"coordinates":[27.88013,48.15687],"type":"Point"}
}