{
  "type": "Feature",
  "properties": {
    "gn:admin1_code":"74.0",
    "gn:asciiname":"Catranic",
    "gn:country_code":"MD",
    "gn:dem":129,
    "gn:feature_class":"P",
    "gn:feature_code":"PPL",
    "gn:name":"Catran\u00eec",
    "gn:population":0,
    "gn:timezone":"Europe/Chisinau",
    "iso:country":"MD",
    "name:ita_x_preferred":[
        "Catran\u00eec"
    ],
    "name:kat_x_preferred":[
        "\u10d9\u10d0\u10e0\u10e2\u10d0\u10dc\u10d8\u10d9\u10d8"
    ],
    "name:ron_x_preferred":[
        "Catran\u00eec"
    ],
    "name:rus_x_preferred":[
        "\u041a\u0430\u0442\u0440\u0430\u043d\u044b\u043a"
    ],
    "name:ukr_x_preferred":[
        "\u041a\u0430\u0442\u0440\u0430\u043d\u0438\u043a"
    ],
    "name:und_x_variant":[
        "Katranyk",
        "Aleksandreny",
        "Catran\u00eec"
    ],
    "wof:name":"Catranic",
    "wof:placetype":"locality"
},
  "geometry": {"coordinates":[27.803,47.59621],"type":"Point"}
}