{
  "type": "Feature",
  "properties": {
    "iso:country":"MD",
    "name:ceb_x_preferred":[
        "Lopatnic"
    ],
    "name:dan_x_preferred":[
        "Lopatnic"
    ],
    "name:deu_x_preferred":[
        "Lopatnic"
    ],
    "name:eng_x_preferred":[
        "Lopatnik"
    ],
    "name:eng_x_variant":[
        "Lopatnic"
    ],
    "name:eus_x_preferred":[
        "Lopatnic"
    ],
    "name:fra_x_preferred":[
        "Lopatnic"
    ],
    "name:ita_x_preferred":[
        "Lopatnic"
    ],
    "name:kat_x_preferred":[
        "\u10da\u10dd\u10de\u10d0\u10e2\u10dc\u10d8\u10d9\u10d8"
    ],
    "name:nld_x_preferred":[
        "Lopatnic"
    ],
    "name:nno_x_preferred":[
        "Lopatnic"
    ],
    "name:nob_x_preferred":[
        "Lopatnic"
    ],
    "name:pol_x_preferred":[
        "Lopatnic"
    ],
    "name:por_x_preferred":[
        "Lopatnic"
    ],
    "name:ron_x_preferred":[
        "Lopatnic"
    ],
    "name:rus_x_preferred":[
        "\u041b\u043e\u043f\u0430\u0442\u043d\u0438\u043a"
    ],
    "name:spa_x_preferred":[
        "Lopatnic"
    ],
    "name:swe_x_preferred":[
        "Lopatnic"
    ],
    "name:ukr_x_preferred":[
        "\u041b\u043e\u043f\u0430\u0442\u043d\u0456\u043a"
    ],
    "name:zho_x_preferred":[
        "\u5967\u514b\u5c3c\u5bdf"
    ],
    "qs:a0":"Moldova",
    "qs:a1":"*Edine\u0163",
    "qs:a1_alt":"Edinet",
    "qs:a1r":"0",
    "qs:adm0":"Moldova",
    "qs:la_lc":"*",
    "qs:level":"locality",
    "qs:loc":"Lopatnic",
    "qs:loc_alt":"Lopatnic",
    "qs:pop":0,
    "qs:type":"buffered point",
    "wd:wordcount":67,
    "wof:lang":[
        "unk"
    ],
    "wof:name":"Lopatnic",
    "wof:placetype":"locality"
},
  "geometry": {"coordinates":[27.056168,48.134754],"type":"Point"}
}