{
  "type": "Feature",
  "properties": {
    "gn:population":9435,
    "iso:country":"MD",
    "name:eng_x_preferred":[
        "Dondyushany"
    ],
    "name:eng_x_variant":[
        "Dondushen'"
    ],
    "name:fin_x_preferred":[
        "Dondu\u0219eni"
    ],
    "name:ind_x_preferred":[
        "Dondu\u015feni"
    ],
    "name:ita_x_preferred":[
        "Dondu\u0219eni"
    ],
    "name:kat_x_preferred":[
        "\u10d3\u10dd\u10dc\u10d3\u10e3\u10e8\u10d4\u10dc\u10d8"
    ],
    "name:kor_x_preferred":[
        "\ub3c8\ub450\uc170\ub2c8"
    ],
    "name:lit_x_preferred":[
        "Dondu\u0161enis"
    ],
    "name:nld_x_preferred":[
        "Dondu\u0219eni"
    ],
    "name:pnb_x_preferred":[
        "\u062f\u0648\u0646\u062f\u0648\u0634\u06cc\u0646\u06cc"
    ],
    "name:pol_x_preferred":[
        "Dondu\u0219eni"
    ],
    "name:ron_x_preferred":[
        "Dondu\u0219eni"
    ],
    "name:rus_x_preferred":[
        "\u0414\u043e\u043d\u0434\u044e\u0448\u0430\u043d\u044b"
    ],
    "name:spa_x_preferred":[
        "Dondu\u0219eni"
    ],
    "name:ukr_x_preferred":[
        "\u0414\u043e\u043d\u0434\u0443\u0448\u0435\u043d\u044c"
    ],
    "name:und_x_colloquial":[
        "Dondusani",
        "Donduseni"
    ],
    "name:und_x_preferred":[
        "Dondu\u015feni"
    ],
    "name:und_x_variant":[
        "Dondu\u015f\u0103ni"
    ],
    "name:unk_x_variant":[
        "Dondu\u015f\u0103ni"
    ],
    "qs:a0":"Moldova",
    "qs:a1":"*Dondu\u015feni",
    "qs:a1_alt":"Donduseni",
    "qs:a1r":"0",
    "qs:adm0":"Moldova",
    "qs:la_lc":"*",
    "qs:level":"locality",
    "qs:loc":"Dondu\u015feni",
    "qs:loc_alt":"Donduseni",
    "qs:pop":0,
    "qs:type":"buffered point",
    "wd:wordcount":79,
    "wof:name":"Dondu\u015feni",
    "wof:placetype":"locality",
    "wof:population":9435
},
  "geometry": {"coordinates":[27.584965,48.226494],"type":"Point"}
}