{
  "type": "Feature",
  "properties": {
    "iso:country":"MD",
    "name:deu_x_preferred":[
        "T\u00eernova"
    ],
    "name:eng_x_preferred":[
        "Tyrnovi"
    ],
    "name:eng_x_variant":[
        "Tyrnova",
        "Tyrnovo",
        "T\u00eernova"
    ],
    "name:fra_x_preferred":[
        "T\u00eernova"
    ],
    "name:frr_x_preferred":[
        "T\u00eernova"
    ],
    "name:ita_x_preferred":[
        "T\u00eernova"
    ],
    "name:nld_x_preferred":[
        "T\u00eernova"
    ],
    "name:ron_x_preferred":[
        "T\u00eernova"
    ],
    "name:rus_x_preferred":[
        "\u0422\u044b\u0440\u043d\u043e\u0432\u043e"
    ],
    "name:ukr_x_preferred":[
        "\u0422\u0438\u0440\u043d\u043e\u0432\u0430"
    ],
    "name:und_x_colloquial":[
        "Tarnova",
        "Tirnova"
    ],
    "name:und_x_variant":[
        "T\u00e2rnova"
    ],
    "qs:a0":"Moldova",
    "qs:a1":"*Dondu\u015feni",
    "qs:a1_alt":"Donduseni",
    "qs:a1r":"0",
    "qs:adm0":"Moldova",
    "qs:la_lc":"*",
    "qs:level":"locality",
    "qs:loc":"T\u00eernova",
    "qs:loc_alt":"Tirnova",
    "qs:pop":0,
    "qs:type":"buffered point",
    "wd:wordcount":26,
    "wof:lang":[
        "unk"
    ],
    "wof:name":"T\u00eernova",
    "wof:placetype":"locality"
},
  "geometry": {"coordinates":[27.658031,48.166763],"type":"Point"}
}