{
  "type": "Feature",
  "properties": {
    "iso:country":"MD",
    "name:ceb_x_preferred":[
        "Nuc\u0103reni"
    ],
    "name:dan_x_preferred":[
        "Nuc\u0103reni"
    ],
    "name:deu_x_preferred":[
        "Nuc\u0103reni"
    ],
    "name:eng_x_preferred":[
        "Nuc\u0103reni"
    ],
    "name:eus_x_preferred":[
        "Nuc\u0103reni"
    ],
    "name:fra_x_preferred":[
        "Nuc\u0103reni"
    ],
    "name:ita_x_preferred":[
        "Nuc\u0103reni"
    ],
    "name:kat_x_preferred":[
        "\u10dc\u10e3\u10d9\u10d4\u10e0\u10d4\u10dc\u10d8"
    ],
    "name:nld_x_preferred":[
        "Nuc\u0103reni"
    ],
    "name:nno_x_preferred":[
        "Nuc\u0103reni"
    ],
    "name:nob_x_preferred":[
        "Nuc\u0103reni"
    ],
    "name:pol_x_preferred":[
        "Nuc\u0103reni"
    ],
    "name:por_x_preferred":[
        "Nuc\u0103reni"
    ],
    "name:ron_x_preferred":[
        "Nuc\u0103reni"
    ],
    "name:rus_x_preferred":[
        "\u041d\u0443\u043a\u044d\u0440\u0435\u043d\u044c"
    ],
    "name:spa_x_preferred":[
        "Nuc\u0103reni"
    ],
    "name:swe_x_preferred":[
        "Nuc\u0103reni"
    ],
    "name:ukr_x_preferred":[
        "\u041d\u0443\u043a\u0435\u0440\u0435\u043d\u044c"
    ],
    "name:ukr_x_variant":[
        "\u041f\u0435\u0440\u0435\u0441\u0435\u0447\u0438\u043d\u0430"
    ],
    "name:und_x_variant":[
        "Inderapnich\u2019"
    ],
    "qs:a0":"Moldova",
    "qs:a1":"*Telene\u015fti",
    "qs:a1_alt":"Telenesti",
    "qs:a1r":"0",
    "qs:adm0":"Moldova",
    "qs:la_lc":"*",
    "qs:level":"locality",
    "qs:loc":"Nuc\u0103reni",
    "qs:loc_alt":"Nucareni",
    "qs:pop":0,
    "qs:type":"buffered point",
    "wd:wordcount":31,
    "wof:name":"Nuc\u0103reni",
    "wof:placetype":"locality"
},
  "geometry": {"coordinates":[28.58424,47.598484],"type":"Point"}
}