{
  "type": "Feature",
  "properties": {
    "gn:admin1_code":"91.0",
    "gn:asciiname":"Cisla",
    "gn:country_code":"MD",
    "gn:dem":116,
    "gn:feature_class":"P",
    "gn:feature_code":"PPL",
    "gn:name":"C\u00ee\u015fla",
    "gn:population":0,
    "gn:timezone":"Europe/Chisinau",
    "iso:country":"MD",
    "name:ita_x_preferred":[
        "C\u00ee\u0219la"
    ],
    "name:kat_x_preferred":[
        "\u10d9\u10d8\u10e8\u10da\u10d0"
    ],
    "name:ron_x_preferred":[
        "C\u00ee\u0219la"
    ],
    "name:rus_x_preferred":[
        "\u041a\u044b\u0448\u043b\u0430"
    ],
    "name:ukr_x_preferred":[
        "\u041a\u0438\u0448\u043b\u0430"
    ],
    "name:und_x_variant":[
        "Kyshla",
        "C\u00e2\u015fla",
        "C\u00ee\u015fla"
    ],
    "wof:name":"Cisla",
    "wof:placetype":"locality"
},
  "geometry": {"coordinates":[28.22609000000001,47.49345],"type":"Point"}
}