{
  "type": "Feature",
  "properties": {
    "gn:admin1_code":"87.0",
    "gn:asciiname":"Regina Maria",
    "gn:country_code":"MD",
    "gn:dem":167,
    "gn:feature_class":"P",
    "gn:feature_code":"PPL",
    "gn:name":"Regina Maria",
    "gn:population":0,
    "gn:timezone":"Europe/Chisinau",
    "iso:country":"MD",
    "name:ron_x_preferred":[
        "Regina Maria"
    ],
    "name:rus_x_preferred":[
        "\u041a\u043e\u0442\u043e\u0432\u0441\u043a"
    ],
    "name:und_x_variant":[
        "Kotovsk"
    ],
    "wof:name":"Regina Maria",
    "wof:placetype":"locality"
},
  "geometry": {"coordinates":[28.14176,48.05666],"type":"Point"}
}