{
  "type": "Feature",
  "properties": {
    "iso:country":"MD",
    "name:ceb_x_preferred":[
        "Covurlui"
    ],
    "name:dan_x_preferred":[
        "Covurlui"
    ],
    "name:deu_x_preferred":[
        "Covurlui"
    ],
    "name:eng_x_preferred":[
        "Kugurluy"
    ],
    "name:eng_x_variant":[
        "Kovurluy",
        "Kovyrluy",
        "Kuvurluy",
        "Kuvyrluy",
        "Covurlui"
    ],
    "name:eus_x_preferred":[
        "Covurlui"
    ],
    "name:fra_x_preferred":[
        "Covurlui"
    ],
    "name:ita_x_preferred":[
        "Covurlui"
    ],
    "name:kat_x_preferred":[
        "\u10d9\u10dd\u10d5\u10e3\u10e0\u10da\u10e3\u10d8"
    ],
    "name:nld_x_preferred":[
        "Covurlui"
    ],
    "name:nno_x_preferred":[
        "Covurlui"
    ],
    "name:nob_x_preferred":[
        "Covurlui"
    ],
    "name:pol_x_preferred":[
        "Covurlui"
    ],
    "name:por_x_preferred":[
        "Covurlui"
    ],
    "name:ron_x_preferred":[
        "Covurlui"
    ],
    "name:ron_x_variant":[
        "T\u00eer\u015fi\u0163ei"
    ],
    "name:rus_x_preferred":[
        "\u041a\u043e\u0432\u0443\u0440\u043b\u0443\u0439"
    ],
    "name:rus_x_variant":[
        "\u041a\u043e\u0432\u044b\u0440\u043b\u0443\u0439"
    ],
    "name:spa_x_preferred":[
        "Covurlui"
    ],
    "name:swe_x_preferred":[
        "Covurlui"
    ],
    "name:ukr_x_preferred":[
        "\u041a\u043e\u0432\u0443\u0440\u043b\u0443\u0439"
    ],
    "name:und_x_preferred":[
        "Covurlui"
    ],
    "name:unk_x_variant":[
        "Kugurluy"
    ],
    "qs:a0":"Moldova",
    "qs:a1":"*Leova",
    "qs:a1_alt":"Leova",
    "qs:a1r":"0",
    "qs:adm0":"Moldova",
    "qs:la_lc":"*",
    "qs:level":"locality",
    "qs:loc":"Covurlui",
    "qs:loc_alt":"Covurlui",
    "qs:pop":0,
    "qs:type":"buffered point",
    "wd:wordcount":67,
    "wof:lang":[
        "unk"
    ],
    "wof:name":"Covurlui",
    "wof:placetype":"locality"
},
  "geometry": {"coordinates":[28.398248,46.593574],"type":"Point"}
}