{
  "type": "Feature",
  "properties": {
    "gn:admin1_code":"87.0",
    "gn:asciiname":"Alexandru cel Bun",
    "gn:country_code":"MD",
    "gn:dem":185,
    "gn:feature_class":"P",
    "gn:feature_code":"PPL",
    "gn:name":"Alexandru cel Bun",
    "gn:population":0,
    "gn:timezone":"Europe/Chisinau",
    "iso:country":"MD",
    "name:rus_x_preferred":[
        "\u0410\u043b\u0435\u043a\u0441\u0430\u043d\u0434\u0440\u0443-\u0447\u0435\u043b-\u0411\u0443\u043d"
    ],
    "name:und_x_variant":[
        "Aleksandru-chel-Bun",
        "Alexandru cel Bun"
    ],
    "wof:name":"Alexandru cel Bun",
    "wof:placetype":"locality"
},
  "geometry": {"coordinates":[28.34013,48.09667],"type":"Point"}
}