{
  "type": "Feature",
  "properties": {
    "gn:admin1_code":"75.0",
    "gn:asciiname":"Hirtop",
    "gn:country_code":"MD",
    "gn:dem":62,
    "gn:feature_class":"P",
    "gn:feature_code":"PPL",
    "gn:name":"H\u00eertop",
    "gn:population":0,
    "gn:timezone":"Europe/Chisinau",
    "iso:country":"MD",
    "name:rus_x_preferred":[
        "\u0413\u044b\u0440\u0442\u043e\u043f"
    ],
    "name:und_x_variant":[
        "Gyrtop",
        "H\u00eertop"
    ],
    "wof:name":"Hirtop",
    "wof:placetype":"locality"
},
  "geometry": {"coordinates":[28.48418,47.70612],"type":"Point"}
}