{
  "type": "Feature",
  "properties": {
    "iso:country":"MD",
    "name:che_x_preferred":[
        "\u0421\u0443\u0434\u0430\u0440\u043a\u0430"
    ],
    "name:eng_x_preferred":[
        "Sudarka"
    ],
    "name:eng_x_variant":[
        "Sudarca"
    ],
    "name:fra_x_preferred":[
        "Sudarca"
    ],
    "name:gle_x_preferred":[
        "Sudarca"
    ],
    "name:ita_x_preferred":[
        "Sudarca"
    ],
    "name:kat_x_preferred":[
        "\u10e1\u10e3\u10d3\u10d0\u10e0\u10d9\u10d0"
    ],
    "name:nld_x_preferred":[
        "Sudarca"
    ],
    "name:ron_x_preferred":[
        "Sudarca"
    ],
    "name:rus_x_preferred":[
        "\u0421\u0443\u0434\u0430\u0440\u043a\u0430"
    ],
    "name:spa_x_preferred":[
        "Sudarca"
    ],
    "name:tat_x_preferred":[
        "\u0421\u0443\u0434\u0430\u0440\u043a\u0430"
    ],
    "name:ukr_x_preferred":[
        "\u0421\u0443\u0434\u0430\u0440\u043a\u0430"
    ],
    "qs:a0":"Moldova",
    "qs:a1":"*Dondu\u015feni",
    "qs:a1_alt":"Donduseni",
    "qs:a1r":"0",
    "qs:adm0":"Moldova",
    "qs:la_lc":"*",
    "qs:level":"locality",
    "qs:loc":"Sudarca",
    "qs:loc_alt":"Sudarca",
    "qs:pop":0,
    "qs:type":"buffered point",
    "wd:wordcount":34,
    "wof:lang":[
        "unk"
    ],
    "wof:name":"Sudarca",
    "wof:placetype":"locality"
},
  "geometry": {"coordinates":[27.784858,48.304134],"type":"Point"}
}