{
  "type": "Feature",
  "properties": {
    "gn:population":7200,
    "iso:country":"MD",
    "name:ast_x_preferred":[
        "S\u00eengera"
    ],
    "name:bul_x_preferred":[
        "\u0421\u044a\u043d\u0434\u0436\u0435\u0440\u0430"
    ],
    "name:ceb_x_preferred":[
        "S\u00eengera"
    ],
    "name:eng_x_preferred":[
        "Synzhera"
    ],
    "name:eng_x_variant":[
        "S\u00eengera"
    ],
    "name:fra_x_preferred":[
        "S\u00eengera"
    ],
    "name:hsb_x_preferred":[
        "S\u00eengera"
    ],
    "name:ita_x_preferred":[
        "S\u00eengera"
    ],
    "name:lit_x_preferred":[
        "Sind\u017eera"
    ],
    "name:mdf_x_preferred":[
        "\u0421\u044b\u043d\u0434\u0436\u044d\u0440\u0430"
    ],
    "name:nld_x_preferred":[
        "S\u00eengera"
    ],
    "name:pol_x_preferred":[
        "S\u00eengera"
    ],
    "name:ron_x_preferred":[
        "S\u00eengera"
    ],
    "name:rus_x_preferred":[
        "\u0421\u044b\u043d\u0434\u0436\u0435\u0440\u0430"
    ],
    "name:rus_x_variant":[
        "\u0421\u044b\u043d\u0436\u0435\u0440\u0430"
    ],
    "name:srp_x_preferred":[
        "\u0421\u0438\u043d\u0452\u0435\u0440\u0430"
    ],
    "name:swe_x_preferred":[
        "S\u00eengera"
    ],
    "name:ukr_x_preferred":[
        "\u0421\u0438\u043d\u0434\u0436\u0435\u0440\u0430"
    ],
    "name:und_x_colloquial":[
        "Sangera",
        "Singera"
    ],
    "name:und_x_variant":[
        "S\u00e2ngera"
    ],
    "qs:a0":"Moldova",
    "qs:a1":"*mun.Chi\u015fin\u0103u",
    "qs:a1_alt":"Chisinau",
    "qs:a1r":"0",
    "qs:adm0":"Moldova",
    "qs:la_lc":"*",
    "qs:level":"locality",
    "qs:loc":"S\u00eengera",
    "qs:loc_alt":"Singera",
    "qs:pop":0,
    "qs:type":"buffered point",
    "wd:wordcount":106,
    "wof:lang":[
        "unk"
    ],
    "wof:name":"S\u00eengera",
    "wof:placetype":"locality",
    "wof:population":7200
},
  "geometry": {"coordinates":[28.971064,46.912023],"type":"Point"}
}