{
  "type": "Feature",
  "properties": {
    "iso:country":"MD",
    "name:cym_x_preferred":[
        "Dr\u0103g\u0103ne\u0219ti"
    ],
    "name:eng_x_preferred":[
        "Dr\u0103g\u0103ne\u0219ti"
    ],
    "name:ita_x_preferred":[
        "Dr\u0103g\u0103ne\u0219ti"
    ],
    "name:ita_x_variant":[
        "Dr\u0103g\u0103ne\u015fti"
    ],
    "name:kat_x_preferred":[
        "\u10d3\u10e0\u10d4\u10d2\u10d4\u10dc\u10d4\u10e8\u10e2\u10d8"
    ],
    "name:nld_x_preferred":[
        "Dr\u0103g\u0103ne\u015fti"
    ],
    "name:ron_x_preferred":[
        "Dr\u0103g\u0103ne\u0219ti"
    ],
    "name:rus_x_preferred":[
        "\u0414\u0440\u044d\u0433\u044d\u043d\u0435\u0448\u0442\u044c"
    ],
    "name:rus_x_variant":[
        "\u0414\u0440\u0430\u0433\u0430\u043d\u0435\u0448\u0442\u044b"
    ],
    "name:ukr_x_preferred":[
        "\u0414\u0440\u0435\u0433\u0435\u043d\u0435\u0448\u0442\u0438"
    ],
    "name:und_x_preferred":[
        "Dragoneshty"
    ],
    "name:unk_x_variant":[
        "Dregeneshti"
    ],
    "qs:a0":"Moldova",
    "qs:a1":"*S\u00eengerei",
    "qs:a1_alt":"Singerei",
    "qs:a1r":"0",
    "qs:adm0":"Moldova",
    "qs:la_lc":"*",
    "qs:level":"locality",
    "qs:loc":"Dr\u0103g\u0103ne\u015fti",
    "qs:loc_alt":"Draganesti",
    "qs:pop":0,
    "qs:type":"buffered point",
    "wd:wordcount":22,
    "wof:lang":[
        "unk"
    ],
    "wof:name":"Dr\u0103g\u0103ne\u015fti",
    "wof:placetype":"locality"
},
  "geometry": {"coordinates":[28.25139,47.7169],"type":"Point"}
}