{
  "type": "Feature",
  "properties": {
    "gn:admin1_code":"74.0",
    "gn:asciiname":"Magura Noua",
    "gn:country_code":"MD",
    "gn:dem":112,
    "gn:feature_class":"P",
    "gn:feature_code":"PPL",
    "gn:name":"M\u0103gura Nou\u0103",
    "gn:population":0,
    "gn:timezone":"Europe/Chisinau",
    "iso:country":"MD",
    "name:rus_x_preferred":[
        "\u041d\u043e\u0432\u0430\u044f \u041c\u044d\u0433\u0443\u0440\u0430"
    ],
    "name:und_x_variant":[
        "Novaya Megura",
        "M\u0103gura Nou\u0103"
    ],
    "wof:name":"Magura Noua",
    "wof:placetype":"locality"
},
  "geometry": {"coordinates":[27.95185,47.50613],"type":"Point"}
}