{
  "type": "Feature",
  "properties": {
    "gn:admin1_code":"80.0",
    "gn:asciiname":"Selisteni",
    "gn:country_code":"MD",
    "gn:dem":89,
    "gn:feature_class":"P",
    "gn:feature_code":"PPL",
    "gn:name":"Seli\u015fteni",
    "gn:population":0,
    "gn:timezone":"Europe/Chisinau",
    "iso:country":"MD",
    "name:rus_x_preferred":[
        "\u0421\u0435\u043b\u0438\u0448\u0442\u0435\u043d\u044b"
    ],
    "name:und_x_variant":[
        "Selishteny",
        "Seli\u015fteni"
    ],
    "wof:name":"Selisteni",
    "wof:placetype":"locality"
},
  "geometry": {"coordinates":[28.06866,47.06224],"type":"Point"}
}