{
  "type": "Feature",
  "properties": {
    "gn:admin1_code":"84.0",
    "gn:asciiname":"Butesti",
    "gn:country_code":"MD",
    "gn:dem":105,
    "gn:feature_class":"P",
    "gn:feature_code":"PPL",
    "gn:name":"Bute\u015fti",
    "gn:population":0,
    "gn:timezone":"Europe/Chisinau",
    "iso:country":"MD",
    "name:rus_x_preferred":[
        "\u0411\u0443\u0442\u0435\u0448\u0442\u044b"
    ],
    "name:und_x_variant":[
        "Butesht\u2019",
        "Buteshty",
        "Buteshti",
        "Bute\u015fti"
    ],
    "wof:name":"Butesti",
    "wof:placetype":"locality"
},
  "geometry": {"coordinates":[27.33316,47.79685],"type":"Point"}
}