{
  "type": "Feature",
  "properties": {
    "iso:country":"MD",
    "name:ceb_x_preferred":[
        "Cri\u0219c\u0103u\u021bi"
    ],
    "name:dan_x_preferred":[
        "Cri\u0219c\u0103u\u021bi"
    ],
    "name:deu_x_preferred":[
        "Cri\u0219c\u0103u\u021bi"
    ],
    "name:eng_x_preferred":[
        "Krishkauts'"
    ],
    "name:eng_x_variant":[
        "Krishkautsy",
        "Cri\u0219c\u0103u\u021bi"
    ],
    "name:eus_x_preferred":[
        "Cri\u0219c\u0103u\u021bi"
    ],
    "name:fra_x_preferred":[
        "Cri\u0219c\u0103u\u021bi"
    ],
    "name:ita_x_preferred":[
        "Cri\u0219c\u0103u\u021bi"
    ],
    "name:ita_x_variant":[
        "Cri\u015fc\u0103u\u0163i"
    ],
    "name:kat_x_preferred":[
        "\u10d9\u10e0\u10d8\u10e8\u10d9\u10d4\u10e3\u10ea\u10d8"
    ],
    "name:nld_x_preferred":[
        "Cri\u015fc\u0103u\u0163i"
    ],
    "name:nno_x_preferred":[
        "Cri\u0219c\u0103u\u021bi"
    ],
    "name:nob_x_preferred":[
        "Cri\u0219c\u0103u\u021bi"
    ],
    "name:pol_x_preferred":[
        "Cri\u0219c\u0103u\u021bi"
    ],
    "name:por_x_preferred":[
        "Cri\u0219c\u0103u\u021bi"
    ],
    "name:ron_x_preferred":[
        "Cri\u0219c\u0103u\u021bi"
    ],
    "name:rus_x_preferred":[
        "\u041a\u0440\u0438\u0448\u043a\u0430\u0443\u0446\u044b"
    ],
    "name:spa_x_preferred":[
        "Cri\u0219c\u0103u\u021bi"
    ],
    "name:swe_x_preferred":[
        "Cri\u0219c\u0103u\u021bi"
    ],
    "name:ukr_x_preferred":[
        "\u041a\u0440\u0456\u0448\u043a\u0430\u0443\u0446\u044c"
    ],
    "name:ukr_x_variant":[
        "\u0426\u0430\u0443\u043b"
    ],
    "name:und_x_colloquial":[
        "Criscauti"
    ],
    "name:und_x_preferred":[
        "Cri\u015fc\u0103u\u0163i"
    ],
    "name:unk_x_variant":[
        "Krishkauts\u2019"
    ],
    "qs:a0":"Moldova",
    "qs:a1":"*Dondu\u015feni",
    "qs:a1_alt":"Donduseni",
    "qs:a1r":"0",
    "qs:adm0":"Moldova",
    "qs:la_lc":"*",
    "qs:level":"locality",
    "qs:loc":"Cri\u015fc\u0103u\u0163i",
    "qs:loc_alt":"Criscauti",
    "qs:pop":0,
    "qs:type":"buffered point",
    "wd:wordcount":33,
    "wof:lang":[
        "unk"
    ],
    "wof:name":"Cri\u015fc\u0103u\u0163i",
    "wof:placetype":"locality"
},
  "geometry": {"coordinates":[27.855339,48.265778],"type":"Point"}
}