{
  "type": "Feature",
  "properties": {
    "gn:gn_country":"MD",
    "gn:gn_fcode":"PPLA",
    "gn:gn_pop":6633,
    "gn:population":6633,
    "iso:country":"MD",
    "name:chi_x_preferred":[
        "\u6cf0\u840a\u5167\u4ec0\u8482"
    ],
    "name:dut_x_preferred":[
        "Telene\u0219ti"
    ],
    "name:eng_x_preferred":[
        "Telene\u0219ti"
    ],
    "name:fin_x_preferred":[
        "Telene\u0219ti"
    ],
    "name:fre_x_preferred":[
        "Telene\u0219ti"
    ],
    "name:heb_x_preferred":[
        "\u05d8\u05dc\u05e0\u05e9\u05d8\u05d9"
    ],
    "name:ind_x_preferred":[
        "Telene\u015fti"
    ],
    "name:ita_x_preferred":[
        "Telene\u0219ti"
    ],
    "name:kor_x_preferred":[
        "\ud154\ub808\ub124\uc288\ud2f0"
    ],
    "name:lit_x_preferred":[
        "Telene\u0161tis"
    ],
    "name:pnb_x_preferred":[
        "\u062a\u06cc\u0644\u06cc\u0646\u06cc\u0634\u062a\u06cc"
    ],
    "name:pol_x_preferred":[
        "Telene\u015fti"
    ],
    "name:rum_x_preferred":[
        "Telene\u0219ti"
    ],
    "name:rus_x_preferred":[
        "\u0422\u0435\u043b\u0435\u043d\u0435\u0448\u0442\u044b"
    ],
    "name:srp_x_preferred":[
        "\u0422\u0435\u043b\u0435\u043d\u0435\u0448\u0442\u0438"
    ],
    "name:swe_x_preferred":[
        "Telene\u015fti"
    ],
    "name:ukr_x_preferred":[
        "\u0422\u0435\u043b\u0435\u043d\u0435\u0448\u0442\u0438"
    ],
    "name:unk_x_variant":[
        "Telene\u015fti T\u00e2rg"
    ],
    "qs_pg:aaroncc":"MD",
    "qs_pg:gn_country":"MD",
    "qs_pg:gn_fcode":"PPLA",
    "qs_pg:gn_pop":6633,
    "qs_pg:name":"Telene\u015fti",
    "qs_pg:name_adm0":"Moldova",
    "qs_pg:name_adm1":"Telenesti",
    "qs_pg:photos_9r":0,
    "qs_pg:photos_sr":0,
    "qs_pg:pop_sr":5,
    "qs_pg:qs_pg_placetype":"locality",
    "qs_pg:qs_pg_placetype_gp":"Town",
    "qs_pg:woe_adm0":23424885,
    "woe:adm0_id":23424885,
    "woe:name_adm0":"Moldova",
    "woe:name_adm1":"Telenesti",
    "woe:placetype":"Town",
    "wof:name":"Telene\u015fti",
    "wof:placetype":"locality",
    "wof:population":6633
},
  "geometry": {"coordinates":[28.36556,47.49972],"type":"Point"}
}