{
  "type": "Feature",
  "properties": {
    "iso:country":"MD",
    "name:ceb_x_preferred":[
        "Cremenciug"
    ],
    "name:dan_x_preferred":[
        "Cremenciug"
    ],
    "name:deu_x_preferred":[
        "Cremenciug"
    ],
    "name:eng_x_preferred":[
        "Cremenciug"
    ],
    "name:eus_x_preferred":[
        "Cremenciug"
    ],
    "name:fra_x_preferred":[
        "Cremenciug"
    ],
    "name:ita_x_preferred":[
        "Cremenciug"
    ],
    "name:kat_x_preferred":[
        "\u10d9\u10e0\u10d4\u10db\u10d4\u10dc\u10e9\u10e3\u10d2\u10d8"
    ],
    "name:nld_x_preferred":[
        "Cremenciug"
    ],
    "name:nno_x_preferred":[
        "Cremenciug"
    ],
    "name:nob_x_preferred":[
        "Cremenciug"
    ],
    "name:por_x_preferred":[
        "Cremenciug"
    ],
    "name:ron_x_preferred":[
        "Cremenciug"
    ],
    "name:rus_x_preferred":[
        "\u041a\u0440\u0435\u043c\u0435\u043d\u0447\u0443\u0433"
    ],
    "name:spa_x_preferred":[
        "Cremenciug"
    ],
    "name:spa_x_variant":[
        "Co\u015ferni\u0163a"
    ],
    "name:swe_x_preferred":[
        "Cremenciug"
    ],
    "name:ukr_x_preferred":[
        "\u041a\u0440\u0435\u043c\u0435\u043d\u0447\u0443\u0433"
    ],
    "name:und_x_variant":[
        "Kremenchug"
    ],
    "qs:a0":"Moldova",
    "qs:a1":"*C\u0103u\u015feni",
    "qs:a1_alt":"Causeni",
    "qs:a1r":"0",
    "qs:adm0":"Moldova",
    "qs:la_lc":"*",
    "qs:level":"locality",
    "qs:loc":"Cremenciug",
    "qs:loc_alt":"Cremenciug",
    "qs:pop":0,
    "qs:type":"buffered point",
    "wd:wordcount":147,
    "wof:lang":[
        "unk"
    ],
    "wof:name":"Cremenciug",
    "wof:placetype":"locality"
},
  "geometry": {"coordinates":[29.671911,46.705403],"type":"Point"}
}