{
  "type": "Feature",
  "properties": {
    "iso:country":"MD",
    "name:baq_x_preferred":[
        "Aluatu"
    ],
    "name:bul_x_preferred":[
        "\u0410\u043b\u0443\u0430\u0442\u0443"
    ],
    "name:dan_x_preferred":[
        "Aluatu"
    ],
    "name:dut_x_preferred":[
        "Aluatu"
    ],
    "name:eng_x_preferred":[
        "Aluat"
    ],
    "name:eng_x_variant":[
        "Alauat",
        "Alaut",
        "Aluatul",
        "Aluatu"
    ],
    "name:fre_x_preferred":[
        "Aluatu"
    ],
    "name:geo_x_preferred":[
        "\u10d0\u10da\u10e3\u10d0\u10e2\u10e3"
    ],
    "name:ger_x_preferred":[
        "Aluatu"
    ],
    "name:ita_x_preferred":[
        "Aluatu"
    ],
    "name:kat_x_preferred":[
        "\u10d0\u10da\u10e3\u10d0\u10e2\u10e3"
    ],
    "name:nno_x_preferred":[
        "Aluatu"
    ],
    "name:nob_x_preferred":[
        "Aluatu"
    ],
    "name:pol_x_preferred":[
        "Aluatu"
    ],
    "name:por_x_preferred":[
        "Aluatu"
    ],
    "name:ron_x_preferred":[
        "Aluatu"
    ],
    "name:rum_x_preferred":[
        "Aluatu"
    ],
    "name:rus_x_preferred":[
        "\u0410\u043b\u0443\u0430\u0442\u0443"
    ],
    "name:rus_x_variant":[
        "\u0410\u043b\u0443\u0430\u0442"
    ],
    "name:spa_x_preferred":[
        "Aluatu"
    ],
    "name:swe_x_preferred":[
        "Aluatu"
    ],
    "name:ukr_x_preferred":[
        "\u0410\u043b\u0443\u0430\u0442\u0443"
    ],
    "name:und_x_preferred":[
        "Aluatu"
    ],
    "name:unk_x_variant":[
        "Alaut"
    ],
    "qs:a0":"Moldova",
    "qs:a1":"*Taraclia",
    "qs:a1_alt":"Taraclia",
    "qs:a1r":"0",
    "qs:adm0":"Moldova",
    "qs:la_lc":"*",
    "qs:level":"locality",
    "qs:loc":"Aluatu",
    "qs:loc_alt":"Aluatu",
    "qs:pop":0,
    "qs:type":"buffered point",
    "wd:wordcount":33,
    "wof:lang":[
        "unk"
    ],
    "wof:name":"Aluatu",
    "wof:placetype":"locality"
},
  "geometry": {"coordinates":[28.581631,45.860532],"type":"Point"}
}