{
  "type": "Feature",
  "properties": {
    "gn:admin1_code":"79.0",
    "gn:asciiname":"Troitca",
    "gn:cc2":"MD",
    "gn:country_code":"MD",
    "gn:dem":104,
    "gn:feature_class":"P",
    "gn:feature_code":"PPL",
    "gn:name":"Troi\u0163ca",
    "gn:population":0,
    "gn:timezone":"Europe/Chisinau",
    "iso:country":"MD",
    "name:und_x_variant":[
        "Troitskoye",
        "Troi\u0163a",
        "Troitsa"
    ],
    "wof:name":"Troitca",
    "wof:placetype":"locality"
},
  "geometry": {"coordinates":[28.54778,46.61139],"type":"Point"}
}