{
  "type": "Feature",
  "properties": {
    "iso:country":"MD",
    "name:ceb_x_preferred":[
        "Zberoaia"
    ],
    "name:dan_x_preferred":[
        "Zberoaia"
    ],
    "name:deu_x_preferred":[
        "Zberoaia"
    ],
    "name:eng_x_preferred":[
        "Zberoaia"
    ],
    "name:eus_x_preferred":[
        "Zberoaia"
    ],
    "name:fra_x_preferred":[
        "Zberoaia"
    ],
    "name:ita_x_preferred":[
        "Zberoaia"
    ],
    "name:kat_x_preferred":[
        "\u10d6\u10d1\u10d4\u10e0\u10dd\u10d0\u10d8\u10d0"
    ],
    "name:nld_x_preferred":[
        "Zberoaia"
    ],
    "name:nno_x_preferred":[
        "Zberoaia"
    ],
    "name:nob_x_preferred":[
        "Zberoaia"
    ],
    "name:pol_x_preferred":[
        "Zberoaia"
    ],
    "name:por_x_preferred":[
        "Zberoaia"
    ],
    "name:ron_x_preferred":[
        "Zberoaia"
    ],
    "name:ron_x_variant":[
        "Comuna Prepeli\u021ba"
    ],
    "name:rus_x_preferred":[
        "\u0417\u0431\u0435\u0440\u043e\u0430\u044f"
    ],
    "name:spa_x_preferred":[
        "Zberoaia"
    ],
    "name:swe_x_preferred":[
        "Zberoaia"
    ],
    "name:ukr_x_preferred":[
        "\u0417\u0431\u0435\u0440\u043e\u0430\u044f"
    ],
    "qs:a0":"Moldova",
    "qs:a1":"*Nisporeni",
    "qs:a1_alt":"Nisporeni",
    "qs:a1r":"0",
    "qs:adm0":"Moldova",
    "qs:la_lc":"*",
    "qs:level":"locality",
    "qs:loc":"Zberoaia",
    "qs:loc_alt":"Zberoaia",
    "qs:pop":0,
    "qs:type":"buffered point",
    "wd:wordcount":78,
    "wof:name":"Zberoaia",
    "wof:placetype":"locality"
},
  "geometry": {"coordinates":[28.108112,46.972027],"type":"Point"}
}