{
  "type": "Feature",
  "properties": {
    "iso:country":"MD",
    "name:ita_x_preferred":[
        "Zberoaia"
    ],
    "name:ron_x_preferred":[
        "Zberoaia"
    ],
    "name:rus_x_preferred":[
        "\u0417\u0431\u0435\u0440\u043e\u0430\u044f"
    ],
    "name:ukr_x_preferred":[
        "\u0417\u0431\u0435\u0440\u043e\u0430\u044f"
    ],
    "qs:a0":"Moldova",
    "qs:a1":"*Nisporeni",
    "qs:a1_alt":"Nisporeni",
    "qs:a1r":"0",
    "qs:adm0":"Moldova",
    "qs:la_lc":"*",
    "qs:level":"locality",
    "qs:loc":"Zberoaia",
    "qs:loc_alt":"Zberoaia",
    "qs:pop":0,
    "qs:type":"buffered point",
    "wd:wordcount":78,
    "wof:name":"Zberoaia",
    "wof:placetype":"locality"
},
  "geometry": {"coordinates":[28.108112,46.972027],"type":"Point"}
}