{
  "type": "Feature",
  "properties": {
    "iso:country":"MD",
    "name:dan_x_preferred":[
        "Tabani"
    ],
    "name:deu_x_preferred":[
        "Tabani"
    ],
    "name:eng_x_preferred":[
        "Taban'"
    ],
    "name:eng_x_variant":[
        "Tabany",
        "Tabani"
    ],
    "name:eus_x_preferred":[
        "Tabani"
    ],
    "name:fra_x_preferred":[
        "Tabani"
    ],
    "name:ita_x_preferred":[
        "Tabani"
    ],
    "name:kat_x_preferred":[
        "\u10e2\u10d0\u10d1\u10d0\u10dc\u10d8"
    ],
    "name:nld_x_preferred":[
        "Tabani"
    ],
    "name:nno_x_preferred":[
        "Tabani"
    ],
    "name:nob_x_preferred":[
        "Tabani"
    ],
    "name:pol_x_preferred":[
        "Tabani"
    ],
    "name:por_x_preferred":[
        "Tabani"
    ],
    "name:ron_x_preferred":[
        "Tabani"
    ],
    "name:rus_x_preferred":[
        "\u0422\u0430\u0431\u0430\u043d\u044b"
    ],
    "name:spa_x_preferred":[
        "Tabani"
    ],
    "name:swe_x_preferred":[
        "Tabani"
    ],
    "name:ukr_x_preferred":[
        "\u0422\u0430\u0431\u0430\u043d\u044c"
    ],
    "name:und_x_preferred":[
        "Tabani"
    ],
    "name:unk_x_variant":[
        "Tabany"
    ],
    "name:vep_x_preferred":[
        "Tabani"
    ],
    "qs:a0":"Moldova",
    "qs:a1":"*Briceni",
    "qs:a1_alt":"Briceni",
    "qs:a1r":"0",
    "qs:adm0":"Moldova",
    "qs:la_lc":"*",
    "qs:level":"locality",
    "qs:loc":"Tabani",
    "qs:loc_alt":"Tabani",
    "qs:pop":0,
    "qs:type":"buffered point",
    "wd:wordcount":30,
    "wof:lang":[
        "unk"
    ],
    "wof:name":"Tabani",
    "wof:placetype":"locality"
},
  "geometry": {"coordinates":[27.099814,48.309845],"type":"Point"}
}