{
  "type": "Feature",
  "properties": {
    "iso:country":"MD",
    "name:ceb_x_preferred":[
        "Cli\u0219ova"
    ],
    "name:dan_x_preferred":[
        "Cli\u0219ova"
    ],
    "name:deu_x_preferred":[
        "Cli\u0219ova"
    ],
    "name:eng_x_preferred":[
        "Klishovo"
    ],
    "name:eng_x_variant":[
        "Ilishova",
        "Klishova",
        "Cli\u0219ova"
    ],
    "name:eus_x_preferred":[
        "Cli\u0219ova"
    ],
    "name:fra_x_preferred":[
        "Cli\u0219ova"
    ],
    "name:ita_x_preferred":[
        "Cli\u0219ova"
    ],
    "name:ita_x_variant":[
        "Cli\u015fova"
    ],
    "name:kat_x_preferred":[
        "\u10d9\u10da\u10d8\u10e8\u10dd\u10d5\u10d0"
    ],
    "name:nld_x_preferred":[
        "Cli\u015fova"
    ],
    "name:nno_x_preferred":[
        "Cli\u0219ova"
    ],
    "name:nob_x_preferred":[
        "Cli\u0219ova"
    ],
    "name:pol_x_preferred":[
        "Cli\u0219ova"
    ],
    "name:por_x_preferred":[
        "Cli\u0219ova"
    ],
    "name:ron_x_preferred":[
        "Cli\u0219ova"
    ],
    "name:rus_x_preferred":[
        "\u041a\u043b\u0438\u0448\u043e\u0432\u043e"
    ],
    "name:spa_x_preferred":[
        "Cli\u0219ova"
    ],
    "name:swe_x_preferred":[
        "Cli\u0219ova"
    ],
    "name:ukr_x_preferred":[
        "\u041a\u043b\u0456\u0448\u043e\u0432\u0430"
    ],
    "name:ukr_x_variant":[
        "\u0421\u0430\u0433\u0430\u0439\u0434\u0430\u043a"
    ],
    "name:und_x_colloquial":[
        "Clisova"
    ],
    "name:und_x_preferred":[
        "Cli\u015fova"
    ],
    "name:unk_x_variant":[
        "Klishovo"
    ],
    "qs:a0":"Moldova",
    "qs:a1":"*Orhei",
    "qs:a1_alt":"Orhei",
    "qs:a1r":"0",
    "qs:adm0":"Moldova",
    "qs:la_lc":"*",
    "qs:level":"locality",
    "qs:loc":"Cli\u015fova",
    "qs:loc_alt":"Clisova",
    "qs:pop":0,
    "qs:type":"buffered point",
    "wd:wordcount":33,
    "wof:lang":[
        "unk"
    ],
    "wof:name":"Cli\u015fova",
    "wof:placetype":"locality"
},
  "geometry": {"coordinates":[28.585905,47.471088],"type":"Point"}
}