{
  "type": "Feature",
  "properties": {
    "iso:country":"MD",
    "name:ces_x_preferred":[
        "H\u0103d\u0103r\u0103u\u021bi"
    ],
    "name:dan_x_preferred":[
        "H\u0103d\u0103r\u0103u\u021bi"
    ],
    "name:deu_x_preferred":[
        "H\u0103d\u0103r\u0103u\u021bi"
    ],
    "name:eng_x_preferred":[
        "Khodoreuts'"
    ],
    "name:eng_x_variant":[
        "Khodoroutsy",
        "H\u0103d\u0103r\u0103u\u021bi"
    ],
    "name:eus_x_preferred":[
        "H\u0103d\u0103r\u0103u\u021bi"
    ],
    "name:fra_x_preferred":[
        "H\u0103d\u0103r\u0103u\u021bi"
    ],
    "name:ita_x_preferred":[
        "H\u0103d\u0103r\u0103u\u021bi"
    ],
    "name:kat_x_preferred":[
        "\u10f0\u10d4\u10d3\u10d4\u10e0\u10d4\u10e3\u10ea\u10d8"
    ],
    "name:nld_x_preferred":[
        "H\u0103d\u0103r\u0103u\u0163i"
    ],
    "name:nno_x_preferred":[
        "H\u0103d\u0103r\u0103u\u021bi"
    ],
    "name:nob_x_preferred":[
        "H\u0103d\u0103r\u0103u\u021bi"
    ],
    "name:pol_x_preferred":[
        "H\u0103d\u0103r\u0103u\u0163i"
    ],
    "name:por_x_preferred":[
        "H\u0103d\u0103r\u0103u\u021bi"
    ],
    "name:ron_x_preferred":[
        "H\u0103d\u0103r\u0103u\u021bi"
    ],
    "name:rus_x_preferred":[
        "\u0425\u044d\u0434\u044d\u0440\u044d\u0443\u0446\u044c"
    ],
    "name:rus_x_variant":[
        "\u0425\u043e\u0434\u043e\u0440\u043e\u0443\u0446\u044b"
    ],
    "name:spa_x_preferred":[
        "H\u0103d\u0103r\u0103u\u021bi"
    ],
    "name:swe_x_preferred":[
        "H\u0103d\u0103r\u0103u\u021bi"
    ],
    "name:ukr_x_preferred":[
        "\u0425\u0435\u0434\u0435\u0440\u0435\u0443\u0446\u044c"
    ],
    "name:und_x_colloquial":[
        "Hadarauti"
    ],
    "name:und_x_preferred":[
        "H\u0103d\u0103r\u0103u\u0163i"
    ],
    "name:unk_x_variant":[
        "Khodoroutsy"
    ],
    "qs:a0":"Moldova",
    "qs:a1":"*Ocni\u0163a",
    "qs:a1_alt":"Ocnita",
    "qs:a1r":"0",
    "qs:adm0":"Moldova",
    "qs:la_lc":"*",
    "qs:level":"locality",
    "qs:loc":"H\u0103d\u0103r\u0103u\u0163i",
    "qs:loc_alt":"Hadarauti",
    "qs:pop":0,
    "qs:type":"buffered point",
    "wd:wordcount":22,
    "wof:lang":[
        "unk"
    ],
    "wof:name":"H\u0103d\u0103r\u0103u\u0163i",
    "wof:placetype":"locality"
},
  "geometry": {"coordinates":[27.338152,48.371865],"type":"Point"}
}