{
  "type": "Feature",
  "properties": {
    "gn:country":"MD",
    "gn:fcode":"PPL",
    "gn:population":0,
    "iso:country":"MD",
    "name:ara_x_preferred":[
        "\u0643\u0648\u0646\u062f\u0631\u064a\u062a\u0627"
    ],
    "name:arz_x_preferred":[
        "\u0643\u0648\u0646\u062f\u0631\u064a\u062a\u0633\u0627"
    ],
    "name:ceb_x_preferred":[
        "Condri\u021ba"
    ],
    "name:dan_x_preferred":[
        "Condri\u021ba"
    ],
    "name:deu_x_preferred":[
        "Condri\u021ba"
    ],
    "name:eng_x_preferred":[
        "Condri\u021ba"
    ],
    "name:eus_x_preferred":[
        "Condri\u021ba"
    ],
    "name:fra_x_preferred":[
        "Condri\u021ba"
    ],
    "name:gle_x_preferred":[
        "Condri\u021ba"
    ],
    "name:ita_x_preferred":[
        "Condri\u0163a"
    ],
    "name:nld_x_preferred":[
        "Condri\u0163a"
    ],
    "name:nno_x_preferred":[
        "Condri\u021ba"
    ],
    "name:nob_x_preferred":[
        "Condri\u021ba"
    ],
    "name:pol_x_preferred":[
        "Condri\u021ba"
    ],
    "name:por_x_preferred":[
        "Condri\u021ba"
    ],
    "name:ron_x_preferred":[
        "Condri\u021ba"
    ],
    "name:rus_x_preferred":[
        "\u041a\u043e\u043d\u0434\u0440\u0438\u0446\u0430"
    ],
    "name:spa_x_preferred":[
        "Condri\u021ba"
    ],
    "name:swe_x_preferred":[
        "Condri\u021ba"
    ],
    "name:ukr_x_preferred":[
        "\u041a\u043e\u043d\u0434\u0440\u0456\u0446\u0430"
    ],
    "name:ukr_x_variant":[
        "Dub\u00e6sari"
    ],
    "name:und_x_variant":[
        "Kondritsa"
    ],
    "qs_pg:aaroncc":"MD",
    "qs_pg:gn_country":"MD",
    "qs_pg:gn_fcode":"PPL",
    "qs_pg:gn_pop":0,
    "qs_pg:name":"Condri\u0163a",
    "qs_pg:name_adm0":"Moldova",
    "qs_pg:name_adm1":"Straseni",
    "qs_pg:photos":24,
    "qs_pg:photos_1k":5,
    "qs_pg:photos_9k":1,
    "qs_pg:photos_9r":1,
    "qs_pg:photos_all":24,
    "qs_pg:photos_sr":1,
    "qs_pg:pop_sr":0,
    "qs_pg:qs_pg_placetype":"locality",
    "qs_pg:qs_pg_placetype_gp":"Town",
    "qs_pg:woe_adm0":23424885,
    "woe:adm0_id":23424885,
    "woe:name_adm0":"Moldova",
    "woe:name_adm1":"Straseni",
    "woe:placetype":"Town",
    "wof:name":"Condri\u0163a",
    "wof:placetype":"locality"
},
  "geometry": {"coordinates":[28.56861,47.05667],"type":"Point"}
}