{
  "type": "Feature",
  "properties": {
    "gn:admin1_code":"76.0",
    "gn:asciiname":"Iablona Noua",
    "gn:cc2":"MD",
    "gn:country_code":"MD",
    "gn:dem":164,
    "gn:feature_class":"P",
    "gn:feature_code":"PPL",
    "gn:name":"Iablona Nou\u0103",
    "gn:population":0,
    "gn:timezone":"Europe/Chisinau",
    "iso:country":"MD",
    "name:und_x_variant":[
        "Novaya Yablona",
        "Iablona Nou\u0103",
        "Yablona Noua"
    ],
    "wof:name":"Iablona Noua",
    "wof:placetype":"locality"
},
  "geometry": {"coordinates":[27.61306,47.81556],"type":"Point"}
}