{
  "type": "Feature",
  "properties": {
    "iso:country":"MD",
    "name:che_x_preferred":[
        "\u0412\u044b\u0441\u043a\u044b\u0443\u0446\u0438"
    ],
    "name:eng_x_preferred":[
        "Vaskautsy"
    ],
    "name:eng_x_variant":[
        "Vaskauts'",
        "Vaskautsi",
        "Vaskovtsy",
        "V\u0103sc\u0103u\u021bi"
    ],
    "name:gle_x_preferred":[
        "V\u0103sc\u0103u\u021bi"
    ],
    "name:heb_x_preferred":[
        "\u05d5\u05e1\u05e7\u05d0\u05d5\u05e5"
    ],
    "name:ita_x_preferred":[
        "V\u0103sc\u0103u\u021bi"
    ],
    "name:ita_x_variant":[
        "V\u0103sc\u0103u\u0163i"
    ],
    "name:kat_x_preferred":[
        "\u10d5\u10d4\u10e1\u10d9\u10d4\u10e3\u10ea\u10d8"
    ],
    "name:nld_x_preferred":[
        "V\u0103sc\u0103u\u0163i"
    ],
    "name:ron_x_preferred":[
        "V\u0103sc\u0103u\u021bi"
    ],
    "name:rus_x_preferred":[
        "\u0412\u0430\u0441\u043a\u0430\u0443\u0446\u044b"
    ],
    "name:spa_x_preferred":[
        "V\u0103sc\u0103u\u021bi"
    ],
    "name:tat_x_preferred":[
        "\u0412\u044b\u0441\u043a\u044b\u0443\u0446\u0438"
    ],
    "name:ukr_x_preferred":[
        "\u0412\u0435\u0441\u043a\u0435\u0443\u0446\u044c"
    ],
    "name:und_x_colloquial":[
        "Vascauti"
    ],
    "qs:a0":"Moldova",
    "qs:a1":"*Flore\u015fti",
    "qs:a1_alt":"Floresti",
    "qs:a1r":"0",
    "qs:adm0":"Moldova",
    "qs:la_lc":"*",
    "qs:level":"locality",
    "qs:loc":"V\u0103sc\u0103u\u0163i",
    "qs:loc_alt":"Vascauti",
    "qs:pop":0,
    "qs:type":"buffered point",
    "wd:wordcount":45,
    "wof:lang":[
        "unk"
    ],
    "wof:name":"V\u0103sc\u0103u\u0163i",
    "wof:placetype":"locality"
},
  "geometry": {"coordinates":[28.508696,47.955421],"type":"Point"}
}