{
  "type": "Feature",
  "properties": {
    "gn:admin1_code":"92.0",
    "gn:asciiname":"Sikovets",
    "gn:country_code":"MD",
    "gn:dem":66,
    "gn:feature_class":"P",
    "gn:feature_code":"PPL",
    "gn:name":"Sikovets",
    "gn:population":0,
    "gn:timezone":"Europe/Chisinau",
    "iso:country":"MD",
    "name:rus_x_preferred":[
        "\u0428\u0438\u043a\u043e\u0432\u0435\u0446"
    ],
    "name:und_x_variant":[
        "Shikovets",
        "\u015eicov\u0103\u0163"
    ],
    "wof:name":"Sikovets",
    "wof:placetype":"locality"
},
  "geometry": {"coordinates":[27.90595,47.10783],"type":"Point"}
}