{
  "type": "Feature",
  "properties": {
    "gn:admin1_code":"75.0",
    "gn:asciiname":"Sevirova",
    "gn:country_code":"MD",
    "gn:dem":100,
    "gn:feature_class":"P",
    "gn:feature_code":"PPL",
    "gn:name":"Sevirova",
    "gn:population":0,
    "gn:timezone":"Europe/Chisinau",
    "iso:country":"MD",
    "name:ita_x_preferred":[
        "Sevirova"
    ],
    "name:ron_x_preferred":[
        "Comuna Sevirova"
    ],
    "name:rus_x_preferred":[
        "\u0421\u0435\u0432\u0438\u0440\u043e\u0432\u043e"
    ],
    "name:und_x_variant":[
        "Sevirovka",
        "Sevirovo",
        "Sevirova"
    ],
    "wof:name":"Sevirova",
    "wof:placetype":"locality"
},
  "geometry": {"coordinates":[28.15077,47.9265],"type":"Point"}
}