{
  "type": "Feature",
  "properties": {
    "gn:admin1_code":"75.0",
    "gn:asciiname":"Rosietici",
    "gn:country_code":"MD",
    "gn:dem":126,
    "gn:feature_class":"P",
    "gn:feature_code":"PPL",
    "gn:name":"Ro\u015fietici",
    "gn:population":0,
    "gn:timezone":"Europe/Chisinau",
    "iso:country":"MD",
    "name:rus_x_preferred":[
        "\u0420\u043e\u0448\u0438\u0435\u0442\u0438\u0447\u044c"
    ],
    "name:und_x_variant":[
        "Novyye Roshiyetichi",
        "Roshiyetichi",
        "Roshiyetich-Nouy",
        "Ro\u015fieticii Noui",
        "Roshiyetich\u2019",
        "Ro\u015fietici"
    ],
    "wof:name":"Rosietici",
    "wof:placetype":"locality"
},
  "geometry": {"coordinates":[28.40271,47.83049000000001],"type":"Point"}
}