{
  "type": "Feature",
  "properties": {
    "gn:admin1_code":"64.0",
    "gn:asciiname":"Spicoasa",
    "gn:country_code":"MD",
    "gn:dem":110,
    "gn:feature_class":"P",
    "gn:feature_code":"PPL",
    "gn:name":"Spicoasa",
    "gn:population":0,
    "gn:timezone":"Europe/Chisinau",
    "iso:country":"MD",
    "name:rus_x_preferred":[
        "\u0421\u043f\u0438\u043a\u043e\u0430\u0441\u0430"
    ],
    "name:und_x_variant":[
        "Kochurgoye",
        "Spikoasa",
        "Kochurgoy",
        "Spicoasa"
    ],
    "wof:name":"Spicoasa",
    "wof:placetype":"locality"
},
  "geometry": {"coordinates":[28.37612,46.03415],"type":"Point"}
}