{
  "type": "Feature",
  "properties": {
    "iso:country":"MD",
    "name:ceb_x_preferred":[
        "Ciufle\u0219ti"
    ],
    "name:dan_x_preferred":[
        "Ciufle\u0219ti"
    ],
    "name:deu_x_preferred":[
        "Ciufle\u0219ti"
    ],
    "name:eng_x_preferred":[
        "Chuflesht'"
    ],
    "name:eng_x_variant":[
        "Ciufle\u0219ti"
    ],
    "name:eus_x_preferred":[
        "Ciufle\u0219ti"
    ],
    "name:fra_x_preferred":[
        "Ciufle\u0219ti"
    ],
    "name:ita_x_preferred":[
        "Ciufle\u0219ti"
    ],
    "name:ita_x_variant":[
        "Ciufle\u015fti"
    ],
    "name:kat_x_preferred":[
        "\u10e9\u10e3\u10e4\u10da\u10d4\u10e8\u10e2\u10d8"
    ],
    "name:nld_x_preferred":[
        "Ciufle\u015fti"
    ],
    "name:nno_x_preferred":[
        "Ciufle\u0219ti"
    ],
    "name:nob_x_preferred":[
        "Ciufle\u0219ti"
    ],
    "name:pol_x_preferred":[
        "Ciufle\u0219ti"
    ],
    "name:por_x_preferred":[
        "Ciufle\u0219ti"
    ],
    "name:ron_x_preferred":[
        "Ciufle\u0219ti"
    ],
    "name:rus_x_preferred":[
        "\u0427\u0443\u0444\u043b\u0435\u0448\u0442\u044b"
    ],
    "name:spa_x_preferred":[
        "Ciufle\u0219ti"
    ],
    "name:swe_x_preferred":[
        "Ciufle\u0219ti"
    ],
    "name:ukr_x_preferred":[
        "\u0427\u0443\u0444\u043b\u0435\u0448\u0442\u044c"
    ],
    "name:ukr_x_variant":[
        "\u0413\u0438\u0441\u043a\u0430"
    ],
    "name:und_x_colloquial":[
        "Ciuflesti"
    ],
    "name:und_x_variant":[
        "Chuflesht\u2019"
    ],
    "qs:a0":"Moldova",
    "qs:a1":"*C\u0103u\u015feni",
    "qs:a1_alt":"Causeni",
    "qs:a1r":"0",
    "qs:adm0":"Moldova",
    "qs:la_lc":"*",
    "qs:level":"locality",
    "qs:loc":"Ciufle\u015fti",
    "qs:loc_alt":"Ciuflesti",
    "qs:pop":0,
    "qs:type":"buffered point",
    "wd:wordcount":33,
    "wof:lang":[
        "unk"
    ],
    "wof:name":"Ciufle\u015fti",
    "wof:placetype":"locality"
},
  "geometry": {"coordinates":[28.999241,46.624233],"type":"Point"}
}