{
  "type": "Feature",
  "properties": {
    "iso:country":"MD",
    "name:dan_x_preferred":[
        "Miciurin"
    ],
    "name:deu_x_preferred":[
        "Miciurin"
    ],
    "name:eng_x_preferred":[
        "Gika-Vody"
    ],
    "name:eng_x_variant":[
        "Gika Vode",
        "Michurino",
        "Miciurin"
    ],
    "name:eus_x_preferred":[
        "Miciurin"
    ],
    "name:fra_x_preferred":[
        "Miciurin"
    ],
    "name:ita_x_preferred":[
        "Miciurin"
    ],
    "name:kat_x_preferred":[
        "\u10db\u10d8\u10e9\u10e3\u10e0\u10d8\u10dc\u10d8"
    ],
    "name:nld_x_preferred":[
        "Miciurin"
    ],
    "name:nno_x_preferred":[
        "Miciurin"
    ],
    "name:nob_x_preferred":[
        "Miciurin"
    ],
    "name:pol_x_preferred":[
        "Miciurin"
    ],
    "name:por_x_preferred":[
        "Miciurin"
    ],
    "name:ron_x_preferred":[
        "Miciurin"
    ],
    "name:rus_x_preferred":[
        "\u041c\u0438\u0447\u0443\u0440\u0438\u043d"
    ],
    "name:rus_x_variant":[
        "\u041c\u0438\u0447\u0443\u0440\u0438\u043d\u043e"
    ],
    "name:spa_x_preferred":[
        "Miciurin"
    ],
    "name:swe_x_preferred":[
        "Miciurin"
    ],
    "name:ukr_x_preferred":[
        "\u041c\u0456\u0447\u0443\u0440\u0456\u043d"
    ],
    "name:und_x_colloquial":[
        "Ghica-Voda",
        "Ghica-Vodae"
    ],
    "name:und_x_preferred":[
        "Miciurin"
    ],
    "name:und_x_variant":[
        "Ghica-Vod\u00e6"
    ],
    "name:unk_x_variant":[
        "Ghica-Vod\u0103"
    ],
    "qs:a0":"Moldova",
    "qs:a1":"*Drocia",
    "qs:a1_alt":"Drochia",
    "qs:a1r":"0",
    "qs:adm0":"Moldova",
    "qs:la_lc":"*",
    "qs:level":"locality",
    "qs:loc":"Miciurin",
    "qs:loc_alt":"Miciurin",
    "qs:pop":0,
    "qs:type":"buffered point",
    "wd:wordcount":81,
    "wof:lang":[
        "unk"
    ],
    "wof:name":"Miciurin",
    "wof:placetype":"locality"
},
  "geometry": {"coordinates":[27.792221,47.988609],"type":"Point"}
}