{
  "type": "Feature",
  "properties": {
    "iso:country":"MD",
    "name:eng_x_preferred":[
        "Chokany Noua"
    ],
    "name:eng_x_variant":[
        "Chokany Noua"
    ],
    "name:und_x_preferred":[
        "Novyye Chekany"
    ],
    "name:unk_x_variant":[
        "Novyye Chekany"
    ],
    "qs:gn_adm0_cc":"MD",
    "qs:gn_local":618426,
    "qs:local_max":2628,
    "qs:local_sum":3550,
    "qs:localhoods":5,
    "qs:name":"Novyye Chekany",
    "qs:name_adm0":"Moldova",
    "qs:name_adm1":"Chisinau",
    "qs:name_en":"Chokany Noua",
    "qs:name_local":"Chi\u0163inau",
    "qs:photo_max":23,
    "qs:photo_sum":67,
    "qs:placetype":"Suburb",
    "qs:quad_count":15,
    "qs:woe_adm0":23424885,
    "qs:woe_adm1":20069878,
    "qs:woe_adm2":0,
    "qs:woe_lau":0,
    "qs:woe_local":480793,
    "qs:woe_ver":"7.10.0",
    "wof:lang":[
        "unk"
    ],
    "wof:name":"Novyye Chekany",
    "wof:placetype":"neighbourhood"
},
  "geometry": {"coordinates":[28.897446,47.038309],"type":"Point"}
}