{
  "type": "Feature",
  "properties": {
    "gn:admin1_code":"58.0",
    "gn:asciiname":"Safronovka",
    "gn:cc2":"MD",
    "gn:country_code":"MD",
    "gn:dem":78,
    "gn:feature_class":"P",
    "gn:feature_code":"PPL",
    "gn:name":"Safronovka",
    "gn:population":0,
    "gn:timezone":"Europe/Chisinau",
    "iso:country":"MD",
    "name:und_x_variant":[
        "Safronovskiy"
    ],
    "wof:name":"Safronovka",
    "wof:placetype":"locality"
},
  "geometry": {"coordinates":[29.85,46.83333],"type":"Point"}
}