{
  "type": "Feature",
  "properties": {
    "gn:admin1_code":"81.0",
    "gn:asciiname":"Grinauti-Raia",
    "gn:country_code":"MD",
    "gn:dem":186,
    "gn:feature_class":"P",
    "gn:feature_code":"PPL",
    "gn:name":"Grin\u0103u\u0163i-Raia",
    "gn:population":0,
    "gn:timezone":"Europe/Chisinau",
    "iso:country":"MD",
    "name:rus_x_preferred":[
        "\u0413\u0440\u0438\u043d\u0430\u0443\u0446\u044b-\u0420\u0430\u044f"
    ],
    "name:und_x_variant":[
        "Grinoutsy-Raya",
        "Grinoutsy",
        "Grinauts\u2019",
        "Grinautsy-Raya",
        "Grin\u0103u\u0163i-Raia"
    ],
    "wof:name":"Grinauti-Raia",
    "wof:placetype":"locality"
},
  "geometry": {"coordinates":[27.42895,48.28594],"type":"Point"}
}