{
  "type": "Feature",
  "properties": {
    "iso:country":"MD",
    "name:ceb_x_preferred":[
        "Hlinaia"
    ],
    "name:ces_x_preferred":[
        "Hlinaia"
    ],
    "name:ces_x_variant":[
        "Glinoje"
    ],
    "name:dan_x_preferred":[
        "Hlinaia"
    ],
    "name:deu_x_preferred":[
        "Hlinaia"
    ],
    "name:eng_x_preferred":[
        "Hlinaia"
    ],
    "name:eus_x_preferred":[
        "Hlinaia"
    ],
    "name:fra_x_preferred":[
        "Hlinaia"
    ],
    "name:ita_x_preferred":[
        "Hlinaia"
    ],
    "name:nld_x_preferred":[
        "Hlinaia"
    ],
    "name:nno_x_preferred":[
        "Hlinaia"
    ],
    "name:nob_x_preferred":[
        "Hlinaia"
    ],
    "name:pol_x_preferred":[
        "Hlinaia"
    ],
    "name:por_x_preferred":[
        "Hlinaia"
    ],
    "name:ron_x_preferred":[
        "Hlinaia"
    ],
    "name:rus_x_preferred":[
        "\u0413\u043b\u0438\u043d\u043e\u0435"
    ],
    "name:spa_x_preferred":[
        "Hlinaia"
    ],
    "name:swe_x_preferred":[
        "Hlinaia"
    ],
    "name:tur_x_preferred":[
        "Hlinaia"
    ],
    "name:ukr_x_preferred":[
        "\u0413\u043b\u0438\u043d\u043d\u0435"
    ],
    "name:ukr_x_variant":[
        "\u041d\u043e\u0432\u043e\u0442\u0438\u0440\u0430\u0441\u043f\u043e\u043b\u044c\u0441\u044c\u043a\u0438\u0439"
    ],
    "name:und_x_variant":[
        "Glinnoje"
    ],
    "qs:a0":"Moldova",
    "qs:a1":"*UAT din St\u00eenga Nistrului",
    "qs:a1_alt":"Unitatile administrativ-teritoriale din stinga Nistrului",
    "qs:a1r":"0",
    "qs:adm0":"Moldova",
    "qs:la_lc":"*",
    "qs:level":"locality",
    "qs:loc":"Hlinaia",
    "qs:loc_alt":"Hlinaia",
    "qs:pop":0,
    "qs:type":"buffered point",
    "wd:wordcount":60,
    "wof:name":"Hlinaia",
    "wof:placetype":"locality"
},
  "geometry": {"coordinates":[29.413677,47.228145],"type":"Point"}
}