{
  "type": "Feature",
  "properties": {
    "gn:admin1_code":"58.0",
    "gn:asciiname":"Ocnita",
    "gn:country_code":"MD",
    "gn:dem":63,
    "gn:feature_class":"P",
    "gn:feature_code":"PPL",
    "gn:name":"Ocni\u0163a",
    "gn:population":815,
    "gn:timezone":"Europe/Chisinau",
    "iso:country":"MD",
    "name:rus_x_preferred":[
        "\u041e\u043a\u043d\u0438\u0446\u0430"
    ],
    "name:und_x_variant":[
        "Oknitsa",
        "Ocni\u0163a"
    ],
    "wof:name":"Ocnita",
    "wof:placetype":"locality",
    "wof:population":815
},
  "geometry": {"coordinates":[28.63558,48.13278],"type":"Point"}
}