{
  "type": "Feature",
  "properties": {
    "iso:country":"MD",
    "name:ceb_x_preferred":[
        "Bumb\u0103ta"
    ],
    "name:dan_x_preferred":[
        "Bumb\u0103ta"
    ],
    "name:deu_x_preferred":[
        "Bumb\u0103ta"
    ],
    "name:eng_x_preferred":[
        "Bumb\u0103ta"
    ],
    "name:eus_x_preferred":[
        "Bumb\u0103ta"
    ],
    "name:fra_x_preferred":[
        "Bumb\u0103ta"
    ],
    "name:ita_x_preferred":[
        "Bumb\u0103ta"
    ],
    "name:kat_x_preferred":[
        "\u10d1\u10e3\u10db\u10d1\u10d4\u10e2\u10d0"
    ],
    "name:nld_x_preferred":[
        "Bumb\u0103ta"
    ],
    "name:nno_x_preferred":[
        "Bumb\u0103ta"
    ],
    "name:nob_x_preferred":[
        "Bumb\u0103ta"
    ],
    "name:pol_x_preferred":[
        "Bumb\u0103ta"
    ],
    "name:por_x_preferred":[
        "Bumb\u0103ta"
    ],
    "name:ron_x_preferred":[
        "Bumb\u0103ta"
    ],
    "name:rus_x_preferred":[
        "\u0411\u0443\u043c\u0431\u044d\u0442\u0430"
    ],
    "name:rus_x_variant":[
        "\u0411\u0443\u043c\u0431\u0430\u0442\u0430"
    ],
    "name:spa_x_preferred":[
        "Bumb\u0103ta"
    ],
    "name:swe_x_preferred":[
        "Bumb\u0103ta"
    ],
    "name:ukr_x_preferred":[
        "\u0411\u0443\u043c\u0431\u0435\u0442\u0430"
    ],
    "name:ukr_x_variant":[
        "\u0421\u0442\u0443\u0440\u0437\u043e\u0432\u043a\u0430"
    ],
    "name:und_x_variant":[
        "Bumbota"
    ],
    "qs:a0":"Moldova",
    "qs:a1":"*Ungheni",
    "qs:a1_alt":"Ungheni",
    "qs:a1r":"0",
    "qs:adm0":"Moldova",
    "qs:la_lc":"*",
    "qs:level":"locality",
    "qs:loc":"Bumb\u0103ta",
    "qs:loc_alt":"Bumbata",
    "qs:pop":0,
    "qs:type":"buffered point",
    "wd:wordcount":77,
    "wof:name":"Bumb\u0103ta",
    "wof:placetype":"locality"
},
  "geometry": {"coordinates":[27.967459,47.341397],"type":"Point"}
}