{
  "type": "Feature",
  "properties": {
    "gn:admin1_code":"83.0",
    "gn:asciiname":"Roscanii de Jos",
    "gn:country_code":"MD",
    "gn:dem":140,
    "gn:feature_class":"P",
    "gn:feature_code":"PPL",
    "gn:name":"Ro\u015fcanii de Jos",
    "gn:population":0,
    "gn:timezone":"Europe/Chisinau",
    "iso:country":"MD",
    "name:ron_x_preferred":[
        "Ro\u015fcanii de Jos"
    ],
    "wof:name":"Roscanii de Jos",
    "wof:placetype":"locality"
},
  "geometry": {"coordinates":[28.7375,47.64667],"type":"Point"}
}