{
  "type": "Feature",
  "properties": {
    "gn:admin1_code":"65.0",
    "gn:asciiname":"Tsarankutsa",
    "gn:country_code":"MD",
    "gn:dem":97,
    "gn:feature_class":"P",
    "gn:feature_code":"PPL",
    "gn:name":"Tsarankutsa",
    "gn:population":0,
    "gn:timezone":"Europe/Chisinau",
    "iso:country":"MD",
    "name:rus_x_preferred":[
        "\u0426\u0430\u0440\u0430\u043d\u043a\u0443\u0446\u0430"
    ],
    "name:und_x_variant":[
        "\u0162\u0103r\u0103ncu\u0163a"
    ],
    "wof:name":"Tsarankutsa",
    "wof:placetype":"locality"
},
  "geometry": {"coordinates":[28.41019,46.10758],"type":"Point"}
}