{
  "type": "Feature",
  "properties": {
    "gn:admin1_code":"84.0",
    "gn:asciiname":"Ceparia",
    "gn:country_code":"MD",
    "gn:dem":156,
    "gn:feature_class":"P",
    "gn:feature_code":"PPL",
    "gn:name":"Cep\u0103ria",
    "gn:population":0,
    "gn:timezone":"Europe/Chisinau",
    "iso:country":"MD",
    "name:rus_x_preferred":[
        "\u0427\u0435\u043f\u0430\u0440\u0438\u044f"
    ],
    "name:und_x_variant":[
        "Cheperiya",
        "Chepariya",
        "Cep\u0103ria"
    ],
    "wof:name":"Ceparia",
    "wof:placetype":"locality"
},
  "geometry": {"coordinates":[27.71511,47.93236],"type":"Point"}
}