{
  "type": "Feature",
  "properties": {
    "iso:country":"MD",
    "name:baq_x_preferred":[
        "Trebis\u0103u\u021bi"
    ],
    "name:dan_x_preferred":[
        "Trebis\u0103u\u021bi"
    ],
    "name:dut_x_preferred":[
        "Trebis\u0103u\u0163i"
    ],
    "name:eng_x_preferred":[
        "Trebiskauts'"
    ],
    "name:eng_x_variant":[
        "Trebisoutsy",
        "Trebis\u0103u\u021bi"
    ],
    "name:fre_x_preferred":[
        "Trebis\u0103u\u021bi"
    ],
    "name:geo_x_preferred":[
        "\u10e2\u10e0\u10d4\u10d1\u10d8\u10e1\u10d4\u10e3\u10ea\u10d8"
    ],
    "name:ger_x_preferred":[
        "Trebis\u0103u\u021bi"
    ],
    "name:ita_x_preferred":[
        "Trebis\u0103u\u021bi"
    ],
    "name:kat_x_preferred":[
        "\u10e2\u10e0\u10d4\u10d1\u10d8\u10e1\u10d4\u10e3\u10ea\u10d8"
    ],
    "name:nno_x_preferred":[
        "Trebis\u0103u\u021bi"
    ],
    "name:nob_x_preferred":[
        "Trebis\u0103u\u021bi"
    ],
    "name:pol_x_preferred":[
        "Trebis\u0103u\u021bi"
    ],
    "name:por_x_preferred":[
        "Trebis\u0103u\u021bi"
    ],
    "name:ron_x_preferred":[
        "Trebis\u0103u\u021bi"
    ],
    "name:rum_x_preferred":[
        "Trebis\u0103u\u021bi"
    ],
    "name:rus_x_preferred":[
        "\u0422\u0440\u0435\u0431\u0438\u0441\u043e\u0443\u0446\u044b"
    ],
    "name:spa_x_preferred":[
        "Trebis\u0103u\u021bi"
    ],
    "name:swe_x_preferred":[
        "Trebis\u0103u\u021bi"
    ],
    "name:ukr_x_preferred":[
        "\u0422\u0440\u0435\u0431\u0456\u0441\u0435\u0443\u0446\u044c"
    ],
    "name:und_x_colloquial":[
        "Trebisauti"
    ],
    "name:und_x_preferred":[
        "Trebis\u0103u\u0163i"
    ],
    "name:unk_x_variant":[
        "Trebiskauts\u2019"
    ],
    "qs:a0":"Moldova",
    "qs:a1":"*Briceni",
    "qs:a1_alt":"Briceni",
    "qs:a1r":"0",
    "qs:adm0":"Moldova",
    "qs:la_lc":"*",
    "qs:level":"locality",
    "qs:loc":"Trebis\u0103u\u0163i",
    "qs:loc_alt":"Trebisauti",
    "qs:pop":0,
    "qs:type":"buffered point",
    "wd:wordcount":57,
    "wof:lang":[
        "unk"
    ],
    "wof:name":"Trebis\u0103u\u0163i",
    "wof:placetype":"locality"
},
  "geometry": {"coordinates":[27.18681,48.352588],"type":"Point"}
}