{
  "type": "Feature",
  "properties": {
    "iso:country":"MD",
    "name:arz_x_preferred":[
        "\u0631\u064a\u062f\u064a\u0648\u0644 \u0645\u0627\u0631\u0649"
    ],
    "name:ceb_x_preferred":[
        "Rediul Mare"
    ],
    "name:che_x_preferred":[
        "\u0420\u0435\u0434\u0438\u0443\u043b \u041c\u0430\u0440\u0435"
    ],
    "name:dan_x_preferred":[
        "Rediul Mare"
    ],
    "name:deu_x_preferred":[
        "Rediul Mare"
    ],
    "name:eng_x_preferred":[
        "Redu-Mare"
    ],
    "name:eng_x_variant":[
        "Redyu-Mare",
        "Rediul Mare"
    ],
    "name:eus_x_preferred":[
        "Rediul Mare"
    ],
    "name:fra_x_preferred":[
        "Rediul Mare"
    ],
    "name:gle_x_preferred":[
        "Rediul Mare"
    ],
    "name:ita_x_preferred":[
        "Rediul Mare"
    ],
    "name:kat_x_preferred":[
        "\u10e0\u10d4\u10d3\u10d8\u10e3\u10da-\u10db\u10d0\u10e0\u10d4"
    ],
    "name:nld_x_preferred":[
        "Rediul Mare"
    ],
    "name:nno_x_preferred":[
        "Rediul Mare"
    ],
    "name:nob_x_preferred":[
        "Rediul Mare"
    ],
    "name:pol_x_preferred":[
        "Rediul Mare"
    ],
    "name:por_x_preferred":[
        "Rediul Mare"
    ],
    "name:ron_x_preferred":[
        "Rediul Mare"
    ],
    "name:ron_x_variant":[
        "Comuna Burl\u0103ne\u0219ti"
    ],
    "name:rus_x_preferred":[
        "\u0420\u0435\u0434\u044e-\u041c\u0430\u0440\u0435"
    ],
    "name:spa_x_preferred":[
        "Rediul Mare"
    ],
    "name:swe_x_preferred":[
        "Rediul Mare"
    ],
    "name:tat_x_preferred":[
        "\u0420\u0435\u0434\u0438\u0443\u043b \u041c\u0430\u0440\u0435"
    ],
    "name:ukr_x_preferred":[
        "\u0420\u0435\u0434\u0456\u0443\u043b-\u041c\u0430\u0440\u0435"
    ],
    "qs:a0":"Moldova",
    "qs:a1":"*Dondu\u015feni",
    "qs:a1_alt":"Donduseni",
    "qs:a1r":"0",
    "qs:adm0":"Moldova",
    "qs:la_lc":"*",
    "qs:level":"locality",
    "qs:loc":"Rediul Mare",
    "qs:loc_alt":"Rediul Mare",
    "qs:pop":0,
    "qs:type":"buffered point",
    "wd:wordcount":31,
    "wof:lang":[
        "unk"
    ],
    "wof:name":"Rediul Mare",
    "wof:placetype":"locality"
},
  "geometry": {"coordinates":[27.519043,48.231205],"type":"Point"}
}