{
  "type": "Feature",
  "properties": {
    "iso:country":"MD",
    "name:eng_x_preferred":[
        "Getslova"
    ],
    "name:eng_x_variant":[
        "Getlova",
        "Getlovo",
        "Ghetlova"
    ],
    "name:fra_x_preferred":[
        "Ghetlova"
    ],
    "name:ita_x_preferred":[
        "Ghetlova"
    ],
    "name:kat_x_preferred":[
        "\u10d2\u10d4\u10e2\u10da\u10dd\u10d5\u10d0"
    ],
    "name:nld_x_preferred":[
        "Ghetlova"
    ],
    "name:ron_x_preferred":[
        "Ghetlova"
    ],
    "name:rus_x_preferred":[
        "\u0413\u0435\u0442\u043b\u043e\u0432\u043e"
    ],
    "name:ukr_x_preferred":[
        "\u0413\u0435\u0442\u043b\u043e\u0432\u0430"
    ],
    "name:und_x_preferred":[
        "Ghetlova"
    ],
    "name:unk_x_variant":[
        "Getslova"
    ],
    "qs:a0":"Moldova",
    "qs:a1":"*Orhei",
    "qs:a1_alt":"Orhei",
    "qs:a1r":"0",
    "qs:adm0":"Moldova",
    "qs:la_lc":"*",
    "qs:level":"locality",
    "qs:loc":"Ghetlova",
    "qs:loc_alt":"Ghetlova",
    "qs:pop":0,
    "qs:type":"buffered point",
    "wd:wordcount":18,
    "wof:lang":[
        "unk"
    ],
    "wof:name":"Ghetlova",
    "wof:placetype":"locality"
},
  "geometry": {"coordinates":[28.531983,47.370426],"type":"Point"}
}