{
  "type": "Feature",
  "properties": {
    "gn:admin1_code":"86.0",
    "gn:asciiname":"Socola",
    "gn:country_code":"MD",
    "gn:dem":51,
    "gn:feature_class":"P",
    "gn:feature_code":"PPL",
    "gn:name":"Socola",
    "gn:population":0,
    "gn:timezone":"Europe/Chisinau",
    "iso:country":"MD",
    "name:ron_x_preferred":[
        "Socola"
    ],
    "name:rus_x_preferred":[
        "\u0421\u043e\u043a\u043e\u043b"
    ],
    "name:und_x_variant":[
        "Sokol"
    ],
    "wof:name":"Socola",
    "wof:placetype":"locality"
},
  "geometry": {"coordinates":[28.81557,47.90698],"type":"Point"}
}