{
  "type": "Feature",
  "properties": {
    "gn:admin1_code":"74.0",
    "gn:asciiname":"Pietrosul Nou",
    "gn:country_code":"MD",
    "gn:dem":110,
    "gn:feature_class":"P",
    "gn:feature_code":"PPL",
    "gn:name":"Pietrosul Nou",
    "gn:population":0,
    "gn:timezone":"Europe/Chisinau",
    "iso:country":"MD",
    "name:rus_x_preferred":[
        "\u041d\u043e\u0432\u044b\u0435 \u041f\u0435\u0442\u0440\u043e\u0441\u044b"
    ],
    "name:und_x_variant":[
        "Novyye Petrosy",
        "Pietrosul Nou"
    ],
    "wof:name":"Pietrosul Nou",
    "wof:placetype":"locality"
},
  "geometry": {"coordinates":[27.76865,47.58207],"type":"Point"}
}