{
  "type": "Feature",
  "properties": {
    "iso:country":"MD",
    "name:bel_x_preferred":[
        "\u0414\u0440\u043e\u043a\u0456\u044f"
    ],
    "name:bul_x_preferred":[
        "\u0414\u0440\u043e\u043a\u0438\u044f"
    ],
    "name:ceb_x_preferred":[
        "Drochia"
    ],
    "name:crh_x_preferred":[
        "Drokiya"
    ],
    "name:eng_x_preferred":[
        "Drochia"
    ],
    "name:est_x_preferred":[
        "Drochia"
    ],
    "name:fin_x_preferred":[
        "Drochia"
    ],
    "name:fra_x_preferred":[
        "Drochia"
    ],
    "name:hsb_x_preferred":[
        "Drochia"
    ],
    "name:hye_x_preferred":[
        "\u0534\u0580\u0578\u056f\u056b\u0561"
    ],
    "name:ind_x_preferred":[
        "Drochia"
    ],
    "name:ita_x_preferred":[
        "Drochia"
    ],
    "name:kat_x_preferred":[
        "\u10d3\u10e0\u10dd\u10d9\u10d8\u10d0"
    ],
    "name:kor_x_preferred":[
        "\ub4dc\ub85c\ud0a4\uc544"
    ],
    "name:lit_x_preferred":[
        "Drokija"
    ],
    "name:mkd_x_preferred":[
        "\u0414\u0440\u043e\u043a\u0438\u0458\u0430"
    ],
    "name:nld_x_preferred":[
        "Drochia"
    ],
    "name:pnb_x_preferred":[
        "\u062f\u0631\u0648\u06a9\u06cc\u0627"
    ],
    "name:pol_x_preferred":[
        "Drochia"
    ],
    "name:ron_x_preferred":[
        "Drochia"
    ],
    "name:rus_x_preferred":[
        "\u0414\u0440\u043e\u043a\u0438\u044f"
    ],
    "name:sah_x_preferred":[
        "\u0414\u0440\u043e\u043a\u0438\u044f"
    ],
    "name:spa_x_preferred":[
        "Drochia"
    ],
    "name:srp_x_preferred":[
        "\u0414\u0440\u043e\u043a\u0438\u0458\u0430"
    ],
    "name:swe_x_preferred":[
        "Drochia"
    ],
    "name:tur_x_preferred":[
        "Drochia"
    ],
    "name:ukr_x_preferred":[
        "\u0414\u0440\u043e\u043a\u0456\u044f"
    ],
    "name:urd_x_preferred":[
        "\u062f\u0631\u0648\u06a9\u06cc\u0627"
    ],
    "name:zho_x_preferred":[
        "\u5fb7\u7f85\u57fa\u4e9e"
    ],
    "qs:a0":"Moldova",
    "qs:a1":"*Drocia",
    "qs:a1_alt":"Drochia",
    "qs:a1r":"0",
    "qs:adm0":"Moldova",
    "qs:la_lc":"*",
    "qs:level":"locality",
    "qs:loc":"Drochia",
    "qs:loc_alt":"Drochia",
    "qs:pop":0,
    "qs:type":"buffered point",
    "wd:wordcount":318,
    "wof:name":"Drochia",
    "wof:placetype":"locality"
},
  "geometry": {"coordinates":[27.812586,48.113006],"type":"Point"}
}