{
  "type": "Feature",
  "properties": {
    "iso:country":"MD",
    "qs:a0":"Moldova",
    "qs:a1":"*Drocia",
    "qs:a1_alt":"Drochia",
    "qs:a1r":"0",
    "qs:adm0":"Moldova",
    "qs:la_lc":"*",
    "qs:level":"locality",
    "qs:loc":"Drochia",
    "qs:loc_alt":"Drochia",
    "qs:pop":0,
    "qs:type":"buffered point",
    "wd:wordcount":318,
    "wof:name":"Drochia",
    "wof:placetype":"locality"
},
  "geometry": {"coordinates":[27.812586,48.113006],"type":"Point"}
}