{
  "type": "Feature",
  "properties": {
    "iso:country":"MD",
    "name:arz_x_preferred":[
        "\u0643\u0644\u064a\u0645\u0627\u0648\u062a\u0633\u0649"
    ],
    "name:ceb_x_preferred":[
        "Clim\u0103u\u021bi"
    ],
    "name:che_x_preferred":[
        "\u041a\u043b\u0438\u043c\u044d\u0443\u0446\u044c"
    ],
    "name:dan_x_preferred":[
        "Clim\u0103u\u021bi"
    ],
    "name:deu_x_preferred":[
        "Clim\u0103u\u021bi"
    ],
    "name:eng_x_preferred":[
        "Klimauts'"
    ],
    "name:eng_x_variant":[
        "Klimautsy",
        "Clim\u0103u\u021bi"
    ],
    "name:eus_x_preferred":[
        "Clim\u0103u\u021bi"
    ],
    "name:fra_x_preferred":[
        "Clim\u0103u\u021bi"
    ],
    "name:gle_x_preferred":[
        "Clim\u0103u\u021bi"
    ],
    "name:ita_x_preferred":[
        "Clim\u0103u\u021bi"
    ],
    "name:ita_x_variant":[
        "Clim\u0103u\u0163i"
    ],
    "name:kat_x_preferred":[
        "\u10d9\u10da\u10d8\u10db\u10d4\u10e3\u10ea\u10d8"
    ],
    "name:nld_x_preferred":[
        "Clim\u0103u\u0163i"
    ],
    "name:nno_x_preferred":[
        "Clim\u0103u\u021bi"
    ],
    "name:nob_x_preferred":[
        "Clim\u0103u\u021bi"
    ],
    "name:pol_x_preferred":[
        "Clim\u0103u\u021bi"
    ],
    "name:por_x_preferred":[
        "Clim\u0103u\u021bi"
    ],
    "name:ron_x_preferred":[
        "Clim\u0103u\u021bi"
    ],
    "name:rus_x_preferred":[
        "\u041a\u043b\u0438\u043c\u0430\u0443\u0446\u044b"
    ],
    "name:spa_x_preferred":[
        "Clim\u0103u\u021bi"
    ],
    "name:swe_x_preferred":[
        "Clim\u0103u\u021bi"
    ],
    "name:tat_x_preferred":[
        "\u041a\u043b\u0438\u043c\u044b\u0443\u0446\u0438"
    ],
    "name:ukr_x_preferred":[
        "\u041a\u043b\u0456\u043c\u0430\u0443\u0446\u044c"
    ],
    "name:ukr_x_variant":[
        "\u0421\u043b\u043e\u0431\u043e\u0437\u0456\u044f-\u0428\u0456\u0440\u0430\u0443\u0446\u044c"
    ],
    "name:und_x_colloquial":[
        "Climauti"
    ],
    "name:und_x_variant":[
        "Klimauts\u2019"
    ],
    "qs:a0":"Moldova",
    "qs:a1":"*Dondu\u015feni",
    "qs:a1_alt":"Donduseni",
    "qs:a1r":"0",
    "qs:adm0":"Moldova",
    "qs:la_lc":"*",
    "qs:level":"locality",
    "qs:loc":"Clim\u0103u\u0163i",
    "qs:loc_alt":"Climauti",
    "qs:pop":0,
    "qs:type":"buffered point",
    "wd:wordcount":42,
    "wof:lang":[
        "unk"
    ],
    "wof:name":"Clim\u0103u\u0163i",
    "wof:placetype":"locality"
},
  "geometry": {"coordinates":[27.615349,48.310349],"type":"Point"}
}