{
  "type": "Feature",
  "properties": {
    "gn:admin1_code":"67.0",
    "gn:asciiname":"Cureni",
    "gn:cc2":"MD",
    "gn:country_code":"MD",
    "gn:dem":63,
    "gn:feature_class":"P",
    "gn:feature_code":"PPL",
    "gn:name":"Cureni",
    "gn:population":0,
    "gn:timezone":"Europe/Chisinau",
    "iso:country":"MD",
    "name:und_x_variant":[
        "Kuren'",
        "Kureny",
        "Cureni"
    ],
    "wof:name":"Cureni",
    "wof:placetype":"locality"
},
  "geometry": {"coordinates":[29.10778,46.7175],"type":"Point"}
}