{
  "type": "Feature",
  "properties": {
    "gn:admin1_code":"76.0",
    "gn:asciiname":"Tomestii Vechi",
    "gn:country_code":"MD",
    "gn:dem":55,
    "gn:feature_class":"P",
    "gn:feature_code":"PPL",
    "gn:name":"Tome\u015ftii Vechi",
    "gn:population":0,
    "gn:timezone":"Europe/Chisinau",
    "iso:country":"MD",
    "name:rus_x_preferred":[
        "\u0421\u0442\u0430\u0440\u044b\u0435 \u0422\u043e\u043c\u0435\u0448\u0442\u044b"
    ],
    "name:und_x_variant":[
        "Staryye Tomeshty",
        "Tompeshti Vek\u2019",
        "Tome\u015ftii Vechi"
    ],
    "wof:name":"Tomestii Vechi",
    "wof:placetype":"locality"
},
  "geometry": {"coordinates":[27.33634,47.65531],"type":"Point"}
}