{
  "type": "Feature",
  "properties": {
    "gn:admin1_code":"63.0",
    "gn:asciiname":"Mihaileni",
    "gn:country_code":"MD",
    "gn:dem":189,
    "gn:feature_class":"P",
    "gn:feature_code":"PPL",
    "gn:name":"Mih\u0103ileni",
    "gn:population":0,
    "gn:timezone":"Europe/Chisinau",
    "iso:country":"MD",
    "name:ita_x_preferred":[
        "Mih\u0103ileni"
    ],
    "name:ron_x_preferred":[
        "Comuna Mih\u0103ileni"
    ],
    "name:rus_x_preferred":[
        "\u041c\u0438\u0445\u0430\u0439\u043b\u044f\u043d\u044b"
    ],
    "name:und_x_variant":[
        "Mikhaylyany"
    ],
    "wof:name":"Mihaileni",
    "wof:placetype":"locality"
},
  "geometry": {"coordinates":[27.25143,48.24599],"type":"Point"}
}