{
  "type": "Feature",
  "properties": {
    "gn:admin1_code":"92.0",
    "gn:asciiname":"Novaia Nicolaevca",
    "gn:country_code":"MD",
    "gn:dem":57,
    "gn:feature_class":"P",
    "gn:feature_code":"PPL",
    "gn:name":"Novaia Nicolaevca",
    "gn:population":0,
    "gn:timezone":"Europe/Chisinau",
    "iso:country":"MD",
    "name:rus_x_preferred":[
        "\u041d\u043e\u0432\u0430\u044f \u041d\u0438\u043a\u043e\u043b\u0430\u0435\u0432\u043a\u0430"
    ],
    "name:und_x_variant":[
        "Novaya Nikolayevka",
        "Novaia Nicolaevca"
    ],
    "wof:name":"Novaia Nicolaevca",
    "wof:placetype":"locality"
},
  "geometry": {"coordinates":[27.84437,47.26956],"type":"Point"}
}