{
  "type": "Feature",
  "properties": {
    "gn:admin1_code":"74.0",
    "gn:asciiname":"Ciolacu Vechi",
    "gn:country_code":"MD",
    "gn:dem":133,
    "gn:feature_class":"P",
    "gn:feature_code":"PPL",
    "gn:name":"Ciolacu Vechi",
    "gn:population":0,
    "gn:timezone":"Europe/Chisinau",
    "iso:country":"MD",
    "name:rus_x_preferred":[
        "\u0421\u0442\u0430\u0440\u0430\u044f \u0427\u0435\u043b\u0430\u043a\u043e\u0432\u043a\u0430"
    ],
    "name:und_x_variant":[
        "Cholaku-Vek\u2019",
        "Staryy Cholak",
        "Chuluk",
        "Staraya Chelakovka",
        "Staraya Chelachovka",
        "Ciolacu Vechi"
    ],
    "wof:name":"Ciolacu Vechi",
    "wof:placetype":"locality"
},
  "geometry": {"coordinates":[27.86097,47.47645],"type":"Point"}
}