{
  "type": "Feature",
  "properties": {
    "gn:admin1_code":"71.0",
    "gn:asciiname":"Valeny",
    "gn:cc2":"MD",
    "gn:country_code":"MD",
    "gn:dem":126,
    "gn:feature_class":"P",
    "gn:feature_code":"PPL",
    "gn:name":"Valeny",
    "gn:population":0,
    "gn:timezone":"Europe/Chisinau",
    "iso:country":"MD",
    "name:und_x_variant":[
        "V\u0103leni"
    ],
    "wof:name":"Valeny",
    "wof:placetype":"locality"
},
  "geometry": {"coordinates":[27.93944,47.96083],"type":"Point"}
}