{
  "type": "Feature",
  "properties": {
    "gn:admin1_code":"85.0",
    "gn:asciiname":"Valea Radoaiei",
    "gn:country_code":"MD",
    "gn:dem":133,
    "gn:feature_class":"P",
    "gn:feature_code":"PPL",
    "gn:name":"Valea R\u0103doaiei",
    "gn:population":0,
    "gn:timezone":"Europe/Chisinau",
    "iso:country":"MD",
    "name:rus_x_preferred":[
        "\u0412\u0430\u043b\u044f-\u0420\u0430\u0434\u043e\u0430\u0435\u0439"
    ],
    "name:und_x_variant":[
        "Valya Radoya",
        "Valya-Radoayey",
        "Vale-Radoayye",
        "Valea R\u0103doaiei"
    ],
    "wof:name":"Valea Radoaiei",
    "wof:placetype":"locality"
},
  "geometry": {"coordinates":[28.26266,47.75527],"type":"Point"}
}