{
  "type": "Feature",
  "properties": {
    "gn:admin1_code":"59.0",
    "gn:asciiname":"Telita Noua",
    "gn:country_code":"MD",
    "gn:dem":48,
    "gn:feature_class":"P",
    "gn:feature_code":"PPL",
    "gn:name":"Teli\u0163a Nou\u0103",
    "gn:population":0,
    "gn:timezone":"Europe/Chisinau",
    "iso:country":"MD",
    "name:rus_x_preferred":[
        "\u041d\u043e\u0432\u0430\u044f \u0422\u0435\u043b\u0438\u0446\u0430"
    ],
    "name:und_x_variant":[
        "Novaya Telitsa",
        "Teli\u0163a Nou\u0103"
    ],
    "wof:name":"Telita Noua",
    "wof:placetype":"locality"
},
  "geometry": {"coordinates":[29.28601,46.98111],"type":"Point"}
}