{
  "type": "Feature",
  "properties": {
    "gn:admin1_code":"81.0",
    "gn:asciiname":"Codreni",
    "gn:country_code":"MD",
    "gn:dem":135,
    "gn:feature_class":"P",
    "gn:feature_code":"PPL",
    "gn:name":"Codreni",
    "gn:population":0,
    "gn:timezone":"Europe/Chisinau",
    "iso:country":"MD",
    "name:ceb_x_preferred":[
        "Codreni"
    ],
    "name:deu_x_preferred":[
        "Codreni"
    ],
    "name:ron_x_preferred":[
        "Codreni"
    ],
    "name:rus_x_preferred":[
        "\u041a\u043e\u0434\u0440\u044f\u043d\u044b"
    ],
    "name:srp_x_preferred":[
        "\u041a\u043e\u0434\u0440\u0435\u043d\u0438"
    ],
    "name:ukr_x_preferred":[
        "\u041a\u043e\u0434\u0440\u0435\u043d\u044c"
    ],
    "name:und_x_variant":[
        "Kodryany",
        "Kodren\u2019",
        "Korden\u2019",
        "Codreni"
    ],
    "wof:name":"Codreni",
    "wof:placetype":"locality"
},
  "geometry": {"coordinates":[27.7177,48.43143],"type":"Point"}
}