{
  "type": "Feature",
  "properties": {
    "gn:admin1_code":"75.0",
    "gn:asciiname":"Stirceni",
    "gn:country_code":"MD",
    "gn:dem":80,
    "gn:feature_class":"P",
    "gn:feature_code":"PPL",
    "gn:name":"St\u00eerceni",
    "gn:population":0,
    "gn:timezone":"Europe/Chisinau",
    "iso:country":"MD",
    "name:rus_x_preferred":[
        "\u0421\u0442\u044b\u0440\u0447\u0435\u043d\u044b"
    ],
    "name:und_x_variant":[
        "Styrchan\u2019",
        "Styrcheny",
        "St\u00eerceni"
    ],
    "wof:name":"Stirceni",
    "wof:placetype":"locality"
},
  "geometry": {"coordinates":[28.3651,47.87634],"type":"Point"}
}