{
  "type": "Feature",
  "properties": {
    "iso:country":"MD",
    "name:ceb_x_preferred":[
        "Cernoleuca"
    ],
    "name:dan_x_preferred":[
        "Cernoleuca"
    ],
    "name:deu_x_preferred":[
        "Cernoleuca"
    ],
    "name:eng_x_preferred":[
        "Chernoleuka"
    ],
    "name:eng_x_variant":[
        "Cernoleuca"
    ],
    "name:eus_x_preferred":[
        "Cernoleuca"
    ],
    "name:fra_x_preferred":[
        "Cernoleuca"
    ],
    "name:ita_x_preferred":[
        "Cernoleuca"
    ],
    "name:kat_x_preferred":[
        "\u10e9\u10d4\u10e0\u10dc\u10dd\u10da\u10d4\u10e3\u10d9\u10d0"
    ],
    "name:nld_x_preferred":[
        "Cernoleuca"
    ],
    "name:nno_x_preferred":[
        "Cernoleuca"
    ],
    "name:nob_x_preferred":[
        "Cernoleuca"
    ],
    "name:pol_x_preferred":[
        "Cernoleuca"
    ],
    "name:por_x_preferred":[
        "Cernoleuca"
    ],
    "name:ron_x_preferred":[
        "Cernoleuca"
    ],
    "name:rus_x_preferred":[
        "\u0427\u0435\u0440\u043d\u043e\u043b\u0451\u0432\u043a\u0430"
    ],
    "name:rus_x_variant":[
        "\u0427\u0435\u0440\u043d\u043e\u043b\u0435\u0432\u043a\u0430"
    ],
    "name:spa_x_preferred":[
        "Cernoleuca"
    ],
    "name:swe_x_preferred":[
        "Cernoleuca"
    ],
    "name:ukr_x_preferred":[
        "\u0427\u0435\u0440\u043d\u043e\u043b\u0435\u0443\u043a\u0430"
    ],
    "name:ukr_x_variant":[
        "\u0414\u043e\u043c\u0456\u043d\u0442\u0435\u043d\u044c"
    ],
    "name:und_x_colloquial":[
        "Chernolevka"
    ],
    "name:und_x_variant":[
        "Chernol\u00ebvka"
    ],
    "qs:a0":"Moldova",
    "qs:a1":"*Dondu\u015feni",
    "qs:a1_alt":"Donduseni",
    "qs:a1r":"0",
    "qs:adm0":"Moldova",
    "qs:la_lc":"*",
    "qs:level":"locality",
    "qs:loc":"Cernoleuca",
    "qs:loc_alt":"Cernoleuca",
    "qs:pop":0,
    "qs:type":"buffered point",
    "wd:wordcount":57,
    "wof:lang":[
        "unk"
    ],
    "wof:name":"Cernoleuca",
    "wof:placetype":"locality"
},
  "geometry": {"coordinates":[27.56234,48.312256],"type":"Point"}
}