{
  "type": "Feature",
  "properties": {
    "iso:country":"MD",
    "name:dut_x_preferred":[
        "Mere\u015feni"
    ],
    "name:eng_x_preferred":[
        "Meresheny"
    ],
    "name:eng_x_variant":[
        "Merishen'",
        "Mere\u0219eni"
    ],
    "name:geo_x_preferred":[
        "\u10db\u10d4\u10e0\u10d4\u10e8\u10d4\u10dc\u10d8"
    ],
    "name:ita_x_preferred":[
        "Mere\u0219eni"
    ],
    "name:ron_x_preferred":[
        "Mere\u0219eni"
    ],
    "name:rum_x_preferred":[
        "Mere\u0219eni"
    ],
    "name:rus_x_preferred":[
        "\u041c\u0435\u0440\u0435\u0448\u0435\u043d\u044b"
    ],
    "name:ukr_x_preferred":[
        "\u041c\u0435\u0440\u0435\u0448\u0435\u043d\u044c"
    ],
    "name:und_x_colloquial":[
        "Mereseni"
    ],
    "name:und_x_preferred":[
        "Mere\u015feni"
    ],
    "name:unk_x_variant":[
        "Meresheny"
    ],
    "qs:a0":"Moldova",
    "qs:a1":"*H\u00eence\u015fti",
    "qs:a1_alt":"Hincesti",
    "qs:a1r":"0",
    "qs:adm0":"Moldova",
    "qs:la_lc":"*",
    "qs:level":"locality",
    "qs:loc":"Mere\u015feni",
    "qs:loc_alt":"Mereseni",
    "qs:pop":0,
    "qs:type":"buffered point",
    "wd:wordcount":47,
    "wof:lang":[
        "unk"
    ],
    "wof:name":"Mere\u015feni",
    "wof:placetype":"locality"
},
  "geometry": {"coordinates":[28.540197,46.796661],"type":"Point"}
}