{
  "type": "Feature",
  "properties": {
    "gn:population":10146,
    "iso:country":"MD",
    "name:bul_x_preferred":[
        "\u0413\u043b\u043e\u0434\u0435\u043d\u0438"
    ],
    "name:ceb_x_preferred":[
        "Glodeni"
    ],
    "name:eng_x_preferred":[
        "Malyye Glodyany"
    ],
    "name:eng_x_variant":[
        "Gloden'",
        "Glodyany",
        "Glodeni"
    ],
    "name:est_x_preferred":[
        "Glodeni"
    ],
    "name:fin_x_preferred":[
        "Glodeni"
    ],
    "name:fra_x_preferred":[
        "Glodeni"
    ],
    "name:hsb_x_preferred":[
        "Glodeni"
    ],
    "name:ita_x_preferred":[
        "Glodeni"
    ],
    "name:kat_x_preferred":[
        "\u10d2\u10da\u10dd\u10d3\u10d4\u10dc\u10d8"
    ],
    "name:kor_x_preferred":[
        "\uae00\ub85c\ub370\ub2c8"
    ],
    "name:lit_x_preferred":[
        "Glodenis"
    ],
    "name:nld_x_preferred":[
        "Glodeni"
    ],
    "name:pnb_x_preferred":[
        "\u06af\u0644\u0648\u062f\u06cc\u0646\u06cc"
    ],
    "name:pol_x_preferred":[
        "Glodeni"
    ],
    "name:ron_x_preferred":[
        "Glodeni"
    ],
    "name:rus_x_preferred":[
        "\u0413\u043b\u043e\u0434\u044f\u043d\u044b"
    ],
    "name:spa_x_preferred":[
        "Glodeni"
    ],
    "name:srp_x_preferred":[
        "\u0413\u043b\u043e\u0434\u0435\u043d\u0438"
    ],
    "name:swe_x_preferred":[
        "Glodeni"
    ],
    "name:tat_x_preferred":[
        "\u0413\u043b\u043e\u0434\u0435\u043d"
    ],
    "name:ukr_x_preferred":[
        "\u0413\u043b\u043e\u0434\u044f\u043d\u0438"
    ],
    "name:urd_x_preferred":[
        "\u06af\u0644\u0648\u062f\u06cc\u0646\u06cc"
    ],
    "name:zho_x_preferred":[
        "\u683c\u6d1b\u4ee3\u5c3c"
    ],
    "qs:a0":"Moldova",
    "qs:a1":"*Glodeni",
    "qs:a1_alt":"Glodeni",
    "qs:a1r":"0",
    "qs:adm0":"Moldova",
    "qs:la_lc":"*",
    "qs:level":"locality",
    "qs:loc":"Glodeni",
    "qs:loc_alt":"Glodeni",
    "qs:pop":0,
    "qs:type":"buffered point",
    "wd:wordcount":79,
    "wof:lang":[
        "unk"
    ],
    "wof:name":"Glodeni",
    "wof:placetype":"locality",
    "wof:population":10146
},
  "geometry": {"coordinates":[27.512831,47.776704],"type":"Point"}
}