{
  "type": "Feature",
  "properties": {
    "gn:admin1_code":"65.0",
    "gn:asciiname":"Dimitrova",
    "gn:country_code":"MD",
    "gn:dem":70,
    "gn:feature_class":"P",
    "gn:feature_code":"PPL",
    "gn:name":"Dimitrova",
    "gn:population":0,
    "gn:timezone":"Europe/Chisinau",
    "iso:country":"MD",
    "name:bul_x_preferred":[
        "\u0414\u0438\u043c\u0438\u0442\u0440\u043e\u0432\u0430"
    ],
    "name:hye_x_preferred":[
        "\u0534\u056b\u0574\u056b\u057f\u0580\u0578\u057e\u0561"
    ],
    "name:lav_x_preferred":[
        "Dimitrova"
    ],
    "name:ron_x_preferred":[
        "Dimitrova"
    ],
    "name:rus_x_preferred":[
        "\u0414\u0438\u043c\u0438\u0442\u0440\u043e\u0432\u043e"
    ],
    "name:rus_x_variant":[
        "\u0414\u0438\u043c\u0438\u0442\u0440\u043e\u0432\u0430"
    ],
    "name:ukr_x_preferred":[
        "\u0414\u0438\u043c\u0438\u0442\u0440\u043e\u0432\u0430"
    ],
    "name:und_x_variant":[
        "\u0162\u0103r\u0103ncu\u0163a",
        "Dmitrovo",
        "Tel\u2019piz",
        "Dimitrovo"
    ],
    "wof:name":"Dimitrova",
    "wof:placetype":"locality"
},
  "geometry": {"coordinates":[28.46808,46.15933],"type":"Point"}
}