{
  "type": "Feature",
  "properties": {
    "iso:country":"MD",
    "name:bul_x_preferred":[
        "\u041a\u043e\u043b\u0438\u0431\u0430\u0431\u043e\u0432\u043a\u0430"
    ],
    "name:ceb_x_preferred":[
        "Colibabovca"
    ],
    "name:dan_x_preferred":[
        "Colibabovca"
    ],
    "name:deu_x_preferred":[
        "Colibabovca"
    ],
    "name:eng_x_preferred":[
        "Kolibabovka"
    ],
    "name:eng_x_variant":[
        "Kolybayevka",
        "Colibabovca"
    ],
    "name:eus_x_preferred":[
        "Colibabovca"
    ],
    "name:fra_x_preferred":[
        "Colibabovca"
    ],
    "name:ita_x_preferred":[
        "Colibabovca"
    ],
    "name:kat_x_preferred":[
        "\u10d9\u10dd\u10da\u10d8\u10d1\u10d0\u10d1\u10dd\u10d5\u10d9\u10d0"
    ],
    "name:nld_x_preferred":[
        "Colibabovca"
    ],
    "name:nno_x_preferred":[
        "Colibabovca"
    ],
    "name:nob_x_preferred":[
        "Colibabovca"
    ],
    "name:pol_x_preferred":[
        "Colibabovca"
    ],
    "name:por_x_preferred":[
        "Colibabovca"
    ],
    "name:ron_x_preferred":[
        "Colibabovca"
    ],
    "name:rus_x_preferred":[
        "\u041a\u043e\u043b\u0438\u0431\u0430\u0431\u043e\u0432\u043a\u0430"
    ],
    "name:spa_x_preferred":[
        "Colibabovca"
    ],
    "name:swe_x_preferred":[
        "Colibabovca"
    ],
    "name:ukr_x_preferred":[
        "\u041a\u043e\u043b\u0456\u0431\u0430\u0431\u043e\u0432\u043a\u0430"
    ],
    "name:ukr_x_variant":[
        "\u041a\u0443\u0448\u043c\u0456\u0440\u043a\u0430"
    ],
    "name:und_x_preferred":[
        "Colibabovca"
    ],
    "name:unk_x_variant":[
        "Calibabovca"
    ],
    "qs:a0":"Moldova",
    "qs:a1":"*Leova",
    "qs:a1_alt":"Leova",
    "qs:a1r":"0",
    "qs:adm0":"Moldova",
    "qs:la_lc":"*",
    "qs:level":"locality",
    "qs:loc":"Colibabovca",
    "qs:loc_alt":"Colibabovca",
    "qs:pop":0,
    "qs:type":"buffered point",
    "wd:wordcount":69,
    "wof:lang":[
        "unk"
    ],
    "wof:name":"Colibabovca",
    "wof:placetype":"locality"
},
  "geometry": {"coordinates":[28.429154,46.647606],"type":"Point"}
}