{
  "type": "Feature",
  "properties": {
    "gn:admin1_code":"74.0",
    "gn:asciiname":"Socii Vechi",
    "gn:country_code":"MD",
    "gn:dem":93,
    "gn:feature_class":"P",
    "gn:feature_code":"PPL",
    "gn:name":"Socii Vechi",
    "gn:population":0,
    "gn:timezone":"Europe/Chisinau",
    "iso:country":"MD",
    "name:rus_x_preferred":[
        "\u0421\u0442\u0430\u0440\u044b\u0435 \u0421\u043e\u0447\u0438"
    ],
    "name:und_x_variant":[
        "Staryye Sochi",
        "Socii Vechi"
    ],
    "wof:name":"Socii Vechi",
    "wof:placetype":"locality"
},
  "geometry": {"coordinates":[27.67704,47.52552],"type":"Point"}
}