{
  "type": "Feature",
  "properties": {
    "iso:country":"MD",
    "name:eng_x_preferred":[
        "Khalakhova de Sus"
    ],
    "name:eng_x_variant":[
        "Verkhniye Kholokhory",
        "Halahora de Sus"
    ],
    "name:fra_x_preferred":[
        "Halahora de Sus"
    ],
    "name:ita_x_preferred":[
        "Halahora de Sus"
    ],
    "name:kat_x_preferred":[
        "\u10f0\u10d0\u10da\u10d0\u10f0\u10dd\u10e0\u10d0-\u10d3\u10d4-\u10e1\u10e3\u10e1\u10d8"
    ],
    "name:nld_x_preferred":[
        "Halahora de Sus"
    ],
    "name:ron_x_preferred":[
        "Halahora de Sus"
    ],
    "name:rus_x_preferred":[
        "\u0412\u0435\u0440\u0445\u043d\u0438\u0435 \u0425\u043e\u043b\u043e\u0445\u043e\u0440\u044b"
    ],
    "name:ukr_x_preferred":[
        "\u0413\u0430\u043b\u0430\u0433\u043e\u0440\u0430-\u0434\u0435-\u0421\u0443\u0441"
    ],
    "qs:a0":"Moldova",
    "qs:a1":"*Briceni",
    "qs:a1_alt":"Briceni",
    "qs:a1r":"0",
    "qs:adm0":"Moldova",
    "qs:la_lc":"*",
    "qs:level":"locality",
    "qs:loc":"Halahora de Sus",
    "qs:loc_alt":"Halahora de Sus",
    "qs:pop":0,
    "qs:type":"buffered point",
    "wd:wordcount":45,
    "wof:lang":[
        "unk"
    ],
    "wof:name":"Halahora de Sus",
    "wof:placetype":"locality"
},
  "geometry": {"coordinates":[27.179959,48.253964],"type":"Point"}
}