{
  "type": "Feature",
  "properties": {
    "gn:admin1_code":"74.0",
    "gn:asciiname":"Tambula",
    "gn:country_code":"MD",
    "gn:dem":153,
    "gn:feature_class":"P",
    "gn:feature_code":"PPL",
    "gn:name":"\u0162ambula",
    "gn:population":0,
    "gn:timezone":"Europe/Chisinau",
    "iso:country":"MD",
    "name:ita_x_preferred":[
        "\u021aambula"
    ],
    "name:ron_x_preferred":[
        "Comuna \u021aambula"
    ],
    "name:rus_x_preferred":[
        "\u0426\u0430\u043c\u0431\u0443\u043b\u0430"
    ],
    "name:und_x_variant":[
        "Tsambula",
        "Tsambola",
        "\u0162ambula"
    ],
    "wof:name":"Tambula",
    "wof:placetype":"locality"
},
  "geometry": {"coordinates":[27.92447,47.69689],"type":"Point"}
}