{
  "type": "Feature",
  "properties": {
    "gn:admin1_code":"51.0",
    "gn:asciiname":"Etulia Noua",
    "gn:country_code":"MD",
    "gn:dem":93,
    "gn:feature_class":"P",
    "gn:feature_code":"PPL",
    "gn:name":"Etulia Nou\u0103",
    "gn:population":0,
    "gn:timezone":"Europe/Chisinau",
    "iso:country":"MD",
    "name:rus_x_preferred":[
        "\u041d\u043e\u0432\u0430\u044f \u0415\u0442\u0443\u043b\u0438\u044f"
    ],
    "name:und_x_variant":[
        "Novaya Etuliya",
        "Etulia Nou\u0103"
    ],
    "wof:name":"Etulia Noua",
    "wof:placetype":"locality"
},
  "geometry": {"coordinates":[28.43801,45.5162],"type":"Point"}
}