{
  "type": "Feature",
  "properties": {
    "gn:admin1_code":"92.0",
    "gn:asciiname":"Stolniceni",
    "gn:country_code":"MD",
    "gn:dem":68,
    "gn:feature_class":"P",
    "gn:feature_code":"PPL",
    "gn:name":"Stolniceni",
    "gn:population":0,
    "gn:timezone":"Europe/Chisinau",
    "iso:country":"MD",
    "name:rus_x_preferred":[
        "\u0421\u0442\u043e\u043b\u044c\u043d\u0438\u0447\u0435\u043d\u044b"
    ],
    "name:und_x_variant":[
        "Stol\u2019nicheny",
        "Stolnichen\u2019",
        "Stolnichany",
        "Stolniceni"
    ],
    "wof:name":"Stolniceni",
    "wof:placetype":"locality"
},
  "geometry": {"coordinates":[27.71389000000001,47.41111],"type":"Point"}
}