{
  "type": "Feature",
  "properties": {
    "gn:admin1_code":"75.0",
    "gn:asciiname":"Poeana",
    "gn:cc2":"MD",
    "gn:country_code":"MD",
    "gn:dem":206,
    "gn:feature_class":"P",
    "gn:feature_code":"PPL",
    "gn:name":"Poeana",
    "gn:population":0,
    "gn:timezone":"Europe/Chisinau",
    "iso:country":"MD",
    "name:und_x_variant":[
        "Poyana",
        "Poyyana"
    ],
    "wof:name":"Poeana",
    "wof:placetype":"locality"
},
  "geometry": {"coordinates":[28.63333,47.91194],"type":"Point"}
}