{
  "type": "Feature",
  "properties": {
    "gn:admin1_code":"76.0",
    "gn:asciiname":"Fundurii Noi",
    "gn:country_code":"MD",
    "gn:dem":118,
    "gn:feature_class":"P",
    "gn:feature_code":"PPL",
    "gn:name":"Fundurii Noi",
    "gn:population":0,
    "gn:timezone":"Europe/Chisinau",
    "iso:country":"MD",
    "name:rus_x_preferred":[
        "\u041d\u043e\u0432\u044b\u0435 \u0424\u0443\u043d\u0434\u0443\u0440\u044b"
    ],
    "name:und_x_variant":[
        "Novyye Fundury",
        "Fundurile Noy",
        "Fundurii Noi"
    ],
    "wof:name":"Fundurii Noi",
    "wof:placetype":"locality"
},
  "geometry": {"coordinates":[27.65381,47.75547],"type":"Point"}
}