{
  "type": "Feature",
  "properties": {
    "iso:country":"MD",
    "name:ceb_x_preferred":[
        "Ca\u0219unca"
    ],
    "name:dan_x_preferred":[
        "Ca\u0219unca"
    ],
    "name:deu_x_preferred":[
        "Ca\u0219unca"
    ],
    "name:eng_x_preferred":[
        "Kashunka"
    ],
    "name:eng_x_variant":[
        "Kassovka",
        "Ca\u0219unca"
    ],
    "name:eus_x_preferred":[
        "Ca\u0219unca"
    ],
    "name:fra_x_preferred":[
        "Ca\u0219unca"
    ],
    "name:ita_x_preferred":[
        "Ca\u0219unca"
    ],
    "name:ita_x_variant":[
        "Ca\u015funca"
    ],
    "name:kat_x_preferred":[
        "\u10d9\u10d0\u10e8\u10e3\u10dc\u10d9\u10d0"
    ],
    "name:nld_x_preferred":[
        "Ca\u015funca"
    ],
    "name:nno_x_preferred":[
        "Ca\u0219unca"
    ],
    "name:nob_x_preferred":[
        "Ca\u0219unca"
    ],
    "name:pol_x_preferred":[
        "Ca\u0219unca"
    ],
    "name:por_x_preferred":[
        "Ca\u0219unca"
    ],
    "name:ron_x_preferred":[
        "Ca\u0219unca"
    ],
    "name:rus_x_preferred":[
        "\u041a\u0430\u0448\u0443\u043d\u043a\u0430"
    ],
    "name:spa_x_preferred":[
        "Ca\u0219unca"
    ],
    "name:swe_x_preferred":[
        "Ca\u0219unca"
    ],
    "name:ukr_x_preferred":[
        "\u041a\u0430\u0448\u0443\u043d\u043a\u0430"
    ],
    "name:ukr_x_variant":[
        "\u041a\u043e\u0440\u0436\u043e\u0432\u0430"
    ],
    "name:und_x_colloquial":[
        "Casunca"
    ],
    "qs:a0":"Moldova",
    "qs:a1":"*Flore\u015fti",
    "qs:a1_alt":"Floresti",
    "qs:a1r":"0",
    "qs:adm0":"Moldova",
    "qs:la_lc":"*",
    "qs:level":"locality",
    "qs:loc":"Ca\u015funca",
    "qs:loc_alt":"Casunca",
    "qs:pop":0,
    "qs:type":"buffered point",
    "wd:wordcount":57,
    "wof:lang":[
        "unk"
    ],
    "wof:name":"Ca\u015funca",
    "wof:placetype":"locality"
},
  "geometry": {"coordinates":[28.396135,47.785298],"type":"Point"}
}