{
  "type": "Feature",
  "properties": {
    "iso:country":"MD",
    "name:eng_x_preferred":[
        "Medvezha"
    ],
    "name:eng_x_variant":[
        "Medvezha-Mare",
        "Medveja"
    ],
    "name:ita_x_preferred":[
        "Medveja"
    ],
    "name:kat_x_preferred":[
        "\u10db\u10d4\u10d3\u10d5\u10d4\u10df\u10d0"
    ],
    "name:nld_x_preferred":[
        "Medveja"
    ],
    "name:ron_x_preferred":[
        "Medveja"
    ],
    "name:rus_x_preferred":[
        "\u041c\u0435\u0434\u0432\u0435\u0436\u0430"
    ],
    "name:ukr_x_preferred":[
        "\u041c\u0435\u0434\u0432\u0435\u0436\u0430"
    ],
    "name:und_x_preferred":[
        "Medveja"
    ],
    "name:unk_x_variant":[
        "Medvezha"
    ],
    "qs:a0":"Moldova",
    "qs:a1":"*Briceni",
    "qs:a1_alt":"Briceni",
    "qs:a1r":"0",
    "qs:adm0":"Moldova",
    "qs:la_lc":"*",
    "qs:level":"locality",
    "qs:loc":"Medveja",
    "qs:loc_alt":"Medveja",
    "qs:pop":0,
    "qs:type":"buffered point",
    "wd:wordcount":35,
    "wof:lang":[
        "unk"
    ],
    "wof:name":"Medveja",
    "wof:placetype":"locality"
},
  "geometry": {"coordinates":[26.791921,48.364247],"type":"Point"}
}