{
  "type": "Feature",
  "properties": {
    "gn:admin1_code":"87.0",
    "gn:asciiname":"Slobozia-Vanancau",
    "gn:country_code":"MD",
    "gn:dem":45,
    "gn:feature_class":"P",
    "gn:feature_code":"PPL",
    "gn:name":"Slobozia-V\u00e2n\u0103nc\u0103u",
    "gn:population":0,
    "gn:timezone":"Europe/Chisinau",
    "iso:country":"MD",
    "name:ron_x_preferred":[
        "Slobozia-V\u00e2n\u0103nc\u0103u"
    ],
    "name:rus_x_preferred":[
        "\u0421\u043b\u043e\u0431\u043e\u0434\u0437\u0435\u044f-\u0412\u043e\u0440\u043e\u043d\u043a\u043e\u0432\u043e"
    ],
    "name:und_x_variant":[
        "Slobodzeya-Voronkova",
        "Slobodzeya-Voronkovo",
        "Sloboda Vorynkeu"
    ],
    "wof:name":"Slobozia-Vanancau",
    "wof:placetype":"locality"
},
  "geometry": {"coordinates":[28.46836,48.06846],"type":"Point"}
}