{
  "type": "Feature",
  "properties": {
    "iso:country":"MD",
    "name:bul_x_preferred":[
        "\u0411\u0430\u0443\u0440\u0447\u0438"
    ],
    "name:gag_x_preferred":[
        "Baur\u00e7u"
    ],
    "name:ita_x_preferred":[
        "Baurci"
    ],
    "name:ron_x_preferred":[
        "Baurci"
    ],
    "name:rus_x_preferred":[
        "\u0411\u0430\u0443\u0440\u0447\u0438"
    ],
    "name:ukr_x_preferred":[
        "\u0411\u0430\u0443\u0440\u0447\u0438"
    ],
    "name:und_x_preferred":[
        "Baurchi"
    ],
    "name:unk_x_variant":[
        "Baurchi"
    ],
    "qs:a0":"Moldova",
    "qs:a1":"*Unitatea Teritotrial\u0103 Autonom\u0103 G\u0103g\u0103uzia",
    "qs:a1_alt":"Unitatea Teritotriala Autonoma Gagauzia",
    "qs:a1r":"0",
    "qs:adm0":"Moldova",
    "qs:la_lc":"*",
    "qs:level":"locality",
    "qs:loc":"Baurci",
    "qs:loc_alt":"Baurci",
    "qs:pop":0,
    "qs:type":"buffered point",
    "wd:wordcount":118,
    "wof:lang":[
        "unk"
    ],
    "wof:name":"Baurci",
    "wof:placetype":"locality"
},
  "geometry": {"coordinates":[28.675585,46.094978],"type":"Point"}
}