{
  "type": "Feature",
  "properties": {
    "iso:country":"MD",
    "name:bul_x_preferred":[
        "\u041a\u0430\u0440\u0430\u0431\u0435\u0442\u043e\u0432\u043a\u0430"
    ],
    "name:ceb_x_preferred":[
        "Carabetovca"
    ],
    "name:dan_x_preferred":[
        "Carabetovca"
    ],
    "name:deu_x_preferred":[
        "Carabetovca"
    ],
    "name:eng_x_preferred":[
        "Karabateni"
    ],
    "name:eng_x_variant":[
        "Karabaten'",
        "Karabetovka",
        "Carabetovca"
    ],
    "name:eus_x_preferred":[
        "Carabetovca"
    ],
    "name:fra_x_preferred":[
        "Carabetovca"
    ],
    "name:ita_x_preferred":[
        "Carabetovca"
    ],
    "name:kat_x_preferred":[
        "\u10d9\u10d0\u10e0\u10d0\u10d1\u10d4\u10e2\u10dd\u10d5\u10d9\u10d0"
    ],
    "name:nld_x_preferred":[
        "Carabetovca"
    ],
    "name:nno_x_preferred":[
        "Carabetovca"
    ],
    "name:nob_x_preferred":[
        "Carabetovca"
    ],
    "name:pol_x_preferred":[
        "Carabetovca"
    ],
    "name:por_x_preferred":[
        "Carabetovca"
    ],
    "name:ron_x_preferred":[
        "Carabetovca"
    ],
    "name:rus_x_preferred":[
        "\u041a\u0430\u0440\u0430\u0431\u0435\u0442\u043e\u0432\u043a\u0430"
    ],
    "name:spa_x_preferred":[
        "Carabetovca"
    ],
    "name:swe_x_preferred":[
        "Carabetovca"
    ],
    "name:ukr_x_preferred":[
        "\u041a\u0430\u0440\u0430\u0431\u0435\u0442\u043e\u0432\u043a\u0430"
    ],
    "name:ukr_x_variant":[
        "\u0413\u0438\u0440\u0431\u043e\u0432\u0435\u0446"
    ],
    "name:und_x_colloquial":[
        "Carabateni",
        "Carabeteni"
    ],
    "name:und_x_variant":[
        "Carabe\u0163eni",
        "Carab\u0103\u0163eni",
        "Karabaten\u2019"
    ],
    "qs:a0":"Moldova",
    "qs:a1":"*Basarabeasca",
    "qs:a1_alt":"Basarabeasca",
    "qs:a1r":"0",
    "qs:adm0":"Moldova",
    "qs:la_lc":"*",
    "qs:level":"locality",
    "qs:loc":"Carabetovca",
    "qs:loc_alt":"Carabetovca",
    "qs:pop":0,
    "qs:type":"buffered point",
    "wd:wordcount":16,
    "wof:lang":[
        "unk"
    ],
    "wof:name":"Carabetovca",
    "wof:placetype":"locality"
},
  "geometry": {"coordinates":[28.91252,46.41402],"type":"Point"}
}