{
  "type": "Feature",
  "properties": {
    "gn:admin1_code":"88.0",
    "gn:asciiname":"Semionovca",
    "gn:country_code":"MD",
    "gn:dem":79,
    "gn:feature_class":"P",
    "gn:feature_code":"PPL",
    "gn:name":"Semionovca",
    "gn:population":0,
    "gn:timezone":"Europe/Chisinau",
    "iso:country":"MD",
    "name:rus_x_preferred":[
        "\u0421\u0435\u043c\u0451\u043d\u043e\u0432\u043a\u0430"
    ],
    "name:und_x_variant":[
        "Simioneshty",
        "Simione\u015fti",
        "Sem\u00ebnovka",
        "Semionovca"
    ],
    "wof:name":"Semionovca",
    "wof:placetype":"locality"
},
  "geometry": {"coordinates":[29.5136,46.51678],"type":"Point"}
}