{
  "type": "Feature",
  "properties": {
    "gn:admin1_code":"65.0",
    "gn:asciiname":"Tutovanu",
    "gn:cc2":"MD",
    "gn:country_code":"MD",
    "gn:dem":57,
    "gn:feature_class":"P",
    "gn:feature_code":"PPL",
    "gn:name":"Tutovanu",
    "gn:population":0,
    "gn:timezone":"Europe/Chisinau",
    "iso:country":"MD",
    "name:und_x_variant":[
        "Tutovany",
        "Tutovanul"
    ],
    "wof:name":"Tutovanu",
    "wof:placetype":"locality"
},
  "geometry": {"coordinates":[28.29444,46.18306],"type":"Point"}
}