{
  "type": "Feature",
  "properties": {
    "gn:admin1_code":"75.0",
    "gn:asciiname":"Izvoare",
    "gn:country_code":"MD",
    "gn:dem":107,
    "gn:feature_class":"P",
    "gn:feature_code":"PPL",
    "gn:name":"Izvoare",
    "gn:population":0,
    "gn:timezone":"Europe/Chisinau",
    "iso:country":"MD",
    "name:rus_x_preferred":[
        "\u0418\u0437\u0432\u043e\u0440\u044b"
    ],
    "name:und_x_variant":[
        "Izvoarele",
        "Izvory",
        "Isvoarele",
        "Izvoare"
    ],
    "wof:name":"Izvoare",
    "wof:placetype":"locality"
},
  "geometry": {"coordinates":[28.13114,47.97825],"type":"Point"}
}