{
  "type": "Feature",
  "properties": {
    "iso:country":"MD",
    "name:ceb_x_preferred":[
        "N\u0103v\u00eerne\u021b"
    ],
    "name:dan_x_preferred":[
        "N\u0103v\u00eerne\u021b"
    ],
    "name:deu_x_preferred":[
        "N\u0103v\u00eerne\u021b"
    ],
    "name:eng_x_preferred":[
        "Nyvernetsi"
    ],
    "name:eng_x_variant":[
        "Navyrnets",
        "N\u0103v\u00eerne\u021b"
    ],
    "name:eus_x_preferred":[
        "N\u0103v\u00eerne\u021b"
    ],
    "name:fra_x_preferred":[
        "N\u0103v\u00eerne\u021b"
    ],
    "name:ita_x_preferred":[
        "N\u0103v\u00eerne\u021b"
    ],
    "name:ita_x_variant":[
        "N\u0103v\u00eerne\u0163"
    ],
    "name:kat_x_preferred":[
        "\u10dc\u10d4\u10d5\u10d8\u10e0\u10dc\u10d4\u10ea\u10d8"
    ],
    "name:nld_x_preferred":[
        "N\u0103v\u00eerne\u0163"
    ],
    "name:nno_x_preferred":[
        "N\u0103v\u00eerne\u021b"
    ],
    "name:nob_x_preferred":[
        "N\u0103v\u00eerne\u021b"
    ],
    "name:pol_x_preferred":[
        "N\u0103v\u00eerne\u021b"
    ],
    "name:por_x_preferred":[
        "N\u0103v\u00eerne\u021b"
    ],
    "name:ron_x_preferred":[
        "N\u0103v\u00eerne\u021b"
    ],
    "name:ron_x_variant":[
        "Comuna Oni\u0219cani"
    ],
    "name:rus_x_preferred":[
        "\u041d\u044d\u0432\u044b\u0440\u043d\u0435\u0446"
    ],
    "name:rus_x_variant":[
        "\u041d\u0430\u0432\u044b\u0440\u043d\u0435\u0446"
    ],
    "name:spa_x_preferred":[
        "N\u0103v\u00eerne\u021b"
    ],
    "name:swe_x_preferred":[
        "N\u0103v\u00eerne\u021b"
    ],
    "name:ukr_x_preferred":[
        "\u041d\u0435\u0432\u0438\u0440\u043d\u0435\u0446"
    ],
    "name:und_x_colloquial":[
        "Navarnet",
        "Navirnet"
    ],
    "name:und_x_preferred":[
        "N\u0103v\u00eerne\u0163"
    ],
    "name:und_x_variant":[
        "N\u0103v\u00e2rne\u0163"
    ],
    "name:unk_x_variant":[
        "N\u0103v\u00e2rne\u0163"
    ],
    "qs:a0":"Moldova",
    "qs:a1":"*F\u0103le\u015fti",
    "qs:a1_alt":"Falesti",
    "qs:a1r":"0",
    "qs:adm0":"Moldova",
    "qs:la_lc":"*",
    "qs:level":"locality",
    "qs:loc":"N\u0103v\u00eerne\u0163",
    "qs:loc_alt":"Navirnet",
    "qs:pop":0,
    "qs:type":"buffered point",
    "wd:wordcount":57,
    "wof:lang":[
        "unk"
    ],
    "wof:name":"N\u0103v\u00eerne\u0163",
    "wof:placetype":"locality"
},
  "geometry": {"coordinates":[27.556845,47.588284],"type":"Point"}
}