{
  "type": "Feature",
  "properties": {
    "gn:admin1_code":"59.0",
    "gn:asciiname":"Zolotievca",
    "gn:country_code":"MD",
    "gn:dem":95,
    "gn:feature_class":"P",
    "gn:feature_code":"PPL",
    "gn:name":"Zolotievca",
    "gn:population":0,
    "gn:timezone":"Europe/Chisinau",
    "iso:country":"MD",
    "name:ita_x_preferred":[
        "Zolotievca"
    ],
    "name:ron_x_preferred":[
        "Comuna Zolotievca"
    ],
    "name:rus_x_preferred":[
        "\u0417\u043e\u043b\u043e\u0442\u0438\u0435\u0432\u043a\u0430"
    ],
    "name:und_x_variant":[
        "Zoloteyevka",
        "Zolotiyevka",
        "Zolotyanka",
        "Zoloteanca",
        "Zolotievca"
    ],
    "wof:name":"Zolotievca",
    "wof:placetype":"locality"
},
  "geometry": {"coordinates":[29.18925,46.73833],"type":"Point"}
}