{
  "type": "Feature",
  "properties": {
    "gn:admin1_code":"67.0",
    "gn:asciiname":"Florica",
    "gn:country_code":"MD",
    "gn:dem":76,
    "gn:feature_class":"P",
    "gn:feature_code":"PPL",
    "gn:name":"Florica",
    "gn:population":0,
    "gn:timezone":"Europe/Chisinau",
    "iso:country":"MD",
    "name:ceb_x_preferred":[
        "Florica"
    ],
    "name:ita_x_preferred":[
        "Florica"
    ],
    "name:msa_x_preferred":[
        "Florica"
    ],
    "name:nld_x_preferred":[
        "Florica"
    ],
    "name:por_x_preferred":[
        "Florica"
    ],
    "name:ron_x_preferred":[
        "Florica"
    ],
    "name:rus_x_preferred":[
        "\u0424\u043b\u043e\u0440\u0438\u043a\u0430"
    ],
    "name:srp_x_preferred":[
        "\u041e\u043f\u0448\u0442\u0438\u043d\u0430 \u0424\u043b\u043e\u0440\u0438\u043a\u0430"
    ],
    "name:ukr_x_preferred":[
        "\u0424\u043b\u043e\u0440\u0456\u043a\u0430"
    ],
    "name:und_x_variant":[
        "Florika"
    ],
    "name:vol_x_preferred":[
        "Florica"
    ],
    "name:zho_x_preferred":[
        "\u5f17\u6d1b\u91cc\u5361\u9109"
    ],
    "wof:name":"Florica",
    "wof:placetype":"locality"
},
  "geometry": {"coordinates":[29.2224,46.68944000000001],"type":"Point"}
}