{
  "type": "Feature",
  "properties": {
    "gn:admin1_code":"87.0",
    "gn:asciiname":"Parcani",
    "gn:country_code":"MD",
    "gn:dem":188,
    "gn:feature_class":"P",
    "gn:feature_code":"PPL",
    "gn:name":"Parcani",
    "gn:population":0,
    "gn:timezone":"Europe/Chisinau",
    "iso:country":"MD",
    "name:rus_x_preferred":[
        "\u041f\u0430\u0440\u043a\u0430\u043d\u044b"
    ],
    "name:und_x_variant":[
        "Parkan\u2019",
        "Parkany",
        "Parcani"
    ],
    "wof:name":"Parcani",
    "wof:placetype":"locality"
},
  "geometry": {"coordinates":[28.28659,48.0617],"type":"Point"}
}