{
  "type": "Feature",
  "properties": {
    "gn:population":5700,
    "iso:country":"MD",
    "name:ceb_x_preferred":[
        "St\u0103uceni"
    ],
    "name:dan_x_preferred":[
        "St\u0103uceni"
    ],
    "name:deu_x_preferred":[
        "St\u0103uceni"
    ],
    "name:eng_x_preferred":[
        "St\u0103uceni"
    ],
    "name:eus_x_preferred":[
        "St\u0103uceni"
    ],
    "name:fra_x_preferred":[
        "St\u0103uceni"
    ],
    "name:ita_x_preferred":[
        "St\u0103uceni"
    ],
    "name:nld_x_preferred":[
        "St\u0103uceni"
    ],
    "name:nno_x_preferred":[
        "St\u0103uceni"
    ],
    "name:nob_x_preferred":[
        "St\u0103uceni"
    ],
    "name:por_x_preferred":[
        "St\u0103uceni"
    ],
    "name:ron_x_preferred":[
        "St\u0103uceni"
    ],
    "name:ron_x_variant":[
        "Comuna Piatra"
    ],
    "name:rus_x_preferred":[
        "\u0421\u0442\u0430\u0432\u0447\u0435\u043d\u044b"
    ],
    "name:spa_x_preferred":[
        "St\u0103uceni"
    ],
    "name:swe_x_preferred":[
        "St\u0103uceni"
    ],
    "name:ukr_x_preferred":[
        "\u0421\u0442\u0435\u0443\u0447\u0435\u043d\u044c"
    ],
    "name:und_x_variant":[
        "Stavcheny"
    ],
    "qs:a0":"Moldova",
    "qs:a1":"*mun.Chi\u015fin\u0103u",
    "qs:a1_alt":"Chisinau",
    "qs:a1r":"0",
    "qs:adm0":"Moldova",
    "qs:la_lc":"*",
    "qs:level":"locality",
    "qs:loc":"St\u0103uceni",
    "qs:loc_alt":"Stauceni",
    "qs:pop":0,
    "qs:type":"buffered point",
    "wd:wordcount":88,
    "wof:name":"St\u0103uceni",
    "wof:placetype":"locality",
    "wof:population":5700
},
  "geometry": {"coordinates":[28.868879,47.09409],"type":"Point"}
}