{
  "type": "Feature",
  "properties": {
    "gn:admin1_code":"68.0",
    "gn:asciiname":"Maximeni",
    "gn:country_code":"MD",
    "gn:dem":120,
    "gn:feature_class":"P",
    "gn:feature_code":"PPL",
    "gn:name":"Maximeni",
    "gn:population":0,
    "gn:timezone":"Europe/Chisinau",
    "iso:country":"MD",
    "name:rus_x_preferred":[
        "\u041c\u0430\u043a\u0441\u0438\u043c\u0435\u043d\u044b"
    ],
    "name:und_x_variant":[
        "Maksimeny",
        "Maksimen\u2019 Vtoroy",
        "Maksimeny Vtoryye",
        "Maksimovka",
        "Maximeni II",
        "Maximeni"
    ],
    "wof:name":"Maximeni",
    "wof:placetype":"locality"
},
  "geometry": {"coordinates":[28.59614,46.57135],"type":"Point"}
}