{
  "type": "Feature",
  "properties": {
    "iso:country":"MD",
    "name:baq_x_preferred":[
        "Vertiujeni"
    ],
    "name:dan_x_preferred":[
        "Vertiujeni"
    ],
    "name:dut_x_preferred":[
        "Vertiujeni"
    ],
    "name:eng_x_preferred":[
        "Vertyuzhany"
    ],
    "name:eng_x_variant":[
        "Vertyuzhani",
        "Vertyuzhen'",
        "Vyrtezhen Sat",
        "Vyrtezheni",
        "Vertiujeni"
    ],
    "name:fre_x_preferred":[
        "Vertiujeni"
    ],
    "name:geo_x_preferred":[
        "\u10d5\u10d4\u10e0\u10e2\u10d8\u10e3\u10df\u10d0\u10dc\u10d8"
    ],
    "name:ger_x_preferred":[
        "Vertiujeni"
    ],
    "name:ita_x_preferred":[
        "Vertiujeni"
    ],
    "name:nno_x_preferred":[
        "Vertiujeni"
    ],
    "name:nob_x_preferred":[
        "Vertiujeni"
    ],
    "name:pol_x_preferred":[
        "Vertiujeni"
    ],
    "name:por_x_preferred":[
        "Vertiujeni"
    ],
    "name:ron_x_preferred":[
        "Vertiujeni"
    ],
    "name:ron_x_variant":[
        "Vertlujeni"
    ],
    "name:rum_x_preferred":[
        "Vertiujeni"
    ],
    "name:rus_x_preferred":[
        "\u0412\u0435\u0440\u0442\u044e\u0436\u0435\u043d\u044c"
    ],
    "name:rus_x_variant":[
        "\u0412\u0435\u0440\u0442\u044e\u0436\u0430\u043d\u044b"
    ],
    "name:spa_x_preferred":[
        "Vertiujeni"
    ],
    "name:swe_x_preferred":[
        "Vertiujeni"
    ],
    "name:ukr_x_preferred":[
        "\u0412\u0435\u0440\u0442\u044e\u0436\u0435\u043d\u044c"
    ],
    "name:und_x_colloquial":[
        "Vartejenii-Sat"
    ],
    "name:und_x_preferred":[
        "Vertiujeni"
    ],
    "name:und_x_variant":[
        "V\u00e2rtejenii-Sat"
    ],
    "name:unk_x_variant":[
        "Vertyuzhani"
    ],
    "qs:a0":"Moldova",
    "qs:a1":"*Flore\u015fti",
    "qs:a1_alt":"Floresti",
    "qs:a1r":"0",
    "qs:adm0":"Moldova",
    "qs:la_lc":"*",
    "qs:level":"locality",
    "qs:loc":"Vertiujeni",
    "qs:loc_alt":"Vertiujeni",
    "qs:pop":0,
    "qs:type":"buffered point",
    "wd:wordcount":82,
    "wof:lang":[
        "unk"
    ],
    "wof:name":"Vertiujeni",
    "wof:placetype":"locality"
},
  "geometry": {"coordinates":[28.54043,47.994838],"type":"Point"}
}