{
  "type": "Feature",
  "properties": {
    "iso:country":"MD",
    "name:ceb_x_preferred":[
        "Mole\u0219ti"
    ],
    "name:dan_x_preferred":[
        "Mole\u0219ti"
    ],
    "name:deu_x_preferred":[
        "Mole\u0219ti"
    ],
    "name:eng_x_preferred":[
        "Moleshty"
    ],
    "name:eng_x_variant":[
        "Malayeshty",
        "Molesht'",
        "Mole\u0219ti"
    ],
    "name:eus_x_preferred":[
        "Mole\u0219ti"
    ],
    "name:fra_x_preferred":[
        "Mole\u0219ti"
    ],
    "name:ita_x_preferred":[
        "Mole\u0219ti"
    ],
    "name:kat_x_preferred":[
        "\u10db\u10dd\u10da\u10d4\u10e8\u10e2\u10d8"
    ],
    "name:nld_x_preferred":[
        "Mole\u015fti"
    ],
    "name:nno_x_preferred":[
        "Mole\u0219ti"
    ],
    "name:nob_x_preferred":[
        "Mole\u0219ti"
    ],
    "name:pol_x_preferred":[
        "Mole\u0219ti"
    ],
    "name:por_x_preferred":[
        "Mole\u0219ti"
    ],
    "name:ron_x_preferred":[
        "Mole\u0219ti"
    ],
    "name:rus_x_preferred":[
        "\u041c\u043e\u043b\u0435\u0448\u0442\u044c"
    ],
    "name:rus_x_variant":[
        "\u041c\u043e\u043b\u0435\u0448\u0442\u044b"
    ],
    "name:spa_x_preferred":[
        "Mole\u0219ti"
    ],
    "name:swe_x_preferred":[
        "Mole\u0219ti"
    ],
    "name:ukr_x_preferred":[
        "\u041c\u043e\u043b\u0435\u0448\u0442\u044c"
    ],
    "name:ukr_x_variant":[
        "\u0427\u0435\u043d\u0430\u043a"
    ],
    "name:und_x_colloquial":[
        "Molesti"
    ],
    "qs:a0":"Moldova",
    "qs:a1":"*Ialoveni",
    "qs:a1_alt":"Ialoveni",
    "qs:a1r":"0",
    "qs:adm0":"Moldova",
    "qs:la_lc":"*",
    "qs:level":"locality",
    "qs:loc":"Mole\u015fti",
    "qs:loc_alt":"Molesti",
    "qs:pop":0,
    "qs:type":"buffered point",
    "wd:wordcount":44,
    "wof:lang":[
        "unk"
    ],
    "wof:name":"Mole\u015fti",
    "wof:placetype":"locality"
},
  "geometry": {"coordinates":[28.775921,46.786686],"type":"Point"}
}