{
  "type": "Feature",
  "properties": {
    "iso:country":"MD",
    "name:bul_x_preferred":[
        "\u0422\u043e\u043c\u0430\u0439"
    ],
    "name:ceb_x_preferred":[
        "Tomai"
    ],
    "name:dan_x_preferred":[
        "Tomai"
    ],
    "name:deu_x_preferred":[
        "Tomai"
    ],
    "name:eng_x_preferred":[
        "Tomai"
    ],
    "name:eus_x_preferred":[
        "Tomai"
    ],
    "name:fra_x_preferred":[
        "Tomai"
    ],
    "name:ita_x_preferred":[
        "Tomai"
    ],
    "name:kat_x_preferred":[
        "\u10e2\u10dd\u10db\u10d0\u10d8"
    ],
    "name:nld_x_preferred":[
        "Tomai"
    ],
    "name:nno_x_preferred":[
        "Tomai"
    ],
    "name:nob_x_preferred":[
        "Tomai"
    ],
    "name:pol_x_preferred":[
        "Tomai"
    ],
    "name:por_x_preferred":[
        "Tomai"
    ],
    "name:ron_x_preferred":[
        "Tomai"
    ],
    "name:rus_x_preferred":[
        "\u0422\u043e\u043c\u0430\u0439"
    ],
    "name:spa_x_preferred":[
        "Tomai"
    ],
    "name:swe_x_preferred":[
        "Tomai"
    ],
    "name:ukr_x_preferred":[
        "\u0422\u043e\u043c\u0430\u0439"
    ],
    "name:ukr_x_variant":[
        "\u0411\u043e\u0433\u0456\u0447\u0435\u043d\u044c"
    ],
    "name:und_x_preferred":[
        "Tomai"
    ],
    "name:unk_x_variant":[
        "Tomay"
    ],
    "qs:a0":"Moldova",
    "qs:a1":"*Leova",
    "qs:a1_alt":"Leova",
    "qs:a1r":"0",
    "qs:adm0":"Moldova",
    "qs:la_lc":"*",
    "qs:level":"locality",
    "qs:loc":"Tomai",
    "qs:loc_alt":"Tomai",
    "qs:pop":0,
    "qs:type":"buffered point",
    "wd:wordcount":35,
    "wof:lang":[
        "unk"
    ],
    "wof:name":"Tomai",
    "wof:placetype":"locality"
},
  "geometry": {"coordinates":[28.321848,46.573887],"type":"Point"}
}