{
  "type": "Feature",
  "properties": {
    "iso:country":"MD",
    "name:ceb_x_preferred":[
        "Cini\u0219eu\u021bi"
    ],
    "name:dan_x_preferred":[
        "Cini\u0219eu\u021bi"
    ],
    "name:deu_x_preferred":[
        "Cini\u0219eu\u021bi"
    ],
    "name:eng_x_preferred":[
        "Chinishevtsy"
    ],
    "name:eng_x_variant":[
        "Chinisheuts'",
        "Chinisheutsi",
        "Chinsheutsy",
        "Cini\u0219eu\u021bi"
    ],
    "name:eus_x_preferred":[
        "Cini\u0219eu\u021bi"
    ],
    "name:fra_x_preferred":[
        "Cini\u0219eu\u021bi"
    ],
    "name:ita_x_preferred":[
        "Cini\u0219eu\u021bi"
    ],
    "name:ita_x_variant":[
        "Cini\u015feu\u0163i"
    ],
    "name:kat_x_preferred":[
        "\u10e9\u10d8\u10dc\u10d8\u10e8\u10d4\u10e3\u10ea\u10d8"
    ],
    "name:nld_x_preferred":[
        "Cini\u015feu\u0163i"
    ],
    "name:nno_x_preferred":[
        "Cini\u0219eu\u021bi"
    ],
    "name:nob_x_preferred":[
        "Cini\u0219eu\u021bi"
    ],
    "name:pol_x_preferred":[
        "Cini\u0219eu\u021bi"
    ],
    "name:por_x_preferred":[
        "Cini\u0219eu\u021bi"
    ],
    "name:ron_x_preferred":[
        "Cini\u0219eu\u021bi"
    ],
    "name:rus_x_preferred":[
        "\u0427\u0438\u043d\u0438\u0448\u0435\u0443\u0446\u044b"
    ],
    "name:spa_x_preferred":[
        "Cini\u0219eu\u021bi"
    ],
    "name:swe_x_preferred":[
        "Cini\u0219eu\u021bi"
    ],
    "name:ukr_x_preferred":[
        "\u0427\u0438\u043d\u0456\u0448\u0435\u0443\u0446\u044c"
    ],
    "name:ukr_x_variant":[
        "\u0413\u0456\u0434\u0456\u0433\u0456\u0447"
    ],
    "name:und_x_colloquial":[
        "Ciniseuti"
    ],
    "name:und_x_variant":[
        "Chinisheutsy"
    ],
    "qs:a0":"Moldova",
    "qs:a1":"*Rezina",
    "qs:a1_alt":"Rezina",
    "qs:a1r":"0",
    "qs:adm0":"Moldova",
    "qs:la_lc":"*",
    "qs:level":"locality",
    "qs:loc":"Cini\u015feu\u0163i",
    "qs:loc_alt":"Ciniseuti",
    "qs:pop":0,
    "qs:type":"buffered point",
    "wd:wordcount":33,
    "wof:lang":[
        "unk"
    ],
    "wof:name":"Cini\u015feu\u0163i",
    "wof:placetype":"locality"
},
  "geometry": {"coordinates":[28.857418,47.696263],"type":"Point"}
}