{
  "type": "Feature",
  "properties": {
    "gn:admin1_code":"64.0",
    "gn:asciiname":"Stoianovca",
    "gn:cc2":"MD",
    "gn:country_code":"MD",
    "gn:dem":39,
    "gn:feature_class":"P",
    "gn:feature_code":"PPL",
    "gn:name":"Stoianovca",
    "gn:population":0,
    "gn:timezone":"Europe/Chisinau",
    "iso:country":"MD",
    "name:und_x_variant":[
        "Stoine\u015fti",
        "Stoyanovka"
    ],
    "wof:name":"Stoianovca",
    "wof:placetype":"locality"
},
  "geometry": {"coordinates":[28.20444,46.0275],"type":"Point"}
}