{
  "type": "Feature",
  "properties": {
    "gn:admin1_code":"64.0",
    "gn:asciiname":"Stoianovca",
    "gn:cc2":"MD",
    "gn:country_code":"MD",
    "gn:dem":39,
    "gn:feature_class":"P",
    "gn:feature_code":"PPL",
    "gn:name":"Stoianovca",
    "gn:population":0,
    "gn:timezone":"Europe/Chisinau",
    "iso:country":"MD",
    "name:bul_x_preferred":[
        "\u0421\u0442\u043e\u044f\u043d\u043e\u0432\u043a\u0430"
    ],
    "name:ita_x_preferred":[
        "Stoianovca"
    ],
    "name:kat_x_preferred":[
        "\u10e1\u10e2\u10dd\u10d8\u10d0\u10dc\u10dd\u10d5\u10d9\u10d0"
    ],
    "name:ron_x_preferred":[
        "Stoianovca"
    ],
    "name:rus_x_preferred":[
        "\u0421\u0442\u043e\u044f\u043d\u043e\u0432\u043a\u0430"
    ],
    "name:ukr_x_preferred":[
        "\u0421\u0442\u043e\u044f\u043d\u0456\u0432\u043a\u0430"
    ],
    "name:und_x_variant":[
        "Stoine\u015fti",
        "Stoyanovka"
    ],
    "wof:name":"Stoianovca",
    "wof:placetype":"locality"
},
  "geometry": {"coordinates":[28.20444,46.0275],"type":"Point"}
}