{
  "type": "Feature",
  "properties": {
    "iso:country":"MD",
    "name:eng_x_preferred":[
        "R\u0103c\u0103ria"
    ],
    "name:ita_x_preferred":[
        "R\u0103c\u0103ria"
    ],
    "name:kat_x_preferred":[
        "\u10e0\u10d4\u10d9\u10d4\u10e0\u10d8\u10d0"
    ],
    "name:nld_x_preferred":[
        "R\u0103c\u0103ria"
    ],
    "name:ron_x_preferred":[
        "R\u0103c\u0103ria"
    ],
    "name:rus_x_preferred":[
        "\u0420\u044d\u043a\u044d\u0440\u0438\u044f"
    ],
    "name:rus_x_variant":[
        "\u0420\u0430\u043a\u0430\u0440\u0438\u044f"
    ],
    "name:ukr_x_preferred":[
        "\u0420\u0435\u043a\u0435\u0440\u0456\u044f"
    ],
    "name:und_x_variant":[
        "Rakariya"
    ],
    "qs:a0":"Moldova",
    "qs:a1":"*R\u00ee\u015fcani",
    "qs:a1_alt":"Riscani",
    "qs:a1r":"0",
    "qs:adm0":"Moldova",
    "qs:la_lc":"*",
    "qs:level":"locality",
    "qs:loc":"R\u0103c\u0103ria",
    "qs:loc_alt":"Racaria",
    "qs:pop":0,
    "qs:type":"buffered point",
    "wd:wordcount":34,
    "wof:name":"R\u0103c\u0103ria",
    "wof:placetype":"locality"
},
  "geometry": {"coordinates":[27.612176,47.914795],"type":"Point"}
}