{
  "type": "Feature",
  "properties": {
    "gn:admin1_code":"85.0",
    "gn:asciiname":"Cozesti",
    "gn:country_code":"MD",
    "gn:dem":89,
    "gn:feature_class":"P",
    "gn:feature_code":"PPL",
    "gn:name":"Coze\u015fti",
    "gn:population":0,
    "gn:timezone":"Europe/Chisinau",
    "iso:country":"MD",
    "name:rus_x_preferred":[
        "\u041a\u043e\u0437\u0435\u0448\u0442\u044b"
    ],
    "name:und_x_variant":[
        "Kozeshti",
        "Kozeshty",
        "Kozesht\u2019",
        "Coze\u015fti"
    ],
    "wof:name":"Cozesti",
    "wof:placetype":"locality"
},
  "geometry": {"coordinates":[28.18244,47.56875],"type":"Point"}
}