{
  "type": "Feature",
  "properties": {
    "gn:admin1_code":"67.0",
    "gn:asciiname":"Causanii-Vechi",
    "gn:cc2":"MD",
    "gn:country_code":"MD",
    "gn:dem":15,
    "gn:feature_class":"P",
    "gn:feature_code":"PPL",
    "gn:name":"C\u0103u\u015fanii-Vechi",
    "gn:population":0,
    "gn:timezone":"Europe/Chisinau",
    "iso:country":"MD",
    "name:und_x_variant":[
        "Kaushani-Vek'",
        "Staryye Kaushany"
    ],
    "wof:name":"Causanii-Vechi",
    "wof:placetype":"locality"
},
  "geometry": {"coordinates":[29.44028,46.64722],"type":"Point"}
}