{
  "type": "Feature",
  "properties": {
    "gn:admin1_code":"82.0",
    "gn:asciiname":"Hijdieni",
    "gn:country_code":"MD",
    "gn:dem":132,
    "gn:feature_class":"P",
    "gn:feature_code":"PPL",
    "gn:name":"H\u00eejdieni",
    "gn:population":0,
    "gn:timezone":"Europe/Chisinau",
    "iso:country":"MD",
    "name:rus_x_preferred":[
        "\u0413\u0438\u0436\u0434\u0438\u044f\u043d\u044b"
    ],
    "name:und_x_variant":[
        "Gyzhdlyeni",
        "Gyzhdiyen\u2019",
        "Gyzhdiyeni",
        "H\u00e2jdieni",
        "Gizhdiyany",
        "H\u00eejdieni"
    ],
    "wof:name":"Hijdieni",
    "wof:placetype":"locality"
},
  "geometry": {"coordinates":[28.91472000000001,47.45909],"type":"Point"}
}