{
  "type": "Feature",
  "properties": {
    "iso:country":"MD",
    "name:deu_x_preferred":[
        "V\u0103deni"
    ],
    "name:eng_x_preferred":[
        "V\u0103deni"
    ],
    "name:ita_x_preferred":[
        "V\u0103deni"
    ],
    "name:kat_x_preferred":[
        "\u10d5\u10d4\u10d3\u10d4\u10dc\u10d8"
    ],
    "name:nld_x_preferred":[
        "V\u0103deni"
    ],
    "name:ron_x_preferred":[
        "V\u0103deni"
    ],
    "name:rus_x_preferred":[
        "\u0412\u0430\u0434\u044f\u043d\u044b"
    ],
    "name:ukr_x_preferred":[
        "\u0412\u0430\u0434\u0435\u043d\u044c"
    ],
    "name:und_x_variant":[
        "Vodyany",
        "Vaden\u2019"
    ],
    "qs:a0":"Moldova",
    "qs:a1":"*Soroca",
    "qs:a1_alt":"Soroca",
    "qs:a1r":"0",
    "qs:adm0":"Moldova",
    "qs:la_lc":"*",
    "qs:level":"locality",
    "qs:loc":"V\u0103deni",
    "qs:loc_alt":"Vadeni",
    "qs:pop":0,
    "qs:type":"buffered point",
    "wd:wordcount":29,
    "wof:lang":[
        "unk"
    ],
    "wof:name":"V\u0103deni",
    "wof:placetype":"locality"
},
  "geometry": {"coordinates":[28.224016,48.012024],"type":"Point"}
}