{
  "type": "Feature",
  "properties": {
    "gn:admin1_code":"82.0",
    "gn:asciiname":"Ocnita-Tarani",
    "gn:country_code":"MD",
    "gn:dem":50,
    "gn:feature_class":"P",
    "gn:feature_code":"PPL",
    "gn:name":"Ocni\u0163a-\u0162\u0103rani",
    "gn:population":0,
    "gn:timezone":"Europe/Chisinau",
    "iso:country":"MD",
    "name:rus_x_preferred":[
        "\u041e\u043a\u043d\u0438\u0446\u0430-\u0426\u044d\u0440\u0430\u043d\u044c"
    ],
    "name:und_x_variant":[
        "Oknitsa-Tseran\u2019",
        "Oknitsa Tsaran\u2019",
        "Ocni\u0163a-\u0162\u0103rani"
    ],
    "wof:name":"Ocnita-Tarani",
    "wof:placetype":"locality"
},
  "geometry": {"coordinates":[28.72471,47.45838],"type":"Point"}
}