{
  "type": "Feature",
  "properties": {
    "gn:admin1_code":"59.0",
    "gn:asciiname":"Cretoaia",
    "gn:country_code":"MD",
    "gn:dem":81,
    "gn:feature_class":"P",
    "gn:feature_code":"PPL",
    "gn:name":"Cre\u0163oaia",
    "gn:population":0,
    "gn:timezone":"Europe/Chisinau",
    "iso:country":"MD",
    "name:rus_x_preferred":[
        "\u041a\u0440\u0435\u0446\u043e\u0430\u044f"
    ],
    "name:und_x_variant":[
        "Kretsoya",
        "Kretsoaya",
        "Cre\u0163oaia"
    ],
    "wof:name":"Cretoaia",
    "wof:placetype":"locality"
},
  "geometry": {"coordinates":[29.13431,46.86627],"type":"Point"}
}