{
  "type": "Feature",
  "properties": {
    "gn:admin1_code":"64.0",
    "gn:asciiname":"Gigalboaia",
    "gn:cc2":"MD",
    "gn:country_code":"MD",
    "gn:dem":65,
    "gn:feature_class":"P",
    "gn:feature_code":"PPL",
    "gn:name":"Gig\u0103lboaia",
    "gn:population":0,
    "gn:timezone":"Europe/Chisinau",
    "iso:country":"MD",
    "name:und_x_variant":[
        "Dzhigalboy"
    ],
    "wof:name":"Gigalboaia",
    "wof:placetype":"locality"
},
  "geometry": {"coordinates":[28.41194,45.93694],"type":"Point"}
}