{
  "type": "Feature",
  "properties": {
    "iso:country":"MD",
    "name:eng_x_preferred":[
        "Beshtymik"
    ],
    "name:eng_x_variant":[
        "Beshtemak",
        "Beshtymak",
        "Be\u0219temac"
    ],
    "name:ita_x_preferred":[
        "Be\u0219temac"
    ],
    "name:ita_x_variant":[
        "Be\u015ftemac"
    ],
    "name:kat_x_preferred":[
        "\u10d1\u10d4\u10e8\u10e2\u10d4\u10db\u10d0\u10d9\u10d8"
    ],
    "name:nld_x_preferred":[
        "Be\u015ftemac"
    ],
    "name:ron_x_preferred":[
        "Be\u0219temac"
    ],
    "name:rus_x_preferred":[
        "\u0411\u0435\u0448\u0442\u0435\u043c\u0430\u043a"
    ],
    "name:ukr_x_preferred":[
        "\u0411\u0435\u0448\u0442\u0435\u043c\u0430\u043a"
    ],
    "name:und_x_colloquial":[
        "Bestemac"
    ],
    "qs:a0":"Moldova",
    "qs:a1":"*Leova",
    "qs:a1_alt":"Leova",
    "qs:a1r":"0",
    "qs:adm0":"Moldova",
    "qs:la_lc":"*",
    "qs:level":"locality",
    "qs:loc":"Be\u015ftemac",
    "qs:loc_alt":"Bestemac",
    "qs:pop":0,
    "qs:type":"buffered point",
    "wd:wordcount":34,
    "wof:lang":[
        "unk"
    ],
    "wof:name":"Be\u015ftemac",
    "wof:placetype":"locality"
},
  "geometry": {"coordinates":[28.530503,46.527794],"type":"Point"}
}