{
  "type": "Feature",
  "properties": {
    "iso:country":"MD",
    "name:eng_x_preferred":[
        "Maririci"
    ],
    "name:eng_x_variant":[
        "Marinich",
        "Marinych",
        "Marinici"
    ],
    "name:fra_x_preferred":[
        "Marinici"
    ],
    "name:ita_x_preferred":[
        "Marinici"
    ],
    "name:kat_x_preferred":[
        "\u10db\u10d0\u10e0\u10d8\u10dc\u10d8\u10e9\u10d8"
    ],
    "name:nld_x_preferred":[
        "Marinici"
    ],
    "name:ron_x_preferred":[
        "Marinici"
    ],
    "name:rus_x_preferred":[
        "\u041c\u0430\u0440\u0438\u043d\u0438\u0447"
    ],
    "name:ukr_x_preferred":[
        "\u041c\u0430\u0440\u0456\u043d\u0456\u0447"
    ],
    "qs:a0":"Moldova",
    "qs:a1":"*Nisporeni",
    "qs:a1_alt":"Nisporeni",
    "qs:a1r":"0",
    "qs:adm0":"Moldova",
    "qs:la_lc":"*",
    "qs:level":"locality",
    "qs:loc":"Marinici",
    "qs:loc_alt":"Marinici",
    "qs:pop":0,
    "qs:type":"buffered point",
    "wd:wordcount":46,
    "wof:lang":[
        "unk"
    ],
    "wof:name":"Marinici",
    "wof:placetype":"locality"
},
  "geometry": {"coordinates":[28.166374,46.970043],"type":"Point"}
}