{
  "type": "Feature",
  "properties": {
    "gn:admin1_code":"91.0",
    "gn:asciiname":"Ratus",
    "gn:country_code":"MD",
    "gn:dem":51,
    "gn:feature_class":"P",
    "gn:feature_code":"PPL",
    "gn:name":"Ratu\u015f",
    "gn:population":0,
    "gn:timezone":"Europe/Chisinau",
    "iso:country":"MD",
    "name:rus_x_preferred":[
        "\u0420\u0430\u0442\u0443\u0448"
    ],
    "name:und_x_variant":[
        "Ratush",
        "Ratu\u015f"
    ],
    "wof:name":"Ratus",
    "wof:placetype":"locality"
},
  "geometry": {"coordinates":[28.50408,47.53923],"type":"Point"}
}