{
  "type": "Feature",
  "properties": {
    "iso:country":"MD",
    "name:arz_x_preferred":[
        "\u0647\u064a\u0646\u0633\u064a\u0634\u062a\u0649"
    ],
    "name:ceb_x_preferred":[
        "H\u00eence\u0219ti"
    ],
    "name:che_x_preferred":[
        "\u0425\u044b\u043d\u0447\u0435\u0448\u0442\u0438"
    ],
    "name:dan_x_preferred":[
        "H\u00eence\u0219ti"
    ],
    "name:deu_x_preferred":[
        "H\u00eence\u0219ti"
    ],
    "name:eng_x_preferred":[
        "Gynchesht'-Niorkan'"
    ],
    "name:eng_x_variant":[
        "Gancheshty",
        "Gencheshtiy",
        "H\u00eence\u0219ti"
    ],
    "name:eus_x_preferred":[
        "H\u00eence\u0219ti"
    ],
    "name:fra_x_preferred":[
        "H\u00eence\u0219ti"
    ],
    "name:gle_x_preferred":[
        "H\u00eence\u0219ti"
    ],
    "name:ita_x_preferred":[
        "H\u00eence\u0219ti"
    ],
    "name:ita_x_variant":[
        "H\u00eence\u015fti"
    ],
    "name:kat_x_preferred":[
        "\u10f0\u10d8\u10dc\u10e9\u10d4\u10e8\u10e2\u10d8"
    ],
    "name:nld_x_preferred":[
        "H\u00eence\u015fti"
    ],
    "name:nno_x_preferred":[
        "H\u00eence\u0219ti"
    ],
    "name:nob_x_preferred":[
        "H\u00eence\u0219ti"
    ],
    "name:pol_x_preferred":[
        "H\u00eence\u0219ti"
    ],
    "name:por_x_preferred":[
        "H\u00eence\u0219ti"
    ],
    "name:ron_x_preferred":[
        "H\u00eence\u0219ti"
    ],
    "name:ron_x_variant":[
        "H\u00e2nce\u0219ti",
        "Comuna Dumbr\u0103vi\u021ba"
    ],
    "name:rus_x_preferred":[
        "\u0425\u044b\u043d\u0447\u0435\u0448\u0442\u044c"
    ],
    "name:rus_x_variant":[
        "\u0425\u044b\u043d\u0447\u0435\u0448\u0442\u044b",
        "\u0413\u0430\u043d\u0447\u0435\u0448\u0442\u044b"
    ],
    "name:spa_x_preferred":[
        "H\u00eence\u0219ti"
    ],
    "name:swe_x_preferred":[
        "H\u00eence\u0219ti"
    ],
    "name:tat_x_preferred":[
        "\u0425\u044b\u043d\u0447\u0435\u0448\u0442\u0438"
    ],
    "name:ukr_x_preferred":[
        "\u0425\u0438\u043d\u0447\u0435\u0448\u0442\u044c"
    ],
    "name:und_x_colloquial":[
        "Hancestii Niorcani",
        "Hincesti"
    ],
    "name:und_x_variant":[
        "H\u00e2nce\u015ftii Niorcani"
    ],
    "qs:a0":"Moldova",
    "qs:a1":"*F\u0103le\u015fti",
    "qs:a1_alt":"Falesti",
    "qs:a1r":"0",
    "qs:adm0":"Moldova",
    "qs:la_lc":"*",
    "qs:level":"locality",
    "qs:loc":"H\u00eence\u015fti",
    "qs:loc_alt":"Hincesti",
    "qs:pop":0,
    "qs:type":"buffered point",
    "wd:wordcount":43,
    "wof:lang":[
        "unk"
    ],
    "wof:name":"H\u00eence\u015fti",
    "wof:placetype":"locality"
},
  "geometry": {"coordinates":[27.504513,47.545017],"type":"Point"}
}