{
  "type": "Feature",
  "properties": {
    "iso:country":"MD",
    "name:ceb_x_preferred":[
        "Cobasna"
    ],
    "name:ces_x_preferred":[
        "Cobasna"
    ],
    "name:ces_x_variant":[
        "Kolbasna"
    ],
    "name:dan_x_preferred":[
        "Cobasna"
    ],
    "name:deu_x_preferred":[
        "Cobasna"
    ],
    "name:eng_x_preferred":[
        "Cobasna"
    ],
    "name:eus_x_preferred":[
        "Cobasna"
    ],
    "name:fra_x_preferred":[
        "Cobasna"
    ],
    "name:ita_x_preferred":[
        "Cobasna"
    ],
    "name:nld_x_preferred":[
        "Cobasna"
    ],
    "name:nno_x_preferred":[
        "Cobasna"
    ],
    "name:nob_x_preferred":[
        "Cobasna"
    ],
    "name:pol_x_preferred":[
        "Cobasna"
    ],
    "name:por_x_preferred":[
        "Cobasna"
    ],
    "name:ron_x_preferred":[
        "Cobasna"
    ],
    "name:ron_x_variant":[
        "Colbasna"
    ],
    "name:rus_x_preferred":[
        "\u041a\u043e\u043b\u0431\u0430\u0441\u043d\u0430"
    ],
    "name:spa_x_preferred":[
        "Cobasna"
    ],
    "name:swe_x_preferred":[
        "Cobasna"
    ],
    "name:tur_x_preferred":[
        "Cobasna"
    ],
    "name:ukr_x_preferred":[
        "\u041a\u043e\u043b\u0431\u0430\u0441\u043d\u0430"
    ],
    "name:ukr_x_variant":[
        "\u0413\u0456\u043d\u0434\u0435\u0448\u0442\u0438"
    ],
    "qs:a0":"Moldova",
    "qs:a1":"*UAT din St\u00eenga Nistrului",
    "qs:a1_alt":"Unitatile administrativ-teritoriale din stinga Nistrului",
    "qs:a1r":"0",
    "qs:adm0":"Moldova",
    "qs:la_lc":"*",
    "qs:level":"locality",
    "qs:loc":"Cobasna",
    "qs:loc_alt":"Cobasna",
    "qs:pop":0,
    "qs:type":"buffered point",
    "wd:wordcount":220,
    "wof:name":"Cobasna",
    "wof:placetype":"locality"
},
  "geometry": {"coordinates":[29.20743,47.785362],"type":"Point"}
}