{
  "type": "Feature",
  "properties": {
    "gn:admin1_code":"81.0",
    "gn:asciiname":"Birladeni",
    "gn:country_code":"MD",
    "gn:dem":179,
    "gn:feature_class":"P",
    "gn:feature_code":"PPL",
    "gn:name":"B\u00eerl\u0103deni",
    "gn:population":0,
    "gn:timezone":"Europe/Chisinau",
    "iso:country":"MD",
    "name:rus_x_preferred":[
        "\u0411\u044b\u0440\u043b\u0430\u0434\u044f\u043d\u044b"
    ],
    "name:und_x_variant":[
        "Barladen\u2019",
        "Byrladyany",
        "Barlyadyany",
        "B\u00e2rl\u0103deni",
        "Borladyany",
        "B\u00eerl\u0103deni"
    ],
    "wof:name":"Birladeni",
    "wof:placetype":"locality"
},
  "geometry": {"coordinates":[27.42448,48.26504],"type":"Point"}
}