{
  "type": "Feature",
  "properties": {
    "gn:admin1_code":"89.0",
    "gn:asciiname":"Onesti",
    "gn:country_code":"MD",
    "gn:dem":93,
    "gn:feature_class":"P",
    "gn:feature_code":"PPL",
    "gn:name":"One\u015fti",
    "gn:population":0,
    "gn:timezone":"Europe/Chisinau",
    "iso:country":"MD",
    "name:rus_x_preferred":[
        "\u041e\u043d\u0435\u0448\u0442\u044b"
    ],
    "name:und_x_variant":[
        "Oneshti",
        "Oneshty",
        "Onesht\u2019",
        "One\u015fti"
    ],
    "wof:name":"Onesti",
    "wof:placetype":"locality"
},
  "geometry": {"coordinates":[28.54729,47.28101],"type":"Point"}
}