{
  "type": "Feature",
  "properties": {
    "gn:admin1_code":"83.0",
    "gn:asciiname":"Lipceni",
    "gn:country_code":"MD",
    "gn:dem":190,
    "gn:feature_class":"P",
    "gn:feature_code":"PPL",
    "gn:name":"Lipceni",
    "gn:population":0,
    "gn:timezone":"Europe/Chisinau",
    "iso:country":"MD",
    "name:ita_x_preferred":[
        "Lipceni"
    ],
    "name:kat_x_preferred":[
        "\u10da\u10d8\u10de\u10e9\u10d4\u10dc\u10d8"
    ],
    "name:ron_x_preferred":[
        "Lipceni"
    ],
    "name:rus_x_preferred":[
        "\u041b\u0438\u043f\u0447\u0435\u043d\u044b"
    ],
    "name:ukr_x_preferred":[
        "\u041b\u0456\u043f\u0447\u0435\u043d\u044c"
    ],
    "name:und_x_variant":[
        "Lipch\u00ebny",
        "Lipchen\u2019",
        "Lipcheni",
        "Lipcheny"
    ],
    "wof:name":"Lipceni",
    "wof:placetype":"locality"
},
  "geometry": {"coordinates":[28.871,47.80852],"type":"Point"}
}