{
  "type": "Feature",
  "properties": {
    "gn:gn_country":"MD",
    "gn:gn_fcode":"PPL",
    "gn:gn_pop":0,
    "iso:country":"MD",
    "name:unk_x_variant":[
        "Grechen\u2019"
    ],
    "qs_pg:aaroncc":"MD",
    "qs_pg:gn_country":"MD",
    "qs_pg:gn_fcode":"PPL",
    "qs_pg:gn_pop":0,
    "qs_pg:name":"Greci",
    "qs_pg:name_adm0":"Rom\u00e2nia",
    "qs_pg:name_adm1":"Tulcea",
    "qs_pg:photos":12,
    "qs_pg:photos_1k":2,
    "qs_pg:photos_9k":1,
    "qs_pg:photos_9r":1,
    "qs_pg:photos_all":12,
    "qs_pg:photos_sr":1,
    "qs_pg:pop_sr":0,
    "qs_pg:qs_pg_placetype":"locality",
    "qs_pg:qs_pg_placetype_gp":"Town",
    "qs_pg:woe_adm0":23424933,
    "woe:adm0_id":23424933,
    "woe:name_adm0":"Rom\u00e2nia",
    "woe:name_adm1":"Tulcea",
    "woe:placetype":"Town",
    "wof:name":"Greci",
    "wof:placetype":"locality"
},
  "geometry": {"coordinates":[28.39167,45.72167],"type":"Point"}
}