{
  "type": "Feature",
  "properties": {
    "gn:population":1800,
    "iso:country":"MD",
    "name:eng_x_preferred":[
        "Budzhak"
    ],
    "name:gag_x_preferred":[
        "Bucak"
    ],
    "name:ita_x_preferred":[
        "Bugeac"
    ],
    "name:ron_x_preferred":[
        "Bugeac"
    ],
    "name:rus_x_preferred":[
        "\u0411\u0443\u0434\u0436\u0430\u043a"
    ],
    "name:rus_x_variant":[
        "\u041a\u043e\u043c\u0440\u0430\u0442"
    ],
    "name:ukr_x_preferred":[
        "\u0411\u0443\u0434\u0436\u0430\u043a"
    ],
    "name:und_x_preferred":[
        "Bugeac"
    ],
    "name:unk_x_variant":[
        "Budzhak"
    ],
    "qs:a0":"Moldova",
    "qs:a1":"*Unitatea Teritotrial\u0103 Autonom\u0103 G\u0103g\u0103uzia",
    "qs:a1_alt":"Unitatea Teritotriala Autonoma Gagauzia",
    "qs:a1r":"0",
    "qs:adm0":"Moldova",
    "qs:la_lc":"*",
    "qs:level":"locality",
    "qs:loc":"Bugeac",
    "qs:loc_alt":"Bugeac",
    "qs:pop":0,
    "qs:type":"buffered point",
    "wd:wordcount":93,
    "wof:lang":[
        "unk"
    ],
    "wof:name":"Bugeac",
    "wof:placetype":"locality",
    "wof:population":1800
},
  "geometry": {"coordinates":[28.661516,46.365399],"type":"Point"}
}