{
  "type": "Feature",
  "properties": {
    "gn:population":9280,
    "iso:country":"MD",
    "name:eng_x_preferred":[
        "Myndreshti"
    ],
    "name:eng_x_variant":[
        "Myndresht'",
        "Myndreshty"
    ],
    "name:ita_x_preferred":[
        "M\u00eendre\u0219ti"
    ],
    "name:ron_x_preferred":[
        "M\u00eendre\u0219ti"
    ],
    "name:rus_x_preferred":[
        "\u041c\u044b\u043d\u0434\u0440\u0435\u0448\u0442\u044c"
    ],
    "name:rus_x_variant":[
        "\u041c\u044b\u043d\u0434\u0440\u0435\u0448\u0442\u044b"
    ],
    "name:ukr_x_preferred":[
        "\u041c\u0438\u043d\u0434\u0440\u0435\u0448\u0442\u044c"
    ],
    "name:und_x_colloquial":[
        "Mandresti",
        "Mindresti"
    ],
    "name:und_x_preferred":[
        "M\u00eendre\u015fti"
    ],
    "name:und_x_variant":[
        "M\u00e2ndre\u015fti"
    ],
    "name:unk_x_variant":[
        "M\u00e2ndre\u015fti"
    ],
    "qs:a0":"Moldova",
    "qs:a1":"*Telene\u015fti",
    "qs:a1_alt":"Telenesti",
    "qs:a1r":"0",
    "qs:adm0":"Moldova",
    "qs:la_lc":"*",
    "qs:level":"locality",
    "qs:loc":"M\u00eendre\u015fti",
    "qs:loc_alt":"Mindresti",
    "qs:pop":0,
    "qs:type":"buffered point",
    "wd:wordcount":34,
    "wof:lang":[
        "unk"
    ],
    "wof:name":"M\u00eendre\u015fti",
    "wof:placetype":"locality",
    "wof:population":9280
},
  "geometry": {"coordinates":[28.276659,47.502667],"type":"Point"}
}