{
  "type": "Feature",
  "properties": {
    "iso:country":"MD",
    "name:dan_x_preferred":[
        "Maximovca"
    ],
    "name:deu_x_preferred":[
        "Maximovca"
    ],
    "name:eng_x_preferred":[
        "Maximovca"
    ],
    "name:eus_x_preferred":[
        "Maximovca"
    ],
    "name:fra_x_preferred":[
        "Maximovca"
    ],
    "name:ita_x_preferred":[
        "Maximovca"
    ],
    "name:kat_x_preferred":[
        "\u10db\u10d0\u10e5\u10e1\u10d8\u10db\u10dd\u10d5\u10d9\u10d0"
    ],
    "name:nld_x_preferred":[
        "Maximovca"
    ],
    "name:nno_x_preferred":[
        "Maximovca"
    ],
    "name:nob_x_preferred":[
        "Maximovca"
    ],
    "name:pol_x_preferred":[
        "Maximovca"
    ],
    "name:por_x_preferred":[
        "Maximovca"
    ],
    "name:ron_x_preferred":[
        "Maximovca"
    ],
    "name:rus_x_preferred":[
        "\u041c\u0430\u043a\u0441\u0438\u043c\u043e\u0432\u043a\u0430"
    ],
    "name:spa_x_preferred":[
        "Maximovca"
    ],
    "name:swe_x_preferred":[
        "Maximovca"
    ],
    "name:ukr_x_preferred":[
        "\u041c\u0430\u043a\u0441\u0456\u043c\u043e\u0432\u043a\u0430"
    ],
    "name:unk_x_variant":[
        "Maksimeny"
    ],
    "qs:a0":"Moldova",
    "qs:a1":"*Anenii Noi",
    "qs:a1_alt":"Anenii Noi",
    "qs:a1r":"0",
    "qs:adm0":"Moldova",
    "qs:la_lc":"*",
    "qs:level":"locality",
    "qs:loc":"Maximovca",
    "qs:loc_alt":"Maximovca",
    "qs:pop":0,
    "qs:type":"buffered point",
    "wd:wordcount":13,
    "wof:name":"Maximovca",
    "wof:placetype":"locality"
},
  "geometry": {"coordinates":[29.014384,47.010319],"type":"Point"}
}