{
  "type": "Feature",
  "properties": {
    "iso:country":"MD",
    "name:ceb_x_preferred":[
        "Br\u00eenzeni"
    ],
    "name:dan_x_preferred":[
        "Br\u00eenzeni"
    ],
    "name:deu_x_preferred":[
        "Br\u00eenzeni"
    ],
    "name:eng_x_preferred":[
        "Brynzeny"
    ],
    "name:eng_x_variant":[
        "Brynzen'",
        "Brynzyany",
        "Br\u00eenzeni"
    ],
    "name:eus_x_preferred":[
        "Br\u00eenzeni"
    ],
    "name:fra_x_preferred":[
        "Br\u00eenzeni"
    ],
    "name:ita_x_preferred":[
        "Br\u00eenzeni"
    ],
    "name:kat_x_preferred":[
        "\u10d1\u10e0\u10d8\u10dc\u10d6\u10d4\u10dc\u10d8"
    ],
    "name:nld_x_preferred":[
        "Br\u00eenzeni"
    ],
    "name:nno_x_preferred":[
        "Br\u00eenzeni"
    ],
    "name:nob_x_preferred":[
        "Br\u00eenzeni"
    ],
    "name:pol_x_preferred":[
        "Br\u00eenzeni"
    ],
    "name:por_x_preferred":[
        "Br\u00eenzeni"
    ],
    "name:ron_x_preferred":[
        "Br\u00eenzeni"
    ],
    "name:ron_x_variant":[
        "Comuna Sudarca"
    ],
    "name:rus_x_preferred":[
        "\u0411\u0440\u044b\u043d\u0437\u0435\u043d\u044b"
    ],
    "name:spa_x_preferred":[
        "Br\u00eenzeni"
    ],
    "name:swe_x_preferred":[
        "Br\u00eenzeni"
    ],
    "name:ukr_x_preferred":[
        "\u0411\u0440\u0438\u043d\u0437\u0435\u043d\u044c"
    ],
    "name:und_x_colloquial":[
        "Branzeni",
        "Brinzeni"
    ],
    "name:und_x_variant":[
        "Br\u00e2nzeni"
    ],
    "qs:a0":"Moldova",
    "qs:a1":"*Edine\u0163",
    "qs:a1_alt":"Edinet",
    "qs:a1r":"0",
    "qs:adm0":"Moldova",
    "qs:la_lc":"*",
    "qs:level":"locality",
    "qs:loc":"Br\u00eenzeni",
    "qs:loc_alt":"Brinzeni",
    "qs:pop":0,
    "qs:type":"buffered point",
    "wd:wordcount":80,
    "wof:lang":[
        "unk"
    ],
    "wof:name":"Br\u00eenzeni",
    "wof:placetype":"locality"
},
  "geometry": {"coordinates":[27.174124,48.083462],"type":"Point"}
}