{
  "type": "Feature",
  "properties": {
    "iso:country":"MD",
    "name:ceb_x_preferred":[
        "Putine\u0219ti"
    ],
    "name:dan_x_preferred":[
        "Putine\u0219ti"
    ],
    "name:deu_x_preferred":[
        "Putine\u0219ti"
    ],
    "name:eng_x_preferred":[
        "Putineshty"
    ],
    "name:eng_x_variant":[
        "Putinesht'",
        "Putineshti",
        "Putine\u0219ti"
    ],
    "name:eus_x_preferred":[
        "Putine\u0219ti"
    ],
    "name:fra_x_preferred":[
        "Putine\u0219ti"
    ],
    "name:ita_x_preferred":[
        "Putine\u0219ti"
    ],
    "name:ita_x_variant":[
        "Putine\u015fti"
    ],
    "name:kat_x_preferred":[
        "\u10de\u10e3\u10e2\u10d8\u10dc\u10d4\u10e8\u10e2\u10d8"
    ],
    "name:nld_x_preferred":[
        "Putine\u015fti"
    ],
    "name:nno_x_preferred":[
        "Putine\u0219ti"
    ],
    "name:nob_x_preferred":[
        "Putine\u0219ti"
    ],
    "name:pol_x_preferred":[
        "Putine\u0219ti"
    ],
    "name:por_x_preferred":[
        "Putine\u0219ti"
    ],
    "name:ron_x_preferred":[
        "Putine\u0219ti"
    ],
    "name:rus_x_preferred":[
        "\u041f\u0443\u0442\u0438\u043d\u0435\u0448\u0442\u044b"
    ],
    "name:spa_x_preferred":[
        "Putine\u0219ti"
    ],
    "name:spa_x_variant":[
        "Fr\u0103sine\u015fti"
    ],
    "name:swe_x_preferred":[
        "Putine\u0219ti"
    ],
    "name:ukr_x_preferred":[
        "\u041f\u0443\u0442\u0456\u043d\u0435\u0448\u0442\u044c"
    ],
    "name:und_x_colloquial":[
        "Putinesti"
    ],
    "name:und_x_variant":[
        "Putinesht\u2019"
    ],
    "qs:a0":"Moldova",
    "qs:a1":"*Flore\u015fti",
    "qs:a1_alt":"Floresti",
    "qs:a1r":"0",
    "qs:adm0":"Moldova",
    "qs:la_lc":"*",
    "qs:level":"locality",
    "qs:loc":"Putine\u015fti",
    "qs:loc_alt":"Putinesti",
    "qs:pop":0,
    "qs:type":"buffered point",
    "wd:wordcount":33,
    "wof:lang":[
        "unk"
    ],
    "wof:name":"Putine\u015fti",
    "wof:placetype":"locality"
},
  "geometry": {"coordinates":[28.11838,47.838226],"type":"Point"}
}