{
  "type": "Feature",
  "properties": {
    "gn:population":8250,
    "iso:country":"MD",
    "name:bul_x_preferred":[
        "\u041d\u043e\u0432\u0438 \u0410\u043d\u0435\u043d\u0438"
    ],
    "name:cat_x_preferred":[
        "Anenii Noi"
    ],
    "name:ceb_x_preferred":[
        "Anenii Noi"
    ],
    "name:deu_x_preferred":[
        "Anenii Noi"
    ],
    "name:eng_x_preferred":[
        "Novo-Aneny"
    ],
    "name:eng_x_variant":[
        "Aneni Nouy",
        "Anenii Noui",
        "Novyye Aneny",
        "Anenii Noi"
    ],
    "name:est_x_preferred":[
        "Anenii Noi"
    ],
    "name:fin_x_preferred":[
        "Anenii Noi"
    ],
    "name:fra_x_preferred":[
        "Anenii Noi"
    ],
    "name:hsb_x_preferred":[
        "Anenii Noi"
    ],
    "name:hun_x_preferred":[
        "Anenii Noi"
    ],
    "name:ind_x_preferred":[
        "Anenii Noi"
    ],
    "name:ita_x_preferred":[
        "Anenii Noi"
    ],
    "name:jpn_x_preferred":[
        "\u30a2\u30cd\u30cb\u30a4\u30fb\u30ce\u30a4"
    ],
    "name:kor_x_preferred":[
        "\uc544\ub124\ub2c8\ub178\uc774"
    ],
    "name:lit_x_preferred":[
        "Naujieji An\u0117nai"
    ],
    "name:nld_x_preferred":[
        "Anenii Noi"
    ],
    "name:pnb_x_preferred":[
        "\u0646\u0648\u0627\u06ba \u0627\u0646\u06cc\u0646\u06cc"
    ],
    "name:pol_x_preferred":[
        "Anenii Noi"
    ],
    "name:ron_x_preferred":[
        "Anenii Noi"
    ],
    "name:rus_x_preferred":[
        "\u041d\u043e\u0432\u044b\u0435 \u0410\u043d\u0435\u043d\u044b"
    ],
    "name:rus_x_variant":[
        "\u0410\u043d\u0435\u043d\u0438\u0439-\u041d\u043e\u0439"
    ],
    "name:sco_x_preferred":[
        "Anenii Noi"
    ],
    "name:slk_x_preferred":[
        "Anenii Noi"
    ],
    "name:spa_x_preferred":[
        "Anenii Noi"
    ],
    "name:sqi_x_preferred":[
        "Anenii Noi"
    ],
    "name:srp_x_preferred":[
        "\u0410\u043d\u0435\u043d\u0438\u0458 \u041d\u043e\u0458"
    ],
    "name:swe_x_preferred":[
        "Anenii Noi"
    ],
    "name:ukr_x_preferred":[
        "\u0410\u043d\u0435\u043d\u0456\u0439-\u041d\u043e\u0439"
    ],
    "name:urd_x_preferred":[
        "\u0627\u0646\u06cc\u0646\u0626\u06cc \u0646\u0648\u06cc"
    ],
    "name:zho_x_preferred":[
        "\u65b0\u963f\u5167\u5c3c"
    ],
    "qs:a0":"Moldova",
    "qs:a1":"*Anenii Noi",
    "qs:a1_alt":"Anenii Noi",
    "qs:a1r":"0",
    "qs:adm0":"Moldova",
    "qs:la_lc":"*",
    "qs:level":"locality",
    "qs:loc":"Anenii Noi",
    "qs:loc_alt":"Anenii Noi",
    "qs:pop":0,
    "qs:type":"buffered point",
    "wd:elevation":39.0,
    "wd:wordcount":202,
    "wof:lang":[
        "unk"
    ],
    "wof:name":"Anenii Noi",
    "wof:placetype":"locality",
    "wof:population":8250
},
  "geometry": {"coordinates":[29.231743,46.880818],"type":"Point"}
}