{
  "type": "Feature",
  "properties": {
    "iso:country":"MD",
    "name:arz_x_preferred":[
        "\u0627\u0628\u0627\u0643\u0644\u064a\u0627"
    ],
    "name:bul_x_preferred":[
        "\u0410\u0431\u0430\u043a\u043b\u0438\u044f"
    ],
    "name:ceb_x_preferred":[
        "Abaclia"
    ],
    "name:che_x_preferred":[
        "\u0410\u0431\u0430\u043a\u043b\u0438\u0430"
    ],
    "name:dan_x_preferred":[
        "Abaclia"
    ],
    "name:deu_x_preferred":[
        "Abaclia"
    ],
    "name:eng_x_preferred":[
        "Abaklydzhaba"
    ],
    "name:eng_x_variant":[
        "Abakliya",
        "Abaclia"
    ],
    "name:est_x_preferred":[
        "Abaclia"
    ],
    "name:eus_x_preferred":[
        "Abaclia"
    ],
    "name:fas_x_preferred":[
        "\u0622\u0628\u0627\u06a9\u0644\u06cc\u0627"
    ],
    "name:fra_x_preferred":[
        "Abaclia"
    ],
    "name:gle_x_preferred":[
        "Abaclia"
    ],
    "name:ita_x_preferred":[
        "Abaclia"
    ],
    "name:kat_x_preferred":[
        "\u10d0\u10d1\u10d0\u10d9\u10da\u10d8\u10d0"
    ],
    "name:nld_x_preferred":[
        "Abaclia"
    ],
    "name:nno_x_preferred":[
        "Abaclia"
    ],
    "name:nob_x_preferred":[
        "Abaclia"
    ],
    "name:pol_x_preferred":[
        "Abaclia"
    ],
    "name:por_x_preferred":[
        "Abaclia"
    ],
    "name:ron_x_preferred":[
        "Abaclia"
    ],
    "name:rus_x_preferred":[
        "\u0410\u0431\u0430\u043a\u043b\u0438\u044f"
    ],
    "name:spa_x_preferred":[
        "Abaclia"
    ],
    "name:swe_x_preferred":[
        "Abaclia"
    ],
    "name:tat_x_preferred":[
        "\u0410\u0431\u0430\u043a\u043b\u0438\u0430"
    ],
    "name:ukr_x_preferred":[
        "\u0410\u0431\u0430\u043a\u043b\u0456\u044f"
    ],
    "qs:a0":"Moldova",
    "qs:a1":"*Basarabeasca",
    "qs:a1_alt":"Basarabeasca",
    "qs:a1r":"0",
    "qs:adm0":"Moldova",
    "qs:la_lc":"*",
    "qs:level":"locality",
    "qs:loc":"Abaclia",
    "qs:loc_alt":"Abaclia",
    "qs:pop":0,
    "qs:type":"buffered point",
    "wd:wordcount":22,
    "wof:lang":[
        "unk"
    ],
    "wof:name":"Abaclia",
    "wof:placetype":"locality"
},
  "geometry": {"coordinates":[28.938298,46.359283],"type":"Point"}
}