{
  "type": "Feature",
  "properties": {
    "iso:country":"MD",
    "name:bul_x_preferred":[
        "\u0421\u0442\u043e\u044f\u043d\u043e\u0432\u043a\u0430"
    ],
    "name:dan_x_preferred":[
        "Stoianovca"
    ],
    "name:deu_x_preferred":[
        "Stoianovca"
    ],
    "name:eng_x_preferred":[
        "Stoyanovka"
    ],
    "name:eus_x_preferred":[
        "Stoianovca"
    ],
    "name:fra_x_preferred":[
        "Stoianovca"
    ],
    "name:ita_x_preferred":[
        "Stoianovca"
    ],
    "name:kat_x_preferred":[
        "\u10e1\u10e2\u10dd\u10d8\u10d0\u10dc\u10dd\u10d5\u10d9\u10d0"
    ],
    "name:nld_x_preferred":[
        "Stoianovca"
    ],
    "name:nno_x_preferred":[
        "Stoianovca"
    ],
    "name:nob_x_preferred":[
        "Stoianovca"
    ],
    "name:pol_x_preferred":[
        "Stoianovca"
    ],
    "name:por_x_preferred":[
        "Stoianovca"
    ],
    "name:ron_x_preferred":[
        "Stoianovca"
    ],
    "name:rus_x_preferred":[
        "\u0421\u0442\u043e\u044f\u043d\u043e\u0432\u043a\u0430"
    ],
    "name:spa_x_preferred":[
        "Stoianovca"
    ],
    "name:swe_x_preferred":[
        "Stoianovca"
    ],
    "name:ukr_x_preferred":[
        "\u0421\u0442\u043e\u044f\u043d\u0456\u0432\u043a\u0430"
    ],
    "name:und_x_colloquial":[
        "Stoinesti"
    ],
    "name:und_x_preferred":[
        "Stoianovca"
    ],
    "name:und_x_variant":[
        "Stoine\u015fti"
    ],
    "name:unk_x_variant":[
        "Stoine\u015fti"
    ],
    "qs:a0":"Moldova",
    "qs:a1":"*Cantemir",
    "qs:a1_alt":"Cantemir",
    "qs:a1r":"0",
    "qs:adm0":"Moldova",
    "qs:la_lc":"*",
    "qs:level":"locality",
    "qs:loc":"Stoianovca",
    "qs:loc_alt":"Stoianovca",
    "qs:pop":0,
    "qs:type":"buffered point",
    "wd:wordcount":38,
    "wof:lang":[
        "unk"
    ],
    "wof:name":"Stoianovca",
    "wof:placetype":"locality"
},
  "geometry": {"coordinates":[28.162936,46.255303],"type":"Point"}
}