{
  "type": "Feature",
  "properties": {
    "iso:country":"MD",
    "name:ceb_x_preferred":[
        "Hore\u0219ti"
    ],
    "name:dan_x_preferred":[
        "Hore\u0219ti"
    ],
    "name:deu_x_preferred":[
        "Hore\u0219ti"
    ],
    "name:eng_x_preferred":[
        "Goresht'"
    ],
    "name:eng_x_variant":[
        "Goreshty",
        "Hore\u0219ti"
    ],
    "name:eus_x_preferred":[
        "Hore\u0219ti"
    ],
    "name:fra_x_preferred":[
        "Hore\u0219ti"
    ],
    "name:ita_x_preferred":[
        "Hore\u0219ti"
    ],
    "name:kat_x_preferred":[
        "\u10f0\u10dd\u10e0\u10d4\u10e8\u10e2\u10d8"
    ],
    "name:nld_x_preferred":[
        "Hore\u015fti"
    ],
    "name:nno_x_preferred":[
        "Hore\u0219ti"
    ],
    "name:nob_x_preferred":[
        "Hore\u0219ti"
    ],
    "name:pol_x_preferred":[
        "Hore\u0219ti"
    ],
    "name:por_x_preferred":[
        "Hore\u0219ti"
    ],
    "name:ron_x_preferred":[
        "Hore\u0219ti"
    ],
    "name:rus_x_preferred":[
        "\u0425\u043e\u0440\u0435\u0448\u0442\u044c"
    ],
    "name:rus_x_variant":[
        "\u0413\u043e\u0440\u0435\u0448\u0442\u044b"
    ],
    "name:spa_x_preferred":[
        "Hore\u0219ti"
    ],
    "name:swe_x_preferred":[
        "Hore\u0219ti"
    ],
    "name:ukr_x_preferred":[
        "\u0413\u043e\u0440\u0435\u0448\u0442\u044c"
    ],
    "name:ukr_x_variant":[
        "\u0426\u0438\u043d\u0446\u0435\u0440\u0435\u043d\u044c"
    ],
    "name:und_x_colloquial":[
        "Horasti",
        "Horesti"
    ],
    "name:und_x_variant":[
        "Hor\u0103\u015fti"
    ],
    "qs:a0":"Moldova",
    "qs:a1":"*Ialoveni",
    "qs:a1_alt":"Ialoveni",
    "qs:a1r":"0",
    "qs:adm0":"Moldova",
    "qs:la_lc":"*",
    "qs:level":"locality",
    "qs:loc":"Hore\u015fti",
    "qs:loc_alt":"Horesti",
    "qs:pop":0,
    "qs:type":"buffered point",
    "wd:wordcount":59,
    "wof:lang":[
        "unk"
    ],
    "wof:name":"Hore\u015fti",
    "wof:placetype":"locality"
},
  "geometry": {"coordinates":[28.87048,46.823788],"type":"Point"}
}