{
  "type": "Feature",
  "properties": {
    "gn:admin1_code":"87.0",
    "gn:asciiname":"Oclanda",
    "gn:country_code":"MD",
    "gn:dem":119,
    "gn:feature_class":"P",
    "gn:feature_code":"PPL",
    "gn:name":"Oclanda",
    "gn:population":0,
    "gn:timezone":"Europe/Chisinau",
    "iso:country":"MD",
    "name:ita_x_preferred":[
        "Oclanda"
    ],
    "name:kat_x_preferred":[
        "\u10dd\u10d9\u10da\u10d0\u10dc\u10d3\u10d0"
    ],
    "name:ron_x_preferred":[
        "Oclanda"
    ],
    "name:rus_x_preferred":[
        "\u041e\u043a\u043b\u0430\u043d\u0434\u0430"
    ],
    "name:ukr_x_preferred":[
        "\u041e\u043a\u043b\u0430\u043d\u0434\u0430"
    ],
    "name:und_x_variant":[
        "Oklando",
        "Oklanda"
    ],
    "wof:name":"Oclanda",
    "wof:placetype":"locality"
},
  "geometry": {"coordinates":[28.05826,48.28925],"type":"Point"}
}