{
  "type": "Feature",
  "properties": {
    "iso:country":"MD",
    "name:ceb_x_preferred":[
        "Cu\u0219mirca"
    ],
    "name:dan_x_preferred":[
        "Cu\u0219mirca"
    ],
    "name:deu_x_preferred":[
        "Cu\u0219mirca"
    ],
    "name:eng_x_preferred":[
        "Kushmiria"
    ],
    "name:eng_x_variant":[
        "Cu\u0219mirca"
    ],
    "name:eus_x_preferred":[
        "Cu\u0219mirca"
    ],
    "name:fra_x_preferred":[
        "Cu\u0219mirca"
    ],
    "name:ita_x_preferred":[
        "Cu\u0219mirca"
    ],
    "name:ita_x_variant":[
        "Cu\u015fmirca"
    ],
    "name:kat_x_preferred":[
        "\u10d9\u10e3\u10e8\u10db\u10d8\u10e0\u10d9\u10d0"
    ],
    "name:nld_x_preferred":[
        "Cu\u015fmirca"
    ],
    "name:nno_x_preferred":[
        "Cu\u0219mirca"
    ],
    "name:nob_x_preferred":[
        "Cu\u0219mirca"
    ],
    "name:pol_x_preferred":[
        "Cu\u0219mirca"
    ],
    "name:por_x_preferred":[
        "Cu\u0219mirca"
    ],
    "name:ron_x_preferred":[
        "Cu\u0219mirca"
    ],
    "name:rus_x_preferred":[
        "\u041a\u0443\u0448\u043c\u0438\u0440\u043a\u0430"
    ],
    "name:spa_x_preferred":[
        "Cu\u0219mirca"
    ],
    "name:swe_x_preferred":[
        "Cu\u0219mirca"
    ],
    "name:ukr_x_preferred":[
        "\u041a\u0443\u0448\u043c\u0456\u0440\u043a\u0430"
    ],
    "name:ukr_x_variant":[
        "\u041a\u043e\u0448\u0435\u0440\u043d\u0456\u0446\u0430"
    ],
    "name:und_x_colloquial":[
        "Cusmirca"
    ],
    "name:und_x_preferred":[
        "Cu\u015fmirca"
    ],
    "name:unk_x_variant":[
        "Kushmiria"
    ],
    "qs:a0":"Moldova",
    "qs:a1":"*Sold\u0103ne\u015fti",
    "qs:a1_alt":"Soldanesti",
    "qs:a1r":"0",
    "qs:adm0":"Moldova",
    "qs:la_lc":"*",
    "qs:level":"locality",
    "qs:loc":"Cu\u015fmirca",
    "qs:loc_alt":"Cusmirca",
    "qs:pop":0,
    "qs:type":"buffered point",
    "wd:wordcount":57,
    "wof:lang":[
        "unk"
    ],
    "wof:name":"Cu\u015fmirca",
    "wof:placetype":"locality"
},
  "geometry": {"coordinates":[28.705019,47.905346],"type":"Point"}
}