{
  "type": "Feature",
  "properties": {
    "gn:admin1_code":"77.0",
    "gn:asciiname":"Kokocheny",
    "gn:country_code":"MD",
    "gn:dem":50,
    "gn:feature_class":"P",
    "gn:feature_code":"PPL",
    "gn:name":"Kokocheny",
    "gn:population":0,
    "gn:timezone":"Europe/Chisinau",
    "iso:country":"MD",
    "wof:name":"Kokocheny",
    "wof:placetype":"locality"
},
  "geometry": {"coordinates":[28.30667,46.66972],"type":"Point"}
}