{
  "type": "Feature",
  "properties": {
    "gn:admin1_code":"58.0",
    "gn:asciiname":"Zurka",
    "gn:country_code":"MD",
    "gn:dem":139,
    "gn:feature_class":"P",
    "gn:feature_code":"PPL",
    "gn:name":"\u017burka",
    "gn:population":0,
    "gn:timezone":"Europe/Chisinau",
    "iso:country":"MD",
    "name:rus_x_preferred":[
        "\u0416\u0443\u0440\u043a\u0430"
    ],
    "name:und_x_variant":[
        "Zhurka",
        "\u017burka"
    ],
    "wof:name":"Zurka",
    "wof:placetype":"locality"
},
  "geometry": {"coordinates":[29.11267,47.49228],"type":"Point"}
}