{
  "type": "Feature",
  "properties": {
    "gn:admin1_code":"58.0",
    "gn:asciiname":"Crasnoe",
    "gn:country_code":"MD",
    "gn:dem":109,
    "gn:feature_class":"P",
    "gn:feature_code":"PPL",
    "gn:name":"Crasnoe",
    "gn:population":0,
    "gn:timezone":"Europe/Chisinau",
    "iso:country":"MD",
    "name:rus_x_preferred":[
        "\u041a\u0440\u0430\u0441\u043d\u043e\u0435"
    ],
    "name:und_x_variant":[
        "Krasnoye",
        "Crasnoe"
    ],
    "wof:name":"Crasnoe",
    "wof:placetype":"locality"
},
  "geometry": {"coordinates":[29.36139,47.18153],"type":"Point"}
}