{
  "type": "Feature",
  "properties": {
    "iso:country":"MD",
    "name:che_x_preferred":[
        "\u0417\u044b\u0440\u043d\u0435\u0448\u0442\u044c"
    ],
    "name:eng_x_preferred":[
        "Zerneshty"
    ],
    "name:eng_x_variant":[
        "Zerneshti",
        "Zirneshty",
        "Zyrneshty",
        "Z\u00eerne\u0219ti"
    ],
    "name:gle_x_preferred":[
        "Z\u00eerne\u0219ti"
    ],
    "name:ita_x_preferred":[
        "Z\u00eerne\u0219ti"
    ],
    "name:kat_x_preferred":[
        "\u10d6\u10d8\u10e0\u10dc\u10d4\u10e8\u10e2\u10d8"
    ],
    "name:nld_x_preferred":[
        "Z\u00eerne\u0219ti"
    ],
    "name:ron_x_preferred":[
        "Z\u00eerne\u0219ti"
    ],
    "name:rus_x_preferred":[
        "\u0417\u044b\u0440\u043d\u0435\u0448\u0442\u044c"
    ],
    "name:rus_x_variant":[
        "\u0417\u044b\u0440\u043d\u0435\u0448\u0442\u044b"
    ],
    "name:spa_x_preferred":[
        "Z\u00eerne\u015fti"
    ],
    "name:ukr_x_preferred":[
        "\u0417\u0438\u0440\u043d\u0435\u0448\u0442\u0438"
    ],
    "name:und_x_colloquial":[
        "Zarnesti",
        "Zirnesti"
    ],
    "name:und_x_variant":[
        "Z\u00eerne\u015fti",
        "Z\u0103rne\u015fti"
    ],
    "qs:a0":"Moldova",
    "qs:a1":"*Cahul",
    "qs:a1_alt":"Cahul",
    "qs:a1r":"0",
    "qs:adm0":"Moldova",
    "qs:la_lc":"*",
    "qs:level":"locality",
    "qs:loc":"Z\u00eerne\u015fti",
    "qs:loc_alt":"Zirnesti",
    "qs:pop":0,
    "qs:type":"buffered point",
    "wd:wordcount":95,
    "wof:lang":[
        "unk"
    ],
    "wof:name":"Z\u00eerne\u015fti",
    "wof:placetype":"locality"
},
  "geometry": {"coordinates":[28.168503,46.007542],"type":"Point"}
}