{
  "type": "Feature",
  "properties": {
    "gn:admin1_code":"91.0",
    "gn:asciiname":"Chersac",
    "gn:country_code":"MD",
    "gn:dem":98,
    "gn:feature_class":"P",
    "gn:feature_code":"PPL",
    "gn:name":"Chersac",
    "gn:population":0,
    "gn:timezone":"Europe/Chisinau",
    "iso:country":"MD",
    "name:rus_x_preferred":[
        "\u041a\u0435\u0440\u0441\u0430\u0440\u043a\u0430"
    ],
    "name:und_x_variant":[
        "Kersarka",
        "Chersac"
    ],
    "wof:name":"Chersac",
    "wof:placetype":"locality"
},
  "geometry": {"coordinates":[28.58272,47.63703],"type":"Point"}
}