{
  "type": "Feature",
  "properties": {
    "gn:gn_country":"MD",
    "gn:gn_fcode":"PPL",
    "gn:gn_pop":2365,
    "gn:population":2365,
    "iso:country":"MD",
    "name:ceb_x_preferred":[
        "Saharna"
    ],
    "name:dan_x_preferred":[
        "Saharna"
    ],
    "name:deu_x_preferred":[
        "Saharna"
    ],
    "name:eng_x_preferred":[
        "Saharna"
    ],
    "name:eus_x_preferred":[
        "Saharna"
    ],
    "name:fra_x_preferred":[
        "Saharna"
    ],
    "name:ita_x_preferred":[
        "Saharna"
    ],
    "name:kat_x_preferred":[
        "\u10e1\u10d0\u10f0\u10d0\u10e0\u10dc\u10d0"
    ],
    "name:nld_x_preferred":[
        "Saharna"
    ],
    "name:nno_x_preferred":[
        "Saharna"
    ],
    "name:nob_x_preferred":[
        "Saharna"
    ],
    "name:pol_x_preferred":[
        "Saharna"
    ],
    "name:por_x_preferred":[
        "Saharna"
    ],
    "name:ron_x_preferred":[
        "Saharna"
    ],
    "name:rus_x_preferred":[
        "\u0421\u0430\u0445\u0430\u0440\u043d\u0430"
    ],
    "name:spa_x_preferred":[
        "Saharna"
    ],
    "name:swe_x_preferred":[
        "Saharna"
    ],
    "name:ukr_x_preferred":[
        "\u0421\u0430\u0445\u0430\u0440\u043d\u0430"
    ],
    "name:unk_x_variant":[
        "Sakharna"
    ],
    "name:vol_x_preferred":[
        "Greci"
    ],
    "qs_pg:aaroncc":"MD",
    "qs_pg:gn_country":"MD",
    "qs_pg:gn_fcode":"PPL",
    "qs_pg:gn_pop":2365,
    "qs_pg:name":"Saharna",
    "qs_pg:name_adm0":"Moldova",
    "qs_pg:name_adm1":"Rezina",
    "qs_pg:photos_9k":1,
    "qs_pg:photos_9r":2,
    "qs_pg:photos_all":30,
    "qs_pg:photos_sr":0,
    "qs_pg:pop_sr":4,
    "qs_pg:qs_pg_placetype":"locality",
    "qs_pg:qs_pg_placetype_gp":"Town",
    "qs_pg:woe_adm0":23424885,
    "woe:adm0_id":23424885,
    "woe:name_adm0":"Moldova",
    "woe:name_adm1":"Rezina",
    "woe:placetype":"Town",
    "wof:name":"Saharna",
    "wof:placetype":"locality",
    "wof:population":2365
},
  "geometry": {"coordinates":[28.97028,47.69361],"type":"Point"}
}