{
  "type": "Feature",
  "properties": {
    "gn:admin1_code":"64.0",
    "gn:asciiname":"Viduca",
    "gn:country_code":"MD",
    "gn:dem":12,
    "gn:feature_class":"P",
    "gn:feature_code":"PPL",
    "gn:name":"Viduca",
    "gn:population":0,
    "gn:timezone":"Europe/Chisinau",
    "iso:country":"MD",
    "wof:name":"Viduca",
    "wof:placetype":"locality"
},
  "geometry": {"coordinates":[28.17333,45.78472],"type":"Point"}
}