{
  "type": "Feature",
  "properties": {
    "gn:admin1_code":"77.0",
    "gn:asciiname":"Talaiestii-Vechi",
    "gn:cc2":"MD",
    "gn:country_code":"MD",
    "gn:dem":89,
    "gn:feature_class":"P",
    "gn:feature_code":"PPL",
    "gn:name":"T\u0103l\u0103ie\u015ftii-Vechi",
    "gn:population":0,
    "gn:timezone":"Europe/Chisinau",
    "iso:country":"MD",
    "name:und_x_variant":[
        "Novyye Talayeshty"
    ],
    "wof:name":"Talaiestii-Vechi",
    "wof:placetype":"locality"
},
  "geometry": {"coordinates":[28.28139,46.81417],"type":"Point"}
}