{
  "type": "Feature",
  "properties": {
    "iso:country":"MD",
    "name:ceb_x_preferred":[
        "Lunga"
    ],
    "name:dan_x_preferred":[
        "Lunga"
    ],
    "name:deu_x_preferred":[
        "Lunga"
    ],
    "name:eng_x_preferred":[
        "Lunga"
    ],
    "name:eus_x_preferred":[
        "Lunga"
    ],
    "name:fas_x_preferred":[
        "\u0644\u0648\u0646\u06af\u0627"
    ],
    "name:fra_x_preferred":[
        "Lunga"
    ],
    "name:gle_x_preferred":[
        "Lunga"
    ],
    "name:ita_x_preferred":[
        "Lunga"
    ],
    "name:nno_x_preferred":[
        "Lunga"
    ],
    "name:nob_x_preferred":[
        "Lunga"
    ],
    "name:pol_x_preferred":[
        "Lunga"
    ],
    "name:por_x_preferred":[
        "Lunga"
    ],
    "name:ron_x_preferred":[
        "Lunga"
    ],
    "name:ron_x_variant":[
        "M\u0103l\u0103ie\u015fti"
    ],
    "name:rus_x_preferred":[
        "\u041b\u0443\u043d\u0433\u0430"
    ],
    "name:spa_x_preferred":[
        "Lunga"
    ],
    "name:swe_x_preferred":[
        "Lunga"
    ],
    "name:tur_x_preferred":[
        "Lunga"
    ],
    "name:ukr_x_preferred":[
        "\u041b\u0443\u043d\u0433\u0430"
    ],
    "name:und_x_variant":[
        "Lunca"
    ],
    "qs:a0":"Moldova",
    "qs:a1":"*UAT din St\u00eenga Nistrului",
    "qs:a1_alt":"Unitatile administrativ-teritoriale din stinga Nistrului",
    "qs:a1r":"0",
    "qs:adm0":"Moldova",
    "qs:la_lc":"*",
    "qs:level":"locality",
    "qs:loc":"Lunga",
    "qs:loc_alt":"Lunga",
    "qs:pop":0,
    "qs:type":"buffered point",
    "wd:wordcount":150,
    "wof:name":"Lunga",
    "wof:placetype":"locality"
},
  "geometry": {"coordinates":[29.170756,47.256047],"type":"Point"}
}