{
  "type": "Feature",
  "properties": {
    "gn:admin1_code":"59.0",
    "gn:asciiname":"Botnaresti",
    "gn:country_code":"MD",
    "gn:dem":63,
    "gn:feature_class":"P",
    "gn:feature_code":"PPL",
    "gn:name":"Botn\u0103re\u015fti",
    "gn:population":0,
    "gn:timezone":"Europe/Chisinau",
    "iso:country":"MD",
    "name:rus_x_preferred":[
        "\u0411\u043e\u0442\u043d\u0430\u0440\u0435\u0448\u0442\u044b"
    ],
    "name:und_x_variant":[
        "Botn\u0103re\u015ftii Vechi",
        "Botnareshty",
        "Botnaresht\u2019 Veke",
        "Botn\u0103re\u015fti"
    ],
    "wof:name":"Botnaresti",
    "wof:placetype":"locality"
},
  "geometry": {"coordinates":[29.15988,46.93004000000001],"type":"Point"}
}