{
  "type": "Feature",
  "properties": {
    "iso:country":"MD",
    "name:ceb_x_preferred":[
        "V\u0103ratic"
    ],
    "name:dan_x_preferred":[
        "V\u0103ratic"
    ],
    "name:deu_x_preferred":[
        "V\u0103ratic"
    ],
    "name:eng_x_preferred":[
        "V\u0103ratic"
    ],
    "name:eus_x_preferred":[
        "V\u0103ratic"
    ],
    "name:fra_x_preferred":[
        "V\u0103ratic"
    ],
    "name:ita_x_preferred":[
        "V\u0103ratic"
    ],
    "name:kat_x_preferred":[
        "\u10d5\u10d4\u10e0\u10d0\u10e2\u10d8\u10d9\u10d8"
    ],
    "name:nld_x_preferred":[
        "V\u0103ratic"
    ],
    "name:nno_x_preferred":[
        "V\u0103ratic"
    ],
    "name:nob_x_preferred":[
        "V\u0103ratic"
    ],
    "name:pol_x_preferred":[
        "V\u0103ratic"
    ],
    "name:por_x_preferred":[
        "V\u0103ratic"
    ],
    "name:ron_x_preferred":[
        "V\u0103ratic"
    ],
    "name:rus_x_preferred":[
        "\u0412\u044d\u0440\u0430\u0442\u0438\u043a"
    ],
    "name:rus_x_variant":[
        "\u0412\u0430\u0440\u0430\u0442\u0438\u043a"
    ],
    "name:spa_x_preferred":[
        "V\u0103ratic"
    ],
    "name:swe_x_preferred":[
        "V\u0103ratic"
    ],
    "name:ukr_x_preferred":[
        "\u0412\u0435\u0440\u0430\u0442\u0456\u043a"
    ],
    "name:ukr_x_variant":[
        "\u0420\u0435\u0434\u0435\u043d\u044c"
    ],
    "name:und_x_variant":[
        "Veratek"
    ],
    "qs:a0":"Moldova",
    "qs:a1":"*R\u00ee\u015fcani",
    "qs:a1_alt":"Riscani",
    "qs:a1r":"0",
    "qs:adm0":"Moldova",
    "qs:la_lc":"*",
    "qs:level":"locality",
    "qs:loc":"V\u0103ratic",
    "qs:loc_alt":"Varatic",
    "qs:pop":0,
    "qs:type":"buffered point",
    "wd:wordcount":18,
    "wof:name":"V\u0103ratic",
    "wof:placetype":"locality"
},
  "geometry": {"coordinates":[27.259964,47.916313],"type":"Point"}
}