{
  "type": "Feature",
  "properties": {
    "gn:admin1_code":"77.0",
    "gn:asciiname":"Dubovca",
    "gn:country_code":"MD",
    "gn:dem":146,
    "gn:feature_class":"P",
    "gn:feature_code":"PPL",
    "gn:name":"Dubovca",
    "gn:population":0,
    "gn:timezone":"Europe/Chisinau",
    "iso:country":"MD",
    "name:rus_x_preferred":[
        "\u0414\u0443\u0431\u043e\u0432\u043a\u0430"
    ],
    "name:und_x_variant":[
        "Dubovka",
        "Dubovca"
    ],
    "wof:name":"Dubovca",
    "wof:placetype":"locality"
},
  "geometry": {"coordinates":[28.60741,46.74914],"type":"Point"}
}