{
  "type": "Feature",
  "properties": {
    "gn:admin1_code":"91.0",
    "gn:asciiname":"Dubau",
    "gn:country_code":"MD",
    "gn:dem":79,
    "gn:feature_class":"P",
    "gn:feature_code":"PPL",
    "gn:name":"Dub\u0103u",
    "gn:population":0,
    "gn:timezone":"Europe/Chisinau",
    "iso:country":"MD",
    "name:ita_x_preferred":[
        "Dub\u0103u"
    ],
    "name:ron_x_preferred":[
        "Comuna Dub\u0103u"
    ],
    "name:rus_x_preferred":[
        "\u0414\u0443\u0431\u043e\u0432\u043e"
    ],
    "name:und_x_variant":[
        "Dubova",
        "Dubovo",
        "Dub\u0103u"
    ],
    "wof:name":"Dubau",
    "wof:placetype":"locality"
},
  "geometry": {"coordinates":[29.28036,47.4302],"type":"Point"}
}