{
  "type": "Feature",
  "properties": {
    "iso:country":"MD",
    "name:eng_x_preferred":[
        "Vaneshty"
    ],
    "name:eng_x_variant":[
        "Baneshti",
        "Baneshty"
    ],
    "name:ita_x_preferred":[
        "B\u0103ne\u0219ti"
    ],
    "name:ron_x_preferred":[
        "B\u0103ne\u0219ti"
    ],
    "name:rus_x_preferred":[
        "\u0411\u044d\u043d\u0435\u0448\u0442\u044c"
    ],
    "name:rus_x_variant":[
        "\u0411\u0430\u043d\u0435\u0448\u0442\u044b"
    ],
    "name:ukr_x_preferred":[
        "\u0411\u0435\u043d\u0435\u0448\u0442\u044c"
    ],
    "name:und_x_colloquial":[
        "Banesti"
    ],
    "name:und_x_preferred":[
        "B\u0103ne\u015fti"
    ],
    "name:unk_x_variant":[
        "Vaneshty"
    ],
    "qs:a0":"Moldova",
    "qs:a1":"*Telene\u015fti",
    "qs:a1_alt":"Telenesti",
    "qs:a1r":"0",
    "qs:adm0":"Moldova",
    "qs:la_lc":"*",
    "qs:level":"locality",
    "qs:loc":"B\u0103ne\u015fti",
    "qs:loc_alt":"Banesti",
    "qs:pop":0,
    "qs:type":"buffered point",
    "wd:wordcount":51,
    "wof:lang":[
        "unk"
    ],
    "wof:name":"B\u0103ne\u015fti",
    "wof:placetype":"locality"
},
  "geometry": {"coordinates":[28.383302,47.570393],"type":"Point"}
}