{
  "type": "Feature",
  "properties": {
    "iso:country":"MD",
    "name:eng_x_preferred":[
        "Moscovei"
    ],
    "name:ita_x_preferred":[
        "Moscovei"
    ],
    "name:kat_x_preferred":[
        "\u10db\u10dd\u10e1\u10d9\u10dd\u10d5\u10d4\u10d8"
    ],
    "name:nld_x_preferred":[
        "Moscovei"
    ],
    "name:ron_x_preferred":[
        "Moscovei"
    ],
    "name:rus_x_preferred":[
        "\u041c\u043e\u0441\u043a\u043e\u0432\u0435\u0439"
    ],
    "name:ukr_x_preferred":[
        "\u041c\u043e\u0441\u043a\u043e\u0432\u0435\u0439"
    ],
    "name:und_x_variant":[
        "Moskovey-Chikur",
        "Moskovey"
    ],
    "qs:a0":"Moldova",
    "qs:a1":"*Cahul",
    "qs:a1_alt":"Cahul",
    "qs:a1r":"0",
    "qs:adm0":"Moldova",
    "qs:la_lc":"*",
    "qs:level":"locality",
    "qs:loc":"Moscovei",
    "qs:loc_alt":"Moscovei",
    "qs:pop":0,
    "qs:type":"buffered point",
    "wd:wordcount":95,
    "wof:lang":[
        "unk"
    ],
    "wof:name":"Moscovei",
    "wof:placetype":"locality"
},
  "geometry": {"coordinates":[28.373505,45.913845],"type":"Point"}
}