{
  "type": "Feature",
  "properties": {
    "iso:country":"MD",
    "name:eng_x_preferred":[
        "Syrkovo"
    ],
    "name:eng_x_variant":[
        "Syrkova"
    ],
    "name:ita_x_preferred":[
        "S\u00eercova"
    ],
    "name:ron_x_preferred":[
        "S\u00eercova"
    ],
    "name:rus_x_preferred":[
        "\u0421\u044b\u0440\u043a\u043e\u0432\u043e"
    ],
    "name:ukr_x_preferred":[
        "\u0421\u0438\u0440\u043a\u043e\u0432\u0430"
    ],
    "name:und_x_colloquial":[
        "Sarcova",
        "Sircova"
    ],
    "name:und_x_preferred":[
        "S\u00eercova"
    ],
    "name:und_x_variant":[
        "S\u00e2rcova"
    ],
    "name:unk_x_variant":[
        "Syrkovo"
    ],
    "qs:a0":"Moldova",
    "qs:a1":"*Rezina",
    "qs:a1_alt":"Rezina",
    "qs:a1r":"0",
    "qs:adm0":"Moldova",
    "qs:la_lc":"*",
    "qs:level":"locality",
    "qs:loc":"S\u00eercova",
    "qs:loc_alt":"Sircova",
    "qs:pop":0,
    "qs:type":"buffered point",
    "wd:wordcount":19,
    "wof:lang":[
        "unk"
    ],
    "wof:name":"S\u00eercova",
    "wof:placetype":"locality"
},
  "geometry": {"coordinates":[28.786518,47.738827],"type":"Point"}
}