{
  "type": "Feature",
  "properties": {
    "iso:country":"MD",
    "name:baq_x_preferred":[
        "Boghiceni"
    ],
    "name:dan_x_preferred":[
        "Boghiceni"
    ],
    "name:dut_x_preferred":[
        "Boghiceni"
    ],
    "name:eng_x_preferred":[
        "Bogicheny"
    ],
    "name:eng_x_variant":[
        "Bogichany",
        "Bogichen'",
        "Boghiceni"
    ],
    "name:fre_x_preferred":[
        "Boghiceni"
    ],
    "name:geo_x_preferred":[
        "\u10d1\u10dd\u10d2\u10d8\u10e9\u10d4\u10dc\u10d8"
    ],
    "name:ger_x_preferred":[
        "Boghiceni"
    ],
    "name:ita_x_preferred":[
        "Boghiceni"
    ],
    "name:nno_x_preferred":[
        "Boghiceni"
    ],
    "name:nob_x_preferred":[
        "Boghiceni"
    ],
    "name:pol_x_preferred":[
        "Boghiceni"
    ],
    "name:por_x_preferred":[
        "Boghiceni"
    ],
    "name:ron_x_preferred":[
        "Boghiceni"
    ],
    "name:rum_x_preferred":[
        "Boghiceni"
    ],
    "name:rus_x_preferred":[
        "\u0411\u043e\u0433\u0438\u0447\u0435\u043d\u044b"
    ],
    "name:spa_x_preferred":[
        "Boghiceni"
    ],
    "name:swe_x_preferred":[
        "Boghiceni"
    ],
    "name:ukr_x_preferred":[
        "\u0411\u043e\u0433\u0456\u0447\u0435\u043d\u044c"
    ],
    "name:und_x_preferred":[
        "Boghiceni"
    ],
    "name:unk_x_variant":[
        "Bogichany"
    ],
    "qs:a0":"Moldova",
    "qs:a1":"*H\u00eence\u015fti",
    "qs:a1_alt":"Hincesti",
    "qs:a1r":"0",
    "qs:adm0":"Moldova",
    "qs:la_lc":"*",
    "qs:level":"locality",
    "qs:loc":"Boghiceni",
    "qs:loc_alt":"Boghiceni",
    "qs:pop":0,
    "qs:type":"buffered point",
    "wd:wordcount":57,
    "wof:lang":[
        "unk"
    ],
    "wof:name":"Boghiceni",
    "wof:placetype":"locality"
},
  "geometry": {"coordinates":[28.324511,46.946926],"type":"Point"}
}