{
  "type": "Feature",
  "properties": {
    "iso:country":"MD",
    "name:ceb_x_preferred":[
        "Pohoarna"
    ],
    "name:dan_x_preferred":[
        "Pohoarna"
    ],
    "name:deu_x_preferred":[
        "Pohoarna"
    ],
    "name:eng_x_preferred":[
        "Pogoarna"
    ],
    "name:eng_x_variant":[
        "Pogorna",
        "Pohoarna"
    ],
    "name:eus_x_preferred":[
        "Pohoarna"
    ],
    "name:fra_x_preferred":[
        "Pohoarna"
    ],
    "name:ita_x_preferred":[
        "Pohoarna"
    ],
    "name:kat_x_preferred":[
        "\u10de\u10dd\u10f0\u10dd\u10d0\u10e0\u10dc\u10d0"
    ],
    "name:nld_x_preferred":[
        "Pohoarna"
    ],
    "name:nno_x_preferred":[
        "Pohoarna"
    ],
    "name:nob_x_preferred":[
        "Pohoarna"
    ],
    "name:pol_x_preferred":[
        "Pohoarna"
    ],
    "name:por_x_preferred":[
        "Pohoarna"
    ],
    "name:ron_x_preferred":[
        "Pohoarna"
    ],
    "name:rus_x_preferred":[
        "\u041f\u043e\u0433\u043e\u0440\u043d\u0430"
    ],
    "name:spa_x_preferred":[
        "Pohoarna"
    ],
    "name:swe_x_preferred":[
        "Pohoarna"
    ],
    "name:ukr_x_preferred":[
        "\u041f\u043e\u0433\u043e\u0430\u0440\u043d\u0430"
    ],
    "name:ukr_x_variant":[
        "\u041a\u0456\u043f\u0435\u0448\u043a\u0430"
    ],
    "name:und_x_preferred":[
        "Pohoarna"
    ],
    "name:unk_x_variant":[
        "Pogorna"
    ],
    "qs:a0":"Moldova",
    "qs:a1":"*Sold\u0103ne\u015fti",
    "qs:a1_alt":"Soldanesti",
    "qs:a1r":"0",
    "qs:adm0":"Moldova",
    "qs:la_lc":"*",
    "qs:level":"locality",
    "qs:loc":"Pohoarna",
    "qs:loc_alt":"Pohoarna",
    "qs:pop":0,
    "qs:type":"buffered point",
    "wd:wordcount":57,
    "wof:lang":[
        "unk"
    ],
    "wof:name":"Pohoarna",
    "wof:placetype":"locality"
},
  "geometry": {"coordinates":[28.494599,47.833393],"type":"Point"}
}