{
  "type": "Feature",
  "properties": {
    "iso:country":"MD",
    "name:ceb_x_preferred":[
        "Dr\u0103gu\u0219eni"
    ],
    "name:deu_x_preferred":[
        "Dr\u0103gu\u0219eni"
    ],
    "name:eng_x_preferred":[
        "Dr\u0103gu\u015feni"
    ],
    "name:eus_x_preferred":[
        "Dr\u0103gu\u0219eni"
    ],
    "name:fra_x_preferred":[
        "Dr\u0103gu\u015feni"
    ],
    "name:hun_x_preferred":[
        "Dr\u0103gu\u0219eni"
    ],
    "name:ita_x_preferred":[
        "Dr\u0103gu\u0219eni"
    ],
    "name:nds_x_preferred":[
        "Dr\u0103gu\u0219eni"
    ],
    "name:nld_x_preferred":[
        "Dr\u0103gu\u0219eni"
    ],
    "name:pol_x_preferred":[
        "Dr\u0103gu\u0219eni"
    ],
    "name:ron_x_preferred":[
        "Dr\u0103gu\u0219eni"
    ],
    "name:rus_x_preferred":[
        "\u0414\u0440\u044d\u0433\u0443\u0448\u0435\u043d\u044c"
    ],
    "name:rus_x_variant":[
        "\u0414\u0440\u0430\u0433\u0443\u0448\u0435\u043d\u044b"
    ],
    "name:srp_x_preferred":[
        "\u0414\u0440\u0430\u0433\u0443\u0448\u0435\u043d\u0438"
    ],
    "name:ukr_x_preferred":[
        "\u0414\u0440\u0435\u0433\u0443\u0448\u0435\u043d\u044c"
    ],
    "name:und_x_variant":[
        "Beleshty"
    ],
    "name:vol_x_preferred":[
        "Dr\u0103gu\u015feni"
    ],
    "qs:a0":"Moldova",
    "qs:a1":"*Str\u0103\u015feni",
    "qs:a1_alt":"Straseni",
    "qs:a1r":"0",
    "qs:adm0":"Moldova",
    "qs:la_lc":"*",
    "qs:level":"locality",
    "qs:loc":"Dr\u0103gu\u015feni",
    "qs:loc_alt":"Draguseni",
    "qs:pop":0,
    "qs:type":"buffered point",
    "wd:wordcount":59,
    "wof:name":"Dr\u0103gu\u015feni",
    "wof:placetype":"locality"
},
  "geometry": {"coordinates":[28.665907,47.21579],"type":"Point"}
}