{
  "type": "Feature",
  "properties": {
    "gn:admin1_code":"68.0",
    "gn:asciiname":"Dimitrovca",
    "gn:country_code":"MD",
    "gn:dem":127,
    "gn:feature_class":"P",
    "gn:feature_code":"PPL",
    "gn:name":"Dimitrovca",
    "gn:population":0,
    "gn:timezone":"Europe/Chisinau",
    "iso:country":"MD",
    "name:rus_x_preferred":[
        "\u0414\u0438\u043c\u0438\u0442\u0440\u043e\u0432\u043a\u0430"
    ],
    "name:und_x_variant":[
        "Dimitrovka",
        "Dimitrovca"
    ],
    "wof:name":"Dimitrovca",
    "wof:placetype":"locality"
},
  "geometry": {"coordinates":[28.71691,46.48539],"type":"Point"}
}