{
  "type": "Feature",
  "properties": {
    "iso:country":"MD",
    "name:rus_x_preferred":[
        "\u0414\u0440\u0430\u0433\u0443\u0448\u0435\u043d\u044b"
    ],
    "name:unk_x_variant":[
        "Staryye Dragushany"
    ],
    "qs:a0":"Moldova",
    "qs:a1":"*H\u00eence\u015fti",
    "qs:a1_alt":"Hincesti",
    "qs:a1r":"0",
    "qs:adm0":"Moldova",
    "qs:la_lc":"*",
    "qs:level":"locality",
    "qs:loc":"Dr\u0103gu\u015feni",
    "qs:loc_alt":"Draguseni",
    "qs:pop":0,
    "qs:type":"buffered point",
    "wd:wordcount":59,
    "wof:name":"Dr\u0103gu\u015feni",
    "wof:placetype":"locality"
},
  "geometry": {"coordinates":[28.455784,46.976737],"type":"Point"}
}