{
  "type": "Feature",
  "properties": {
    "gn:admin1_code":"91.0",
    "gn:asciiname":"Sevcenco",
    "gn:country_code":"MD",
    "gn:dem":75,
    "gn:feature_class":"P",
    "gn:feature_code":"PPL",
    "gn:name":"\u015eevcenco",
    "gn:population":0,
    "gn:timezone":"Europe/Chisinau",
    "iso:country":"MD",
    "name:ron_x_preferred":[
        "\u015eevcenco"
    ],
    "name:rus_x_preferred":[
        "\u0428\u0435\u0432\u0447\u0435\u043d\u043a\u043e"
    ],
    "name:und_x_variant":[
        "Pos\u00eblok Shevchenko",
        "Shevchenovka",
        "Shevchenko"
    ],
    "wof:name":"Sevcenco",
    "wof:placetype":"locality"
},
  "geometry": {"coordinates":[29.18359,47.58786],"type":"Point"}
}