{
  "type": "Feature",
  "properties": {
    "gn:admin1_code":"59.0",
    "gn:asciiname":"Mirnoe",
    "gn:country_code":"MD",
    "gn:dem":72,
    "gn:feature_class":"P",
    "gn:feature_code":"PPL",
    "gn:name":"Mirnoe",
    "gn:population":0,
    "gn:timezone":"Europe/Chisinau",
    "iso:country":"MD",
    "name:deu_x_preferred":[
        "Myrne"
    ],
    "name:hye_x_preferred":[
        "\u0544\u056b\u0580\u0576\u0578\u0565"
    ],
    "name:kaz_x_preferred":[
        "\u041c\u0438\u0440\u043d\u043e\u0435"
    ],
    "name:ron_x_preferred":[
        "Mirnoe"
    ],
    "name:rus_x_preferred":[
        "\u041c\u0438\u0440\u043d\u043e\u0435"
    ],
    "name:slk_x_preferred":[
        "Myrne"
    ],
    "name:ukr_x_preferred":[
        "\u041c\u0438\u0440\u043d\u0435"
    ],
    "name:und_x_variant":[
        "Dunduc",
        "Mirnoye",
        "Dunduk"
    ],
    "wof:name":"Mirnoe",
    "wof:placetype":"locality"
},
  "geometry": {"coordinates":[29.22688,46.80283],"type":"Point"}
}