{
  "type": "Feature",
  "properties": {
    "gn:admin1_code":"75.0",
    "gn:asciiname":"Mihailovca",
    "gn:country_code":"MD",
    "gn:dem":124,
    "gn:feature_class":"P",
    "gn:feature_code":"PPL",
    "gn:name":"Mihailovca",
    "gn:population":0,
    "gn:timezone":"Europe/Chisinau",
    "iso:country":"MD",
    "name:ita_x_preferred":[
        "Mihailovca"
    ],
    "name:kat_x_preferred":[
        "\u10db\u10d8\u10f0\u10d0\u10d8\u10da\u10dd\u10d5\u10d9\u10d0"
    ],
    "name:ron_x_preferred":[
        "Mihailovca"
    ],
    "name:rus_x_preferred":[
        "\u041c\u0438\u0445\u0430\u0439\u043b\u043e\u0432\u043a\u0430"
    ],
    "name:und_x_variant":[
        "Mihai Bravul",
        "Mikhaylovka"
    ],
    "wof:name":"Mihailovca",
    "wof:placetype":"locality"
},
  "geometry": {"coordinates":[28.25458,47.79882],"type":"Point"}
}