{
  "type": "Feature",
  "properties": {
    "gn:admin1_code":"85.0",
    "gn:asciiname":"Taura Veche",
    "gn:country_code":"MD",
    "gn:dem":121,
    "gn:feature_class":"P",
    "gn:feature_code":"PPL",
    "gn:name":"T\u0103ura Veche",
    "gn:population":0,
    "gn:timezone":"Europe/Chisinau",
    "iso:country":"MD",
    "name:rus_x_preferred":[
        "\u0421\u0442\u0430\u0440\u0430\u044f \u0422\u0435\u0443\u0440\u0430"
    ],
    "name:und_x_variant":[
        "Teura-Vek\u2019",
        "Teura-Veke",
        "Staraya Teura",
        "T\u0103ura Veche"
    ],
    "wof:name":"Taura Veche",
    "wof:placetype":"locality"
},
  "geometry": {"coordinates":[27.951,47.53889],"type":"Point"}
}