{
  "type": "Feature",
  "properties": {
    "gn:admin1_code":"58.0",
    "gn:asciiname":"Stroiesti",
    "gn:country_code":"MD",
    "gn:dem":47,
    "gn:feature_class":"P",
    "gn:feature_code":"PPL",
    "gn:name":"Stroie\u015fti",
    "gn:population":0,
    "gn:timezone":"Europe/Chisinau",
    "iso:country":"MD",
    "name:ita_x_preferred":[
        "Stroie\u0219ti"
    ],
    "name:pol_x_preferred":[
        "Stroi\u0144ce"
    ],
    "name:ron_x_preferred":[
        "Stroie\u0219ti"
    ],
    "name:rus_x_preferred":[
        "\u0421\u0442\u0440\u043e\u0435\u043d\u0446\u044b"
    ],
    "name:ukr_x_preferred":[
        "\u0421\u0442\u0440\u043e\u0457\u043d\u0446\u0456"
    ],
    "name:und_x_variant":[
        "Strointsy",
        "Strointsi",
        "Stroyentsy",
        "Stroie\u015fti"
    ],
    "wof:name":"Stroiesti",
    "wof:placetype":"locality"
},
  "geometry": {"coordinates":[28.93327,47.88944],"type":"Point"}
}