{
  "type": "Feature",
  "properties": {
    "gn:admin1_code":"73.0",
    "gn:asciiname":"Ciubara",
    "gn:country_code":"MD",
    "gn:dem":188,
    "gn:feature_class":"P",
    "gn:feature_code":"PPL",
    "gn:name":"Ciubara",
    "gn:population":0,
    "gn:timezone":"Europe/Chisinau",
    "iso:country":"MD",
    "name:rus_x_preferred":[
        "\u0427\u0443\u0431\u0430\u0440\u0430"
    ],
    "name:und_x_variant":[
        "Chubara",
        "Ciubara"
    ],
    "wof:name":"Ciubara",
    "wof:placetype":"locality"
},
  "geometry": {"coordinates":[27.53921,48.07637],"type":"Point"}
}