{
  "type": "Feature",
  "properties": {
    "gn:admin1_code":"76.0",
    "gn:asciiname":"Lipovat",
    "gn:country_code":"MD",
    "gn:dem":111,
    "gn:feature_class":"P",
    "gn:feature_code":"PPL",
    "gn:name":"Lipov\u0103\u0163",
    "gn:population":0,
    "gn:timezone":"Europe/Chisinau",
    "iso:country":"MD",
    "name:rus_x_preferred":[
        "\u041b\u0438\u043f\u043e\u0432\u0435\u0446"
    ],
    "name:und_x_variant":[
        "Lipovets",
        "Lipov\u0103\u0163"
    ],
    "wof:name":"Lipovat",
    "wof:placetype":"locality"
},
  "geometry": {"coordinates":[27.36787,47.72645],"type":"Point"}
}