{
  "type": "Feature",
  "properties": {
    "gn:admin1_code":"81.0",
    "gn:asciiname":"Grinauti-Moldova",
    "gn:country_code":"MD",
    "gn:dem":212,
    "gn:feature_class":"P",
    "gn:feature_code":"PPL",
    "gn:name":"Grin\u0103u\u0163i-Moldova",
    "gn:population":0,
    "gn:timezone":"Europe/Chisinau",
    "iso:country":"MD",
    "name:ita_x_preferred":[
        "Grin\u0103u\u021bi-Moldova"
    ],
    "name:ron_x_preferred":[
        "Comuna Grin\u0103u\u021bi-Moldova"
    ],
    "name:rus_x_preferred":[
        "\u0413\u0440\u0438\u043d\u0430\u0443\u0446\u044b-\u041c\u043e\u043b\u0434\u043e\u0432\u0430"
    ],
    "name:und_x_variant":[
        "Grinautsy-Moldova",
        "Grin\u0103u\u0163i-Moldova"
    ],
    "wof:name":"Grinauti-Moldova",
    "wof:placetype":"locality"
},
  "geometry": {"coordinates":[27.45069,48.28034],"type":"Point"}
}