{
  "type": "Feature",
  "properties": {
    "gn:admin1_code":"84.0",
    "gn:asciiname":"Balanu Nou",
    "gn:country_code":"MD",
    "gn:dem":185,
    "gn:feature_class":"P",
    "gn:feature_code":"PPL",
    "gn:name":"B\u0103lanu Nou",
    "gn:population":0,
    "gn:timezone":"Europe/Chisinau",
    "iso:country":"MD",
    "name:rus_x_preferred":[
        "\u041d\u043e\u0432\u044b\u0439 \u0411\u0430\u043b\u0430\u043d"
    ],
    "name:und_x_variant":[
        "Novyy Balan",
        "Balanul Nou",
        "B\u0103lanu Nou"
    ],
    "wof:name":"Balanu Nou",
    "wof:placetype":"locality"
},
  "geometry": {"coordinates":[27.50147,47.96116],"type":"Point"}
}