{
  "type": "Feature",
  "properties": {
    "gn:admin1_code":"82.0",
    "gn:asciiname":"Tirzieni",
    "gn:country_code":"MD",
    "gn:dem":43,
    "gn:feature_class":"P",
    "gn:feature_code":"PPL",
    "gn:name":"T\u00eerzieni",
    "gn:population":0,
    "gn:timezone":"Europe/Chisinau",
    "iso:country":"MD",
    "name:rus_x_preferred":[
        "\u0422\u044b\u0440\u0437\u0438\u0435\u043d\u044b"
    ],
    "name:und_x_variant":[
        "Tyrziyen\u2019",
        "Tyrziyeny",
        "T\u00eerzieni"
    ],
    "wof:name":"Tirzieni",
    "wof:placetype":"locality"
},
  "geometry": {"coordinates":[28.62516,47.44349],"type":"Point"}
}