{
  "type": "Feature",
  "properties": {
    "iso:country":"MD",
    "name:ceb_x_preferred":[
        "Izvoare"
    ],
    "name:dan_x_preferred":[
        "Izvoare"
    ],
    "name:deu_x_preferred":[
        "Izvoare"
    ],
    "name:eng_x_preferred":[
        "Izvory"
    ],
    "name:eng_x_variant":[
        "Isvoarele",
        "Izvoarele",
        "Izvoare"
    ],
    "name:eus_x_preferred":[
        "Izvoare"
    ],
    "name:fra_x_preferred":[
        "Izvoare"
    ],
    "name:ita_x_preferred":[
        "Izvoare"
    ],
    "name:kat_x_preferred":[
        "\u10d8\u10d6\u10d5\u10dd\u10d0\u10e0\u10d4"
    ],
    "name:nld_x_preferred":[
        "Izvoare"
    ],
    "name:nno_x_preferred":[
        "Izvoare"
    ],
    "name:nob_x_preferred":[
        "Izvoare"
    ],
    "name:pol_x_preferred":[
        "Izvoare"
    ],
    "name:por_x_preferred":[
        "Izvoare"
    ],
    "name:ron_x_preferred":[
        "Izvoare"
    ],
    "name:ron_x_variant":[
        "Comuna Pruteni"
    ],
    "name:rus_x_preferred":[
        "\u0418\u0437\u0432\u043e\u0430\u0440\u0435"
    ],
    "name:rus_x_variant":[
        "\u0418\u0437\u0432\u043e\u0440\u044b"
    ],
    "name:spa_x_preferred":[
        "Izvoare"
    ],
    "name:swe_x_preferred":[
        "Izvoare"
    ],
    "name:ukr_x_preferred":[
        "\u0406\u0437\u0432\u043e\u0430\u0440\u0435"
    ],
    "name:und_x_preferred":[
        "Izvoare"
    ],
    "name:unk_x_variant":[
        "Izvory"
    ],
    "qs:a0":"Moldova",
    "qs:a1":"*F\u0103le\u015fti",
    "qs:a1_alt":"Falesti",
    "qs:a1r":"0",
    "qs:adm0":"Moldova",
    "qs:la_lc":"*",
    "qs:level":"locality",
    "qs:loc":"Izvoare",
    "qs:loc_alt":"Izvoare",
    "qs:pop":0,
    "qs:type":"buffered point",
    "wd:wordcount":35,
    "wof:lang":[
        "unk"
    ],
    "wof:name":"Izvoare",
    "wof:placetype":"locality"
},
  "geometry": {"coordinates":[27.666771,47.435147],"type":"Point"}
}