{
  "type": "Feature",
  "properties": {
    "iso:country":"MD",
    "name:ceb_x_preferred":[
        "Copceac"
    ],
    "name:dan_x_preferred":[
        "Copceac"
    ],
    "name:deu_x_preferred":[
        "Copceac"
    ],
    "name:eng_x_preferred":[
        "Kopchak"
    ],
    "name:eng_x_variant":[
        "Copceac"
    ],
    "name:eus_x_preferred":[
        "Copceac"
    ],
    "name:fra_x_preferred":[
        "Copceac"
    ],
    "name:ita_x_preferred":[
        "Copceac"
    ],
    "name:kat_x_preferred":[
        "\u10d9\u10dd\u10de\u10e9\u10d0\u10d9\u10d8"
    ],
    "name:nld_x_preferred":[
        "Copceac"
    ],
    "name:nno_x_preferred":[
        "Copceac"
    ],
    "name:nob_x_preferred":[
        "Copceac"
    ],
    "name:pol_x_preferred":[
        "Copceac"
    ],
    "name:por_x_preferred":[
        "Copceac"
    ],
    "name:ron_x_preferred":[
        "Copceac"
    ],
    "name:ron_x_variant":[
        "Comuna Lozova"
    ],
    "name:rus_x_preferred":[
        "\u041a\u043e\u043f\u0447\u0430\u043a"
    ],
    "name:spa_x_preferred":[
        "Copceac"
    ],
    "name:swe_x_preferred":[
        "Copceac"
    ],
    "name:ukr_x_preferred":[
        "\u041a\u043e\u043f\u0447\u0430\u043a"
    ],
    "qs:a0":"Moldova",
    "qs:a1":"*\u015etefan Vod\u0103",
    "qs:a1_alt":"Stefan Voda",
    "qs:a1r":"0",
    "qs:adm0":"Moldova",
    "qs:la_lc":"*",
    "qs:level":"locality",
    "qs:loc":"Copceac",
    "qs:loc_alt":"Copceac",
    "qs:pop":0,
    "qs:type":"buffered point",
    "wd:wordcount":23,
    "wof:lang":[
        "unk"
    ],
    "wof:name":"Copceac",
    "wof:placetype":"locality"
},
  "geometry": {"coordinates":[29.523873,46.450729],"type":"Point"}
}