{
  "type": "Feature",
  "properties": {
    "gn:admin1_code":"82.0",
    "gn:asciiname":"Pelivan",
    "gn:country_code":"MD",
    "gn:dem":88,
    "gn:feature_class":"P",
    "gn:feature_code":"PPL",
    "gn:name":"Pelivan",
    "gn:population":0,
    "gn:timezone":"Europe/Chisinau",
    "iso:country":"MD",
    "name:eng_x_preferred":[
        "Pelivan"
    ],
    "name:ita_x_preferred":[
        "Pelivan"
    ],
    "name:ron_x_preferred":[
        "Pelivan"
    ],
    "name:ron_x_variant":[
        "Comuna Pelivan"
    ],
    "wof:name":"Pelivan",
    "wof:placetype":"locality"
},
  "geometry": {"coordinates":[28.7786,47.4078],"type":"Point"}
}