{
  "type": "Feature",
  "properties": {
    "iso:country":"MD",
    "name:eng_x_preferred":[
        "Lozovo"
    ],
    "name:ita_x_preferred":[
        "Lozova"
    ],
    "name:ron_x_preferred":[
        "Lozova"
    ],
    "name:rus_x_preferred":[
        "\u041b\u043e\u0437\u043e\u0432\u0430"
    ],
    "name:rus_x_variant":[
        "\u041b\u043e\u0437\u043e\u0432\u043e"
    ],
    "name:spa_x_preferred":[
        "Lozova"
    ],
    "name:ukr_x_preferred":[
        "\u041b\u043e\u0437\u043e\u0432\u0430"
    ],
    "name:und_x_preferred":[
        "Lozova"
    ],
    "name:unk_x_variant":[
        "Lozovo"
    ],
    "qs:a0":"Moldova",
    "qs:a1":"*Str\u0103\u015feni",
    "qs:a1_alt":"Straseni",
    "qs:a1r":"0",
    "qs:adm0":"Moldova",
    "qs:la_lc":"*",
    "qs:level":"locality",
    "qs:loc":"Lozova",
    "qs:loc_alt":"Lozova",
    "qs:pop":0,
    "qs:type":"buffered point",
    "wd:wordcount":34,
    "wof:lang":[
        "unk"
    ],
    "wof:name":"Lozova",
    "wof:placetype":"locality"
},
  "geometry": {"coordinates":[28.387028,47.129055],"type":"Point"}
}