{
  "type": "Feature",
  "properties": {
    "gn:admin1_code":"69.0",
    "gn:asciiname":"Pascani",
    "gn:country_code":"MD",
    "gn:dem":82,
    "gn:feature_class":"P",
    "gn:feature_code":"PPL",
    "gn:name":"Pa\u015fcani",
    "gn:population":0,
    "gn:timezone":"Europe/Chisinau",
    "iso:country":"MD",
    "name:rus_x_preferred":[
        "\u041f\u0430\u0448\u043a\u0430\u043d\u044b"
    ],
    "name:und_x_variant":[
        "Pashkan\u2019",
        "Pashkani",
        "Pashkany",
        "Pa\u015fcani"
    ],
    "wof:name":"Pascani",
    "wof:placetype":"locality"
},
  "geometry": {"coordinates":[28.8325,47.16967],"type":"Point"}
}