{
  "type": "Feature",
  "properties": {
    "iso:country":"MD",
    "name:ceb_x_preferred":[
        "Vladimirovca"
    ],
    "name:dan_x_preferred":[
        "Vladimirovca"
    ],
    "name:deu_x_preferred":[
        "Vladimirovca"
    ],
    "name:eng_x_preferred":[
        "Vladimirovca"
    ],
    "name:eus_x_preferred":[
        "Vladimirovca"
    ],
    "name:fra_x_preferred":[
        "Vladimirovca"
    ],
    "name:ita_x_preferred":[
        "Vladimirovca"
    ],
    "name:nld_x_preferred":[
        "Vladimirovca"
    ],
    "name:nno_x_preferred":[
        "Vladimirovca"
    ],
    "name:nob_x_preferred":[
        "Vladimirovca"
    ],
    "name:pol_x_preferred":[
        "Vladimirovca"
    ],
    "name:por_x_preferred":[
        "Vladimirovca"
    ],
    "name:ron_x_preferred":[
        "Vladimirovca"
    ],
    "name:rus_x_preferred":[
        "\u0412\u043b\u0430\u0434\u0438\u043c\u0438\u0440\u043e\u0432\u043a\u0430"
    ],
    "name:spa_x_preferred":[
        "Vladimirovca"
    ],
    "name:swe_x_preferred":[
        "Vladimirovca"
    ],
    "name:tur_x_preferred":[
        "Vladimirovca"
    ],
    "name:ukr_x_preferred":[
        "\u0412\u043e\u043b\u043e\u0434\u0438\u043c\u0438\u0440\u0456\u0432\u043a\u0430"
    ],
    "name:ukr_x_variant":[
        "\u0413\u043b\u0438\u043d\u043d\u0435"
    ],
    "name:unk_x_variant":[
        "Vladimirovka"
    ],
    "qs:a0":"Moldova",
    "qs:a1":"*UAT din St\u00eenga Nistrului",
    "qs:a1_alt":"Unitatile administrativ-teritoriale din stinga Nistrului",
    "qs:a1r":"0",
    "qs:adm0":"Moldova",
    "qs:la_lc":"*",
    "qs:level":"locality",
    "qs:loc":"Vladimirovca",
    "qs:loc_alt":"Vladimirovca",
    "qs:pop":0,
    "qs:type":"buffered point",
    "wd:wordcount":80,
    "wof:name":"Vladimirovca",
    "wof:placetype":"locality"
},
  "geometry": {"coordinates":[29.793857,46.836689],"type":"Point"}
}