{
  "type": "Feature",
  "properties": {
    "gn:admin1_code":"92.0",
    "gn:asciiname":"Rezina",
    "gn:country_code":"MD",
    "gn:dem":118,
    "gn:feature_class":"P",
    "gn:feature_code":"PPL",
    "gn:name":"Rezina",
    "gn:population":0,
    "gn:timezone":"Europe/Chisinau",
    "iso:country":"MD",
    "name:bak_x_preferred":[
        "\u0420\u0435\u0437\u0438\u043d\u0430"
    ],
    "name:bel_x_preferred":[
        "\u0420\u044d\u0437\u0456\u043d\u0430"
    ],
    "name:bul_x_preferred":[
        "\u0420\u0435\u0437\u0438\u043d\u0430"
    ],
    "name:ceb_x_preferred":[
        "Rezina"
    ],
    "name:crh_x_preferred":[
        "Rezina"
    ],
    "name:fin_x_preferred":[
        "Rezina"
    ],
    "name:fra_x_preferred":[
        "Rezina"
    ],
    "name:hsb_x_preferred":[
        "Rezina"
    ],
    "name:ita_x_preferred":[
        "Rezina"
    ],
    "name:kor_x_preferred":[
        "\ub808\uc9c0\ub098"
    ],
    "name:lit_x_preferred":[
        "Rezina"
    ],
    "name:nld_x_preferred":[
        "Rezina"
    ],
    "name:pnb_x_preferred":[
        "\u0631\u06cc\u0632\u06cc\u0646\u0627"
    ],
    "name:pol_x_preferred":[
        "Rezina"
    ],
    "name:ron_x_preferred":[
        "Rezina"
    ],
    "name:rus_x_preferred":[
        "\u0420\u0435\u0437\u0438\u043d\u0430"
    ],
    "name:sah_x_preferred":[
        "\u0420\u0435\u0437\u0438\u043d\u0430"
    ],
    "name:spa_x_preferred":[
        "Rezina"
    ],
    "name:srp_x_preferred":[
        "\u0420\u0435\u0437\u0438\u043d\u0430"
    ],
    "name:swe_x_preferred":[
        "Rezina"
    ],
    "name:ukr_x_preferred":[
        "\u0420\u0435\u0437\u0438\u043d\u0430"
    ],
    "name:zho_x_preferred":[
        "\u96f7\u6fdf\u7d0d"
    ],
    "wof:name":"Rezina",
    "wof:placetype":"locality"
},
  "geometry": {"coordinates":[27.87646,47.21578],"type":"Point"}
}