{
  "type": "Feature",
  "properties": {
    "gn:admin1_code":"92.0",
    "gn:asciiname":"Rezina",
    "gn:country_code":"MD",
    "gn:dem":118,
    "gn:feature_class":"P",
    "gn:feature_code":"PPL",
    "gn:name":"Rezina",
    "gn:population":0,
    "gn:timezone":"Europe/Chisinau",
    "iso:country":"MD",
    "name:ron_x_preferred":[
        "Rezina"
    ],
    "wof:name":"Rezina",
    "wof:placetype":"locality"
},
  "geometry": {"coordinates":[27.87646,47.21578],"type":"Point"}
}