{
  "type": "Feature",
  "properties": {
    "iso:country":"MD",
    "name:ceb_x_preferred":[
        "B\u0103lceana"
    ],
    "name:dan_x_preferred":[
        "B\u0103lceana"
    ],
    "name:deu_x_preferred":[
        "B\u0103lceana"
    ],
    "name:eng_x_preferred":[
        "B\u0103lceana"
    ],
    "name:eus_x_preferred":[
        "B\u0103lceana"
    ],
    "name:fra_x_preferred":[
        "B\u0103lceana"
    ],
    "name:ita_x_preferred":[
        "B\u0103lceana"
    ],
    "name:kat_x_preferred":[
        "\u10d1\u10d4\u10da\u10e9\u10d0\u10dc\u10d0"
    ],
    "name:nld_x_preferred":[
        "B\u0103lceana"
    ],
    "name:nno_x_preferred":[
        "B\u0103lceana"
    ],
    "name:nob_x_preferred":[
        "B\u0103lceana"
    ],
    "name:pol_x_preferred":[
        "B\u0103lceana"
    ],
    "name:por_x_preferred":[
        "B\u0103lceana"
    ],
    "name:ron_x_preferred":[
        "B\u0103lceana"
    ],
    "name:rus_x_preferred":[
        "\u0411\u043e\u043b\u0447\u0430\u043d\u044b"
    ],
    "name:spa_x_preferred":[
        "B\u0103lceana"
    ],
    "name:swe_x_preferred":[
        "B\u0103lceana"
    ],
    "name:ukr_x_preferred":[
        "\u0411\u0435\u043b\u0447\u0430\u043d\u0430"
    ],
    "name:ukr_x_variant":[
        "\u0413\u0443\u0440\u0430-\u0413\u0430\u043b\u0431\u0435\u043d\u0435\u0439"
    ],
    "name:unk_x_variant":[
        "Bolchany"
    ],
    "qs:a0":"Moldova",
    "qs:a1":"*H\u00eence\u015fti",
    "qs:a1_alt":"Hincesti",
    "qs:a1r":"0",
    "qs:adm0":"Moldova",
    "qs:la_lc":"*",
    "qs:level":"locality",
    "qs:loc":"B\u0103lceana",
    "qs:loc_alt":"Balceana",
    "qs:pop":0,
    "qs:type":"buffered point",
    "wd:wordcount":69,
    "wof:name":"B\u0103lceana",
    "wof:placetype":"locality"
},
  "geometry": {"coordinates":[28.406482,46.846557],"type":"Point"}
}