{
  "type": "Feature",
  "properties": {
    "gn:admin1_code":"91.0",
    "gn:asciiname":"Ordasei",
    "gn:country_code":"MD",
    "gn:dem":78,
    "gn:feature_class":"P",
    "gn:feature_code":"PPL",
    "gn:name":"Ord\u0103\u015fei",
    "gn:population":0,
    "gn:timezone":"Europe/Chisinau",
    "iso:country":"MD",
    "name:rus_x_preferred":[
        "\u041e\u0440\u0434\u0430\u0448\u0435\u0439"
    ],
    "name:und_x_variant":[
        "Ordeshei",
        "Ordashey",
        "Ord\u0103\u015fei"
    ],
    "wof:name":"Ordasei",
    "wof:placetype":"locality"
},
  "geometry": {"coordinates":[28.49824000000001,47.68507],"type":"Point"}
}