{
  "type": "Feature",
  "properties": {
    "gn:admin1_code":"77.0",
    "gn:asciiname":"Rusestii Vechi",
    "gn:country_code":"MD",
    "gn:dem":155,
    "gn:feature_class":"P",
    "gn:feature_code":"PPL",
    "gn:name":"Ruse\u015ftii Vechi",
    "gn:population":0,
    "gn:timezone":"Europe/Chisinau",
    "iso:country":"MD",
    "name:rus_x_preferred":[
        "\u0421\u0442\u0430\u0440\u044b\u0435 \u0420\u0443\u0441\u0435\u0448\u0442\u044b"
    ],
    "name:und_x_variant":[
        "Ruseshti-Vek\u2019",
        "Staryye Ruseshty",
        "Velikiye Ruseshty",
        "Ruse\u015ftii Vechi"
    ],
    "wof:name":"Rusestii Vechi",
    "wof:placetype":"locality"
},
  "geometry": {"coordinates":[28.62523,46.91943],"type":"Point"}
}