{
  "type": "Feature",
  "properties": {
    "iso:country":"MD",
    "name:eng_x_preferred":[
        "Yalpuzhen'"
    ],
    "name:eng_x_variant":[
        "Yalpuzheny"
    ],
    "name:rus_x_preferred":[
        "\u041f\u0435\u0440\u0432\u043e\u043c\u0430\u0439\u0441\u043a"
    ],
    "name:und_x_preferred":[
        "Ialpugeni"
    ],
    "name:unk_x_variant":[
        "Pervomaysk"
    ],
    "qs:a0":"Moldova",
    "qs:a1":"*Cimi\u015flia",
    "qs:a1_alt":"Cimislia",
    "qs:a1r":"0",
    "qs:adm0":"Moldova",
    "qs:la_lc":"*",
    "qs:level":"locality",
    "qs:loc":"Ialpugeni",
    "qs:loc_alt":"Ialpugeni",
    "qs:pop":0,
    "qs:type":"buffered point",
    "wd:wordcount":473,
    "wof:lang":[
        "unk"
    ],
    "wof:name":"Ialpugeni",
    "wof:placetype":"locality"
},
  "geometry": {"coordinates":[28.621649,46.57761],"type":"Point"}
}